Workbook

Sheet initial_search
A1: Publication Type | B1: Authors | C1: Book Authors | D1: Book Editors | E1: Book Group Authors | F1: Author Full Names | G1: Book Author Full Names | H1: Group Authors | I1: Article Title | J1: Source Title | K1: Book Series Title | L1: Book Series Subtitle | M1: Language | N1: Document Type | O1: Conference Title | P1: Conference Date | Q1: Conference Location | R1: Conference Sponsor | S1: Conference Host | T1: Author Keywords | U1: Keywords Plus | V1: Abstract | W1: Addresses | X1: Affiliations | Y1: Reprint Addresses | Z1: Email Addresses | AA1: Researcher Ids | AB1: ORCIDs | AC1: Funding Orgs | AD1: Funding Name Preferred | AE1: Funding Text | AF1: Cited References | AG1: Cited Reference Count | AH1: Times Cited, WoS Core | AI1: Times Cited, All Databases | AJ1: 180 Day Usage Count | AK1: Since 2013 Usage Count | AL1: Publisher | AM1: Publisher City | AN1: Publisher Address | AO1: ISSN | AP1: eISSN | AQ1: ISBN | AR1: Journal Abbreviation | AS1: Journal ISO Abbreviation | AT1: Publication Date | AU1: Publication Year | AV1: Volume | AW1: Issue | AX1: Part Number | AY1: Supplement | AZ1: Special Issue | BA1: Meeting Abstract | BB1: Start Page | BC1: End Page | BD1: Article Number | BE1: DOI | BF1: DOI Link | BG1: Book DOI | BH1: Early Access Date | BI1: Number of Pages | BJ1: WoS Categories | BK1: Web of Science Index | BL1: Research Areas | BM1: IDS Number | BN1: Pubmed Id | BO1: Open Access Designations | BP1: Highly Cited Status | BQ1: Hot Paper Status | BR1: Date of Export | BS1: UT (Unique WOS ID) | BT1: Web of Science Record
A2: J | B2: Li, X; Xu, F; Zhang, C; Che, T; Dai, LY; Zhang, YL | F2: Li, Xuan; Xu, Fan; Zhang, Chen; Che, Tao; Dai, Liyun; Zhang, Yanli | I2: Estimation of snow depth from AMSR-2 based on an AutoML method over the Qinghai-Tibet Plateau | J2: CRYOSPHERE | V2: Snow depth is a crucial parameter for describing the spatiotemporal variations of snow cover, and passive microwave snow depth products (10-25 km) are widely used for monitoring snow depth changes. However, as one of the three major snow-covered regions in China, the Qinghai-Tibet Plateau has complex terrain and rapid changes in snow cover with strong spatial heterogeneity, making it difficult for coarse-resolution snow depth products to accurately describe its spatiotemporal characteristics. This study proposes a high spatial resolution (500 m) snow depth estimation method based on the Advanced Microwave Scanning Radiometer 2 (AMSR-2) brightness temperature data and Automated Machine Learning. Firstly, using Pearson correlation coefficients, 19 key factors influencing snow depth, including AMSR-2 brightness temperature, slope, and surface roughness, were selected as input data (independent variables) for Automated Machine Learning. Meanwhile, passive microwave downscaled snow depth data and ground-based snow depth measurements were introduced as dependent variables for Automated Machine Learning. The Automated Machine Learning model was then trained separately for four different types of snow cover surfaces (forest, grassland, water, and bare land). Finally, through ten-fold cross-validation, the optimal machine learning model for snow depth estimation under each type of underlying surface coverage was selected, thus generating sequential snow depth datasets for the ten-year snow cover period of the Qinghai-Tibet Plateau from 2012 to 2021. Results show that (1) the estimated snow depth values well with ground-based observations, yielding a coefficient of determination (R-2) of 0.71 and a root mean square error (RMSE) of 3.64 cm, indicating high estimation accuracy. (2) Snow depth estimation demonstrates the highest accuracy in unused land (CatBoost, R-2 = 0.82), followed by grassland (CatBoost, R-2 = 0.77, RMSE = 3.11 cm), water (ET, R-2 = 0.75, RMSE = 2.20 cm), and forest (XGBoost, R-2 = 0.71, RMSE = 3.30 cm). (3) A comparison with snow cover extent derived from Landsat-8 optical imagery reveals that the estimated snow depth spatial distribution is consistent with snow cover extent, providing reliable data for monitoring snow cover changes in mountainous regions. | AO2: 1994-0416 | AP2: 1994-0424 | AU2: 2026 | AV2: 20 | AW2: 5 | BB2: 2977 | BC2: 2997 | BE2: 10.5194/tc-20-2977-2026 | BF2: =HYPERLINK("http://dx.doi.org/10.5194/tc-20-2977-2026","http://dx.doi.org/10.5194/tc-20-2977-2026") -> http://dx.doi.org/10.5194/tc-20-2977-2026 | BH2: MAY 2026 | BS2: WOS:001772482400001 | BT2: =HYPERLINK("https%3A%2F%2Fwww.webofscience.com%2Fwos%2Fwoscc%2Ffull-record%2FWOS:001772482400001","View Full Record in Web of Science") -> View Full Record in Web of Science
A3: J | B3: Ying, JJ; Yang, JW; Jiang, LM; Pan, JM; Xiong, C | F3: Ying, Jiajie; Yang, Jianwei; Jiang, Lingmei; Pan, Jinmei; Xiong, Chuan | I3: Scale patterns of the Sentinel-1 SAR-based snow depth product compared with station measurements and airborne LiDAR observations | J3: CRYOSPHERE | V3: Water storage in snowpacks in mountainous areas is critical for hydropower production, hydrological forecasting, and freshwater availability. Spaceborne synthetic aperture radar (SAR) is a powerful tool for quantitatively measuring snow mass because of its high spatial resolution and signal sensitivity to snow depth (SD). In particular, the first SAR SD product (C-snow) based on Sentinel-1 satellites displays high sensitivity to depolarization signals for dynamic SD monitoring in mountainous areas. Moreover, upscaled C-snow retrievals (e.g., 10 and 25 km) have been used to provide reference data to train machine learning models, improve passive microwave-based retrieval, and calibrate many hydrological models. However, to date, a systematic assessment of C-snow products at various scales has not been conducted. In this study, the performance of C-snow products at three scales (1, 10 and 25 km) is compared via station-based measurements and airborne LiDAR observations, and the scale patterns associated with the heterogeneity of the geographic environment and the representativeness of so-called true data are analyzed. The scale patterns of C-snow products vary across resolutions. They differ from the patterns observed in the station and airborne reference data. As the spatial scale increases from 1 to 25 km, the error of C-snow retrieval in reference to station measurements tends to increase (e.g., ubRMSE from 69.43 to 81.87 cm; bias from -8.89 to 11.66 cm), whereas it tends to decrease compared with Airborne Snow Observatory (ASO) data, with ubRMSE values ranging from 104.3 to 83.29 cm and bias values ranging from -91.31 to -52.73 cm. We also found that land cover types, e.g., tree cover and permanent ice, affect the C-snow product at various scales. Overestimation tends to occur in coarse pixels covered with even a small amount of permanent ice. The findings indicate that C-snow retrieval at three scales is characterized by high uncertainty. Therefore, researchers should focus on developing a robust SD retrieval algorithm by combining SAR backscattering signals and polarimetric and interferometric information. | AA3: ; Jiang, Lingmei/L-6099-2016 | AB3: 熊, 川/0000-0001-9164-4810; | AO3: 1994-0416 | AP3: 1994-0424 | AT3: JAN 14 | AU3: 2026 | AV3: 20 | AW3: 1 | BB3: 227 | BC3: 244 | BE3: 10.5194/tc-20-227-2026 | BF3: =HYPERLINK("http://dx.doi.org/10.5194/tc-20-227-2026","http://dx.doi.org/10.5194/tc-20-227-2026") -> http://dx.doi.org/10.5194/tc-20-227-2026 | BS3: WOS:001660928400001 | BT3: =HYPERLINK("https%3A%2F%2Fwww.webofscience.com%2Fwos%2Fwoscc%2Ffull-record%2FWOS:001660928400001","View Full Record in Web of Science") -> View Full Record in Web of Science
A4: J | B4: Bai, YN; Li, Z; Zhang, P; Zeng, JY; Huang, L; Qiao, HW; Gao, S; Hu, HD | F4: Bai, Yanan; Li, Zhen; Zhang, Ping; Zeng, Jiangyuan; Huang, Lei; Qiao, Haiwei; Gao, Shuo; Hu, Huadong | I4: A Snow Depth Retrieval Method Based on Super-Resolution Brightness Temperature Reconstruction and Multimodal Feature Synergy | J4: IEEE TRANSACTIONS ON GEOSCIENCE AND REMOTE SENSING | V4: Snow plays a critical role in the hydrological ecosystem of the Tibetan Plateau (TP), influencing both regional water availability and climate dynamics. Passive microwave remote sensing is a powerful tool for large-scale continuous snow depth (SD) monitoring, yet the low spatial resolution and saturation limitation of brightness temperature (TB) make it difficult for a single passive microwave dataset to address the challenges posed by the complex topography and fragmented snow distribution on the TP. To address this issue, an area-to-point downscaled daily SD retrieval method that accounts for spatial heterogeneity was proposed in this study using multimodal remote sensing data. First, we developed a new algorithm to reconstruct the high-resolution TB from Advanced Microwave Scanning Radiometer 2 (AMSR2), considering the effects of snow and land cover types. The recursive feature elimination (RFE) was used to select the optimal subset of features, including active and passive remote sensing information, meteorological data, and geographic factors, and then a multimodal feature-driven convolutional neural network (CNN)-long short-term memory network (LSTM) was used to retrieve daily 500-m SD data. The method effectively captures the dynamic spatial variation features of SD. The validation of the proposed TB reconstruction downscaling method using the enhanced-resolution TB data showed the RMSE ranged from 2.65 to 6.81 K at different frequencies. The contribution of multimodal features was analyzed based on SHapley Additive exPlanations (SHAP) values. Snow cover accumulation (SCA), H-pol TB at 89 GHz, and latitude were key features, although the relative contributions of these features varied significantly across different environments. In the site-based independent validation, the RMSE of the proposed method was 2.33 cm, demonstrating better accuracy than existing SD retrieval methods in the TP. The use of multimodal features improved accuracy by 1.67 cm (41.7%) compared to passive microwave features only. The proposed SD retrieval algorithm can obtain high-resolution and high-precision SD information, thereby supporting water resource management and climate change monitoring over the TP. | AA4: Zeng, Jiangyuan/AAJ-8512-2020 | AO4: 0196-2892 | AP4: 1558-0644 | AU4: 2026 | AV4: 64 | BD4: 4300615 | BE4: 10.1109/TGRS.2026.3653456 | BF4: =HYPERLINK("http://dx.doi.org/10.1109/TGRS.2026.3653456","http://dx.doi.org/10.1109/TGRS.2026.3653456") -> http://dx.doi.org/10.1109/TGRS.2026.3653456 | BS4: WOS:001708259200007 | BT4: =HYPERLINK("https%3A%2F%2Fwww.webofscience.com%2Fwos%2Fwoscc%2Ffull-record%2FWOS:001708259200007","View Full Record in Web of Science") -> View Full Record in Web of Science
A5: J | B5: Li, YX; Huang, XD; Ma, Y; Zhang, YH; Guo, QH; Liang, TG | F5: Li, Yuxin; Huang, Xiaodong; Ma, Ying; Zhang, Yonghui; Guo, Qianhao; Liang, Tiangang | I5: Persistent Reduction in Snow Mass Over China: Evidence From 40 Years of Satellite Observations | J5: IEEE TRANSACTIONS ON GEOSCIENCE AND REMOTE SENSING | V5: Snow water equivalent (SWE) serves as a key parameter for assessing snow hydrology, climate regulation, and water resource management. Despite its critical role, high spatiotemporal resolution SWE datasets remain limited, particularly for vast and topographically diverse regions such as China. Here, we present an innovative daily, 500-m resolution SWE dataset spanning 1980-2020 across China, developed through multisource remote sensing data fusion and machine learning (ML)-based downscaling. This dataset overcomes the spatiotemporal constraints inherent in conventional passive microwave (PMW) SWE retrievals. Validation with ground-based measurements yields an root mean square error (RMSE) of 10.85 mm, demonstrating its enhanced accuracy relative to existing products. Analysis of the dataset reveals a clear seasonal snow mass cycle in China, with a four-decade daily mean of 2.05 x 0(10) m(3) and peak values reaching 6.90 x 10(10) m(3) in January or February. Longitudinal trends indicate a significant and persistent decline in snow mass accumulation from 1980 to 2020. Furthermore, spatial variability analysis highlights marked regional differences in SWE trends during the snow season. This study advances the understanding of snow cover dynamics over China, offering a robust, highresolution SWE dataset with applications in snow hydrology, climate change studies, and water resource planning. | AA5: MA, Ying/KIB-0165-2024 | AO5: 0196-2892 | AP5: 1558-0644 | AU5: 2026 | AV5: 64 | BD5: 4300714 | BE5: 10.1109/TGRS.2026.3658511 | BF5: =HYPERLINK("http://dx.doi.org/10.1109/TGRS.2026.3658511","http://dx.doi.org/10.1109/TGRS.2026.3658511") -> http://dx.doi.org/10.1109/TGRS.2026.3658511 | BS5: WOS:001683260800023 | BT5: =HYPERLINK("https%3A%2F%2Fwww.webofscience.com%2Fwos%2Fwoscc%2Ffull-record%2FWOS:001683260800023","View Full Record in Web of Science") -> View Full Record in Web of Science
A6: J | B6: Brodylo, D; Bosche, LV; Busby, RR; Deeb, EJ; Douglas, TA; Lemmetyinen, J | F6: Brodylo, David; Bosche, Lauren V.; Busby, Ryan R.; Deeb, Elias J.; Douglas, Thomas A.; Lemmetyinen, Juha | I6: Object-based ensemble estimation of snow depth and snow water equivalent over multiple months in Sodankylä, Finland | J6: CRYOSPHERE | V6: Snowpack characteristics such as snow depth and snow water equivalent (SWE) are widely studied in regions prone to heavy snowfall and long winters. These features are measured in the field via manual or automated observations and over larger spatial scales with stand-alone remote sensing methods. However, individually these methods may struggle with accurately assessing snow depth and SWE in local spatial scales of several square kilometers. One method for leveraging the benefits of each individual dataset is to link field-based observations with high-resolution remote sensing imagery and then employ machine learning techniques to estimate snow depth and SWE across a broader geographic region. Here, we combined field-based repeat snow depth and SWE measurements over six instances from December 2022 to April 2023 in Sodankyl & auml;, Finland with Light Detection and Ranging (LiDAR) and WorldView-2 (WV-2) data to estimate snow depth, SWE, and snow density over a 10 km2 local scale study area. This was achieved with an object-based machine learning ensemble approach by first upscaling more numerous snow depth field data and then utilizing the estimated local scale snow depth to aid in estimating SWE over the study area. Snow density was then calculated from snow depth and SWE estimates. Snow depth peaked in March, SWE shortly after in early April, and snow density at the end of April. The ensemble-based approach had encouraging success with upscaling snow depth and SWE. Associations were also identified with carbon- and mineral-based forest surface soils, alongside dry and wet peatbogs. | AA6: Lemmetyinen, Juha/B-3739-2016; Brodylo, David/KVY-5799-2024 | AB6: Lemmetyinen, Juha/0000-0003-4434-9696; Brodylo, David/0000-0002-0331-2398 | AO6: 1994-0416 | AP6: 1994-0424 | AT6: NOV 24 | AU6: 2025 | AV6: 19 | AW6: 11 | BB6: 6127 | BC6: 6148 | BE6: 10.5194/tc-19-6127-2025 | BF6: =HYPERLINK("http://dx.doi.org/10.5194/tc-19-6127-2025","http://dx.doi.org/10.5194/tc-19-6127-2025") -> http://dx.doi.org/10.5194/tc-19-6127-2025 | BS6: WOS:001620513000001 | BT6: =HYPERLINK("https%3A%2F%2Fwww.webofscience.com%2Fwos%2Fwoscc%2Ffull-record%2FWOS:001620513000001","View Full Record in Web of Science") -> View Full Record in Web of Science
A7: J | B7: Kumawat, D; Ebtehaj, A; Kumar, S; Colliander, A | F7: Kumawat, Divya; Ebtehaj, Ardeshir; Kumar, Sujay; Colliander, Andreas | I7: Deep learning of seasonal peak snow water content of global boreal forest and arctic using spaceborne L-band radiometry | J7: REMOTE SENSING OF ENVIRONMENT | V7: Estimating peak snow water equivalent (SWE) across the Northern Hemisphere is critical for assessing seasonal water availability for both ecosystems and human needs. This study is the first to demonstrate a direct link between peak SWE and the temporal variability of L-band surface emission under a moderately dense vegetation canopy. We introduce SWEFormer, a novel deep transformer neural network that retrieves peak SWE primarily using time series of L-band brightness temperatures from NASA's Soil Moisture Active and Passive (SMAP) satellite. The model is trained using an incremental learning approach that transfers low-level information from reanalysis data for spatially coherent high-level learning from sparse in situ observations. SWEFormer outperforms leading global products, including ERA5, GlobSnow, and AMSR-based estimates, particularly in complex boreal watersheds, where previous global SWE estimates suffer from significant uncertainties, as vegetation canopy often markedly attenuates high-frequency microwave signatures of snowpack. | AA7: Kumar, Sujay/B-8142-2015; Colliander, Andreas/M-9864-2018; Kumawat, Divya/NAX-6725-2025 | AB7: Kumawat, Divya/0000-0002-7150-3954 | AO7: 0034-4257 | AP7: 1879-0704 | AT7: DEC 1 | AU7: 2025 | AV7: 330 | BD7: 114963 | BE7: 10.1016/j.rse.2025.114963 | BF7: =HYPERLINK("http://dx.doi.org/10.1016/j.rse.2025.114963","http://dx.doi.org/10.1016/j.rse.2025.114963") -> http://dx.doi.org/10.1016/j.rse.2025.114963 | BH7: AUG 2025 | BS7: WOS:001561289100003 | BT7: =HYPERLINK("https%3A%2F%2Fwww.webofscience.com%2Fwos%2Fwoscc%2Ffull-record%2FWOS:001561289100003","View Full Record in Web of Science") -> View Full Record in Web of Science
A8: J | B8: Demil, G; Haghighi, AT; Klove, B; Oussalah, M | F8: Demil, Getnet; Haghighi, Ali Torabi; Klove, Bjorn; Oussalah, Mourad | I8: Seeing through the clouds: enhanced snow and cloud segmentation in sentinel-2 imagery with mDeepLabV3+ | J8: EARTH SCIENCE INFORMATICS | V8: The application of satellite-based remote sensing has become increasingly prominent in snow hydrology parameter estimation, owing to its cost-efficiency, frequent revisit times, and broad spatial coverage. However, the presence of clouds introduces significant obstacles by obscuring features in optical satellite imagery. Differentiating snow from clouds remains challenging due to their similar color profiles and reflective properties. Conventional approaches, including manual thresholding, traditional machine learning techniques, and advanced deep learning models such as Convolutional Neural Networks (CNNs) and U-Net, have achieved only moderate success, despite remote sensing imagery's rich spatial and spectral data. To address this, we propose a novel deep-learning framework for classifying background, snow, and cloud regions in multispectral satellite imagery, based on a modified DeepLabV3+ architecture. Our approach incorporates an elevated dilation rate of 24 and leverages cross-domain transfer learning with ResNet-50 and ResNet-101 as backbone networks. Additionally, we utilized the Random Forest algorithm to evaluate the significance of spectral band features and support the semantic segmentation process. We also explored the impact of different input band combinations to determine the optimal configuration. Notably, the combination of Blue (Band 2), Short-Wave Infrared (Band 11), Red (Band 4), and Water Vapor (Band 9) with the ResNet-101 backbone outperformed all other tested configurations. This study provides a detailed assessment of the segmentation capabilities of modified DeepLabV3+ (mDeepLabV3+) models, using ResNet-50 (R50) and ResNet-101 (R101) backbones, on Sentinel-2 imagery for distinguishing cloud, snow, and background classes. Performance was benchmarked against established models, including Random Forest (RF), U-Net, and UCTNet, across various band combinations. Our results reveal that the mDeepLabV3+ model with the R50 backbone achieves exceptional precision (99.9%), F1 score (98.0%), and mean Intersection over Union (mIOU) of 91.13%, while the R101 variant excels in recall (97.8%) and overall accuracy (96.78%). These outcomes highlight the superior performance and reliability of the mDeepLabV3+ models for Sentinel-2 image segmentation. This work presents a robust and domain-adapted approach for snow and cloud segmentation in Sentinel-2 imagery, demonstrating improved accuracy over existing baselines. This thorough analysis offers critical insights into the efficacy of deep learning in such tasks, emphasizing opportunities for further refinement and practical implementation. | AA8: ; Haghighi, Ali/AAE-6862-2021 | AB8: Demil, Getnet/0009-0006-5158-0895; | AO8: 1865-0473 | AP8: 1865-0481 | AT8: JUL 28 | AU8: 2025 | AV8: 18 | AW8: 3 | BD8: 477 | BE8: 10.1007/s12145-025-01950-6 | BF8: =HYPERLINK("http://dx.doi.org/10.1007/s12145-025-01950-6","http://dx.doi.org/10.1007/s12145-025-01950-6") -> http://dx.doi.org/10.1007/s12145-025-01950-6 | BS8: WOS:001538089500001 | BT8: =HYPERLINK("https%3A%2F%2Fwww.webofscience.com%2Fwos%2Fwoscc%2Ffull-record%2FWOS:001538089500001","View Full Record in Web of Science") -> View Full Record in Web of Science
A9: J | B9: Cui, YR; Chen, SX; Mo, GQ; Ji, DB; Lv, LS; Fu, J | F9: Cui, Yurong; Chen, Sixuan; Mo, Guiquan; Ji, Dabin; Lv, Lansong; Fu, Juan | I9: Snow Depth Retrieval Using Sentinel-1 Radar Data: A Comparative Analysis of Random Forest and Support Vector Machine Models with Simulated Annealing Optimization | J9: REMOTE SENSING | V9: Snow plays a crucial role in global climate regulation, hydrological processes, and environmental change, making the accurate acquisition of snow depth data highly significant. In this study, we used Sentinel-1 radar data and employed a simulated annealing algorithm to select the optimal influencing factors from radar backscatter characteristics and spatiotemporal geographical parameters within the study area. Snow depth retrieval was subsequently performed using both random forest (RF) and Support Vector Machine (SVM) models. The retrieval results were validated against in situ measurements and compared with the long-term daily snow depth dataset of China for the period 2017-2019. The results indicate that the RF model achieves better agreement with the measured data than existing snow depth products. Specifically, in the Xinjiang region, the RF model demonstrates superior performance, with an R2 of 0.92, a root mean square error (RMSE) of 2.61 cm, and a mean absolute error (MAE) of 1.42 cm. In contrast, the SVM regression model shows weaker agreement with the observations, with an R2 lower than that of the existing snow depth product (0.51) in Xinjiang, and it performs poorly in other regions as well. Overall, the SVM model exhibits deficiencies in both predictive accuracy and spatial stability. This study provides a valuable reference for snow depth retrieval research based on active microwave remote sensing techniques. | AA9: Ji, Dabin/ADL-7793-2022 | AB9: 姬, 大彬/0000-0001-6388-2555 | AP9: 2072-4292 | AT9: JUL 24 | AU9: 2025 | AV9: 17 | AW9: 15 | BD9: 2584 | BE9: 10.3390/rs17152584 | BF9: =HYPERLINK("http://dx.doi.org/10.3390/rs17152584","http://dx.doi.org/10.3390/rs17152584") -> http://dx.doi.org/10.3390/rs17152584 | BS9: WOS:001549552300001 | BT9: =HYPERLINK("https%3A%2F%2Fwww.webofscience.com%2Fwos%2Fwoscc%2Ffull-record%2FWOS:001549552300001","View Full Record in Web of Science") -> View Full Record in Web of Science
A10: J | B10: Ying, J; Yang, J; Jiang, L; Pan, J; Zhang, C; Xiong, C; Shi, J | F10: Ying, J. J.; Yang, J. W.; Jiang, L. M.; Pan, J. M.; Zhang, C.; Xiong, C.; Shi, J. C. | I10: Evaluation of the Sentinel-1 SAR-based snow depth product over the Northern Hemisphere | J10: JOURNAL OF HYDROLOGY | V10: Active microwave remote sensing techniques, especially synthetic aperture radar (SAR), are valid tools for monitoring snow depth (SD) because of their high spatial resolution and day-night all-weather monitoring. The first SAR (C-band)-based SD product (C-snow), which covers all mountain ranges in the Northern Hemisphere, has been used as a reference dataset in many applications, such as building SD retrieval algorithms, acting as training samples for machine learning models, and improving passive microwave-based retrievals. However, the performance of the C-snow dataset over the Northern Hemisphere is unknown and remains to be evaluated. In this study, we integrated several ground-based SD datasets and also collected airborne lidar surveys (ASO) to assess the accuracy of C-snow SD retrievals. Moreover, we quantitatively analyzed the influence of various factors, such as landscape, terrain, dry/wet state, etc., on the SD retrievals. The results revealed that compared with ground-based SD measurements, the overall unbiased root mean square error (ubRMSE) and bias values of C-snow in the Northern Hemisphere ranged from 60.98 to 68.18 cm and-22.93 to-9.81 cm, respectively, with correlation coefficients ranging from 0.52 to 0.58. Compared with the ASO observations, the ubRMSE and bias were 107.2 cm and-91.72 cm, respectively. The performances of the C-snow product exhibited spatial differences due to the topography (elevation, terrain slope, and undulation), landcover types (especially ice and forest), wet snow and availability of time series Sentinel-1 observations (affecting the C-snow retrieval algorithm). Moreover, C-snow retrievals tend to underestimate the SD in the late snow season annually because of the decreasing snow index (SI) caused by wet snow or snow metamorphism, although the SD still increases. The performance analysis in this study will be useful for determining the dominant factors impacting SD retrievals, evaluating and building SD retrieval models, and understanding the spatiotemporal distribution and changes in snowpack in mountains. | AA10: ; Jiang, Lingmei/L-6099-2016 | AB10: 施, 建成/0000-0002-6163-2912; Jiang, Lingmei/0000-0002-9847-9034 | AO10: 0022-1694 | AP10: 1879-2707 | AT10: NOV | AU10: 2025 | AV10: 661 | AX10: A | BD10: 133593 | BE10: 10.1016/j.jhydrol.2025.133593 | BF10: =HYPERLINK("http://dx.doi.org/10.1016/j.jhydrol.2025.133593","http://dx.doi.org/10.1016/j.jhydrol.2025.133593") -> http://dx.doi.org/10.1016/j.jhydrol.2025.133593 | BH10: JUN 2025 | BS10: WOS:001504904400002 | BT10: =HYPERLINK("https%3A%2F%2Fwww.webofscience.com%2Fwos%2Fwoscc%2Ffull-record%2FWOS:001504904400002","View Full Record in Web of Science") -> View Full Record in Web of Science
A11: J | B11: Kesikoglu, MH | F11: Kesikoglu, Mustafa Hayri | I11: Enhancing Snow Detection through Deep Learning: Evaluating CNN Performance Against Machine Learning and Unsupervised Classification Methods | J11: WATER RESOURCES MANAGEMENT | V11: Snow cover is a crucial natural water resource that provides water storage. Monitoring snow cover is essential for sustainable water resource management. Accurate and efficient snow cover mapping is vital for water resource planning, flood control, and climate impact assessments. Remote sensing provides a cost-effective approach for monitoring snow cover dynamics, but classification accuracy remains a challenge. This study introduces a deep learning-based 1D convolutional neural network (1D CNN) approach for improved snow cover classification in mountainous regions utilizing Landsat 5 and 8 satellite images. The effectiveness of 1D CNN was compared with unsupervised classification (UC) methods (Normalized Difference Snow Index (NDSI), band ratio-based Red/Short wave infrared (R/SWIR), and Near infrared/Short wave infrared (NIR/SWIR)) and supervised machine learning classification methods (support vector machines (SVM) and classification and regression trees (CART)) in this research. The study was performed on Erciyes Mountain, Turkey, across four different years. Classifier performances were assessed using various quantitative (precision, recall, F-score, overall accuracy, kappa) and qualitative (mean squared error, Pearson correlation coefficient, structural similarity index measure, peak signal-to-noise ratio) evaluation metrics. Pairwise statistical analysis using McNemar's test revealed significant differences between 1D CNN and the other classifiers. The findings demonstrated that the 1D CNN approach outperformed all other methods in achieving the highest accuracy in snow cover classification. These results indicate the potential of deep learning for enhancing snow cover assessment and supporting more effective water resource management strategies and policy-making. | AA11: Kesikoglu, Mustafa Hayri/AAL-1358-2020 | AB11: Kesikoglu, Mustafa Hayri/0000-0001-5199-0815 | AO11: 0920-4741 | AP11: 1573-1650 | AT11: SEP | AU11: 2025 | AV11: 39 | AW11: 12 | BB11: 6053 | BC11: 6071 | BE11: 10.1007/s11269-025-04240-4 | BF11: =HYPERLINK("http://dx.doi.org/10.1007/s11269-025-04240-4","http://dx.doi.org/10.1007/s11269-025-04240-4") -> http://dx.doi.org/10.1007/s11269-025-04240-4 | BH11: MAY 2025 | BS11: WOS:001489326400001 | BT11: =HYPERLINK("https%3A%2F%2Fwww.webofscience.com%2Fwos%2Fwoscc%2Ffull-record%2FWOS:001489326400001","View Full Record in Web of Science") -> View Full Record in Web of Science
A12: J | B12: Bai, YN; Li, Z; Zhang, P; Huang, L; Gao, S; Qiao, HW; Liu, C; Liang, S; Hu, HD | F12: Bai, Yanan; Li, Zhen; Zhang, Ping; Huang, Lei; Gao, Shuo; Qiao, Haiwei; Liu, Chang; Liang, Shuang; Hu, Huadong | I12: High-resolution snow depth retrieval by passive microwave based on linear unmixing and machine learning stacking technique | J12: INTERNATIONAL JOURNAL OF APPLIED EARTH OBSERVATION AND GEOINFORMATION | V12: Accurate measurement of high-resolution snow depth (SD) is crucial for regional ecohydrology and climate studies. Passive microwave remote sensing is an effective technique for SD retrieval on global or regional scales. However, its low spatial resolution limits its application in various fields. Additionally, the complex effects of multiple factors in the microwave radiation process pose a significant challenge for accurate SD retrieval as SD increases. In this study, a high-resolution SD retrieval algorithm for passive microwave data was developed based on the linear unmixing method and machine learning (ML) stacking technique. Firstly, the 0.25 degrees AMSR2 brightness temperature data were downscaled to 0.01 degrees through linear unmixing. Then, combining the temporal and spatial features of the snowpack, the high-resolution SD was retrieved based on the ML stacking technique. This method combined the advantages of multiple base models for retrieving different depths of snow, which effectively improved the overall estimation performance of the algorithm. Compared with in situ observed SD at meteorological stations and field observation SD, the algorithm achieved an overall RMSE of 5.25 cm, which was lower than that of other coarse-resolution SD datasets and products, including the long-term series of daily SD dataset in China (7.40 cm), the ERA5-Land (9.71 cm), and JAXA AMSR2 Level 2 SD products (12.59 cm). Especially, it reduced the estimation error of deep snow with a depth exceeding 30 cm by 20.3 %, 21.5 %, and 24.9 %, respectively. | AA12: Liu, Chang/JCN-7173-2023 | AB12: , lizhen/0000-0003-3491-0697 | AO12: 1569-8432 | AP12: 1872-826X | AT12: APR | AU12: 2025 | AV12: 138 | BD12: 104467 | BE12: 10.1016/j.jag.2025.104467 | BF12: =HYPERLINK("http://dx.doi.org/10.1016/j.jag.2025.104467","http://dx.doi.org/10.1016/j.jag.2025.104467") -> http://dx.doi.org/10.1016/j.jag.2025.104467 | BH12: APR 2025 | BS12: WOS:001447293400001 | BT12: =HYPERLINK("https%3A%2F%2Fwww.webofscience.com%2Fwos%2Fwoscc%2Ffull-record%2FWOS:001447293400001","View Full Record in Web of Science") -> View Full Record in Web of Science
A13: J | B13: Wei, YL; Li, XF; Gu, LJ; Zheng, ZJ; Zheng, XM; Jiang, T | F13: Wei, Yanlin; Li, Xiaofeng; Gu, Lingjia; Zheng, Zhaojun; Zheng, Xingming; Jiang, Tao | I13: Snow depth inversion and mapping at 500 m resolution from 1980 to 2020 in Northeast China using radiative transfer model and machine learning | J13: INTERNATIONAL JOURNAL OF APPLIED EARTH OBSERVATION AND GEOINFORMATION | V13: Accurate snow cover parameter assessment and mapping at a fine resolution can have profound implications for our understanding of the planet's water balance and energy dynamics. Passive microwave (PMW) remote sensing is among the most effective methods for snow depth (SD) retrieval. However, significant uncertainties persist in SD retrieval and mapping due to snow characteristic variations, forest canopy interference, and low spatial resolution of PMW. To overcome these limitations, a novel method considering multiple influencing factors was proposed by integration a radiation transfer model with a machine learning model for SD retrieval, and a 500 m resolution SD dataset (NCSD) was generated for 1980-2020 in Northeast China by combining downscaling model. The validation against independent ground observations revealed that the MAE, RMSE, and R values for NCSD were 4.39 cm, 6.65 cm and 0.77, respectively. Compared to existing SD products, NCSD data effectively avoid mixed pixel issues, improved SD retrieval performance, and reveal more refined snow cover spatiotemporal patterns. Additionally, the NCSD results indicated that the annual average SD in Northeast China exhibited an increasing trend from 1980 to 2020 (0.26 cm/10a, p > 0.05). However, a notable inflection point occurred in 2000, and a subsequent decreasing trend occurred from 2000 to 2020 (0.49 cm/10a, p > 0.05). Overall, the creation of NCSD effectively filled the gap related to high-resolution SD data, and facilitated the development of hydrological studies and climate change at the basin scale. | AB13: Li, Xiaofeng/0000-0002-1799-844X; Gu, Lingjia/0000-0002-4909-2263 | AO13: 1569-8432 | AP13: 1872-826X | AT13: MAY | AU13: 2025 | AV13: 139 | BD13: 104533 | BE13: 10.1016/j.jag.2025.104533 | BF13: =HYPERLINK("http://dx.doi.org/10.1016/j.jag.2025.104533","http://dx.doi.org/10.1016/j.jag.2025.104533") -> http://dx.doi.org/10.1016/j.jag.2025.104533 | BH13: APR 2025 | BS13: WOS:001471822100001 | BT13: =HYPERLINK("https%3A%2F%2Fwww.webofscience.com%2Fwos%2Fwoscc%2Ffull-record%2FWOS:001471822100001","View Full Record in Web of Science") -> View Full Record in Web of Science
A14: J | B14: Goodarzi, MR; Barzkar, A; Sabaghzadeh, M; Ghanbari, M; Attar, NF | F14: Goodarzi, Mohammad Reza; Barzkar, Ali; Sabaghzadeh, Maryam; Ghanbari, Meysam; Attar, Nasrin Fathollahzadeh | I14: Uncertainty Analysis of Machine Learning Methods To Estimate Snow Water Equivalent Using Meteorological and Remote Sensing Data | J14: WATER RESOURCES MANAGEMENT | V14: A better understanding of regional water resources may help improve management of these resources. Snow is a resource that cannot be accurately measured. Research in this field has been increasing in recent years with the advancements in machine learning methods and satellite imagery. This research measured Snow Water Equivalent (SWE) using eight machine learning approaches; Furthermore, the input data used in this study are monthly. Ten meteorological parameters related to snow, and also two parameters for albedo and snow cover fraction obtained from satellite imagery from 1981 to 2022, were provided as inputs to the models. The best input combination was determined through the gamma test, and the impact percentage of each input on the result was evaluated using sensitivity analysis. The results showed that the XGBoost (XGB) method with a Nash-Sutcliffe Efficiency (NSE) coefficient of 0.99 is the best, and Ridge regression with an NSE coefficient value of 0.6486 has the worst result. The dataset was divided into 80% for training and 20% for testing. The trend of snow water equivalent (SWE) during this period was evaluated utilizing the Mann-Kendall test and Sen's slope analysis. The findings indicate a decreasing trend in SWE. The utilization of current machine learning methods helps a more precise estimation of the water volume in the region, providing improved decision-making for the management of regional water resources. | AA14: Goodarzi, Mohammad/AAQ-3253-2020; Ghanbari, Meysam/PRR-2115-2026; Fathollahzadeh Attar, Nasrin/P-6175-2017 | AB14: Fathollahzadeh Attar, Nasrin/0000-0002-9506-452X | AO14: 0920-4741 | AP14: 1573-1650 | AT14: JUL | AU14: 2025 | AV14: 39 | AW14: 9 | BB14: 4471 | BC14: 4491 | BE14: 10.1007/s11269-025-04164-z | BF14: =HYPERLINK("http://dx.doi.org/10.1007/s11269-025-04164-z","http://dx.doi.org/10.1007/s11269-025-04164-z") -> http://dx.doi.org/10.1007/s11269-025-04164-z | BH14: APR 2025 | BS14: WOS:001459610300001 | BT14: =HYPERLINK("https%3A%2F%2Fwww.webofscience.com%2Fwos%2Fwoscc%2Ffull-record%2FWOS:001459610300001","View Full Record in Web of Science") -> View Full Record in Web of Science
A15: J | B15: Esfahani, AG; Moradizadeh, M; Srivastava, PK | F15: Esfahani, Ali Ghofrani; Moradizadeh, Mina; Srivastava, Prashant K. | I15: Improving AMSR2-derived Snow Depth Spatial Resolution Through Synergistic Combination of Machine Learning and Random Sets Over the European Alps | J15: PFG-JOURNAL OF PHOTOGRAMMETRY REMOTE SENSING AND GEOINFORMATION SCIENCE | V15: Snow depth is a critical parameter for meteorological, climatological, and hydrological models, enhancing regional water resource information and weather prediction accuracy. AMSR2 passive microwave data with 10-kilometer spatial resolution results in high error and uncertainty in snow depth estimation. This study attempted to develop machine learning algorithms to downscale AMSR2 snow depth data to 1 kilometer spatial resolution. One of the primary factors inflicting errors in snow depth downscaling is the absence of proper identification of snow-covered area boundaries (mixed pixels), leading to extensional uncertainty. In the present study, a novel method based on the theory of random sets has been developed to resolve the issue of mixed pixels in the boundaries of snow-covered areas for the European Alps. In addition to snow cover data acquired from random sets, auxiliary data for developing and training machine learning algorithms comprises of the Digital Elevation Model (DEM), Land Surface Temperature (LST), and Land Cover Type data were processed. The machine learning algorithms employed includes Support Vector Regression (SVR), Multi-Layer Perceptron (MLP), and Random Forest (RF). The RF algorithm, when considering snow cover data derived from random sets method, confirmed the excellent performance among the SVR and MLP algorithms. Using RF, the RMSE decreased from 31.67-16.34 cm, the correlation coefficient increased from 0.312-0.81, and the relative error decreased from 9.85-0.52% (reduced error and increased accuracy). The results based on evaluation metrics indicates an outstanding performance of the proposed innovative method for downscaling of AMSR2 snow depth. | AA15: /O-2815-2019 | AO15: 2512-2789 | AP15: 2512-2819 | AT15: JUN | AU15: 2025 | AV15: 93 | AW15: 3 | BB15: 231 | BC15: 250 | BE15: 10.1007/s41064-025-00338-x | BF15: =HYPERLINK("http://dx.doi.org/10.1007/s41064-025-00338-x","http://dx.doi.org/10.1007/s41064-025-00338-x") -> http://dx.doi.org/10.1007/s41064-025-00338-x | BH15: APR 2025 | BS15: WOS:001459026000001 | BT15: =HYPERLINK("https%3A%2F%2Fwww.webofscience.com%2Fwos%2Fwoscc%2Ffull-record%2FWOS:001459026000001","View Full Record in Web of Science") -> View Full Record in Web of Science
A16: J | B16: Demil, G; Haghighi, AT; Klöve, B; Oussalah, M | F16: Demil, Getnet; Haghighi, Ali Torabi; Klove, Bjorn; Oussalah, Mourad | I16: Advances in image-based estimation of snow variable: A systematic literature review on recent studies | J16: JOURNAL OF HYDROLOGY | V16: Accurately estimating snow hydrology parameters, including snow coverage mapping and snow depth, plays a significant role in comprehending water resource dynamics, flood forecasting, and environmental management in regions influenced by snow cover. These parameters are critical for hydrological models that simulate snowmelt and runoff, which are essential for predicting water availability and managing water resources in snow-covered areas. Traditional methods for estimating these parameters often rely on manual measurements or simplistic models, which can be inadequate for capturing the complexity of snow-related processes. In recent years, there has been a growing interest in leveraging deep learning techniques for snow hydrology parameter estimation, offering the potential to overcome these limitations. This review paper comprehensively analyzes the current state, challenges, and future directions of image-based approaches in snow hydrology parameter estimation. By harnessing the power of automated methods, particularly deep learning, these approaches demonstrate the ability to capture intricate spatial and temporal relationships present in image data. A comparative analysis on image-based methods highlights the strengths of automated approaches, including scalability and accuracy. Integration of image sensors, such as satellite imagery and crowd-sourced data, is explored as a crucial component of snow hydrology parameter estimation. Various satellite image sources, including Sentinel 1-2, Landsat, and Moderate Resolution Imaging Spectroradiometer (MODIS), are discussed in terms of their suitability for snow hydrological applications. Despite the promise of image-based approaches, challenges remain, including data availability, model interpretability, and transferability. The paper identifies future research directions, emphasizing the exploration of novel deep learning architectures and uncertainty quantification techniques to address these challenges. In conclusion, this review underscores the importance of image-based approaches for advancing snow hydrology parameter estimation. By addressing challenges and maximizing potential impact, these approaches have the potential to revolutionize snow hydrological modeling and environmental management. | AA16: ; Haghighi, Ali/AAE-6862-2021 | AB16: Klöve, Björn/0000-0002-2353-1440; Demil, Getnet/0009-0006-5158-0895; Oussalah, Mourad/0000-0002-4422-8723 | AO16: 0022-1694 | AP16: 1879-2707 | AT16: JUN | AU16: 2025 | AV16: 654 | BD16: 132855 | BE16: 10.1016/j.jhydrol.2025.132855 | BF16: =HYPERLINK("http://dx.doi.org/10.1016/j.jhydrol.2025.132855","http://dx.doi.org/10.1016/j.jhydrol.2025.132855") -> http://dx.doi.org/10.1016/j.jhydrol.2025.132855 | BH16: FEB 2025 | BS16: WOS:001433637500001 | BT16: =HYPERLINK("https%3A%2F%2Fwww.webofscience.com%2Fwos%2Fwoscc%2Ffull-record%2FWOS:001433637500001","View Full Record in Web of Science") -> View Full Record in Web of Science
A17: J | B17: Tanniru, S; Singh, DK; Singh, KK; Ramsankaran, R | F17: Tanniru, Srinivasarao; Singh, Dhiraj Kumar; Singh, Kamal Kant; Ramsankaran, Raaj | I17: Exploring Machine Learning's Potential for Estimating High Resolution Daily Snow Depth in Western Himalaya Using Passive Microwave Remote Sensing Data Sets | J17: EARTH AND SPACE SCIENCE | V17: Snow depth (SD) exhibits high spatiotemporal heterogeneity in Western Himalaya (WH), and its knowledge is essential for applications related to water resources, disaster management, climate, etc. However, due to inclement weather and rugged topographical conditions, only a sparse network of SD monitoring stations exists in WH. Spaceborne passive microwave (PMW) remote sensing data sets provides valuable information about SD; however, only a limited PMW SD studies that cover subregions of WH are available. Different machine learning (ML) methods viz. support vector machine, random forest, and Extremely Randomized Trees (ERT) were tested for estimating SD. Based on our preliminary assessment of these ML approaches, the current study utilizes ERT approach to estimate daily SD over the entire WH region. The ERT SD model is developed using PMW brightness temperature data sets from Advanced Microwave Scanning Radiometer-2 (AMSR-2), snow cover duration (SCD), and other auxiliary parameters (i.e., location, elevation, vegetation cover, etc.) during the winter period between 2012-2013 and 2019-2020. The data between 2012-2013 and 2017-2018 is used for training the model, whereas the data between 2018-2019 and 2019-2020 is used for testing the model. The results demonstrate: (a) The ERT SD model has shown improved SD estimates compared to the available PMW remote sensing-based operational SD products and empirical PMW SD models. (b) In general, with an increase in SD, the mean absolute error of SD retrievals has increased in all SD products/models. (c) Unlike the operational AMSR2 SD product, and Northern Hemisphere Machine Learning SD product, the ERT SD model retrievals have shown better consistency with MODIS snow cover. (d) The developed model has shown a wider range in SD retrievals as compared to other products considered in this study. | AA17: Tanniru, Srinivasarao/F-1862-2013; Ramsankaran, RAAJ/B-9198-2008 | AB17: Ramsankaran, RAAJ/0000-0001-8602-1934 | AP17: 2333-5084 | AT17: FEB 12 | AU17: 2025 | AV17: 12 | AW17: 2 | BD17: e2024EA003849 | BE17: 10.1029/2024EA003849 | BF17: =HYPERLINK("http://dx.doi.org/10.1029/2024EA003849","http://dx.doi.org/10.1029/2024EA003849") -> http://dx.doi.org/10.1029/2024EA003849 | BS17: WOS:001467218000001 | BT17: =HYPERLINK("https%3A%2F%2Fwww.webofscience.com%2Fwos%2Fwoscc%2Ffull-record%2FWOS:001467218000001","View Full Record in Web of Science") -> View Full Record in Web of Science
A18: J | B18: Hu, HH; He, L; Hui, FM; Cheng, X; Zheng, ZJ; Che, T; Chen, ZQ | F18: Hu, Haihan; He, Lian; Hui, Fengming; Cheng, Xiao; Zheng, Zhaojun; Che, Tao; Chen, Zhuoqi | I18: Snow Cover Mapping From Chinese Geostationary Meteorological Satellite FY-2F VISSR-II Data Using Random Forest Classifier | J18: IEEE JOURNAL OF SELECTED TOPICS IN APPLIED EARTH OBSERVATIONS AND REMOTE SENSING | V18: Accurate monitoring of snow cover is essential for understanding climate dynamics and supporting hydrological and environmental management. The Fengyun-2F (FY-2F) satellite is one of China's first geostationary meteorological satellites, equipped with the Stretched Visible and Infrared Spin Scan Radiometer-II (VISSR-II), which provides moderate-resolution imagery at high temporal resolution but has only five spectral channels. To enhance the snow cover mapping capability of the FY-2F VISSR-II sensor, this study develops a novel algorithm in which multitemporal observations within a single day are first fused to generate a daily synthesis image, thereby reducing cloud contamination. Based on this synthesized image, snow cover detection is then carried out using a random forest model driven by multisource spatiotemporal features. The algorithm was rigorously evaluated against in situ snow depth observations, Landsat 8 snow cover maps, Moderate Resolution Imaging Spectroradiometer (MODIS) snow cover products, and Fengyun-4 (FY-4) A snow cover product. The results indicate strong performance of the FY-2F snow cover product, with an overall accuracy (OA) of 90.8% and an F1-score (FS) of 88.9% against in situ measurements, and an OA of 94.6% with an FS of 91.9% compared to Landsat 8 snow cover maps. When validated against the four MODIS-based reference products and FY-4 A snow cover product, the FY-2F snow cover product achieved OA values ranging from 92% to 99%. The novelty of this work lies in the effective integration of auxiliary data to compensate for the limited bands. It provides a valuable reference for snow cover mapping from early geostationary meteorological satellites with a limited number of spectral bands. | AA18: He, Lian/AAF-3997-2020; Che, Tao/K-7136-2013 | AB18: He, Lian/0000-0002-9909-6107; Cheng, Xiao/0000-0001-6910-6565; Hu, Haihan/0009-0006-6101-6155; ZHENG, Zhaojun/0000-0002-7331-1905; Che, Tao/0000-0001-6848-7271 | AO18: 1939-1404 | AP18: 2151-1535 | AU18: 2025 | AV18: 18 | BB18: 27979 | BC18: 27992 | BE18: 10.1109/JSTARS.2025.3626728 | BF18: =HYPERLINK("http://dx.doi.org/10.1109/JSTARS.2025.3626728","http://dx.doi.org/10.1109/JSTARS.2025.3626728") -> http://dx.doi.org/10.1109/JSTARS.2025.3626728 | BS18: WOS:001626465700006 | BT18: =HYPERLINK("https%3A%2F%2Fwww.webofscience.com%2Fwos%2Fwoscc%2Ffull-record%2FWOS:001626465700006","View Full Record in Web of Science") -> View Full Record in Web of Science
A19: C | B19: Kumawat, D; Ehtehaj, A | E19: IEEE | F19: Kumawat, Divya; Ehtehaj, Ardeshir | I19: CAN DEEP TRANSFORMERS LEARN GLOBAL PEAK SNOW WATER EQUIVALENT FROM L-BAND SURFACE EMISSIONS? | J19: IGARSS 2025-2025 IEEE INTERNATIONAL GEOSCIENCE AND REMOTE SENSING SYMPOSIUM | K19: IEEE International Symposium on Geoscience and Remote Sensing IGARSS | O19: 2025 International Geoscience and Remote Sensing Symposium-IGARSS-Annual | P19: AUG 03-08, 2025 | Q19: Brisbane, AUSTRALIA | R19: Institute of Electrical and Electronics Engineers Inc | V19: The seasonal peak snow water equivalent (SWEp) is a key parameter for spring streamflow prediction, hydroelectricity generation, drought management, and ecosystem productivity. For the first time, this study proposes a novel methodology for estimating SWEp through learning from the coincident time series of L-band brightness temperature (TB) from the Soil Moisture Active Passive (SMAP) satellite (inputs) as well as reanalysis data and ground-based observations (outputs). This approach uses a deep transformer neural network, leveraging dynamic and static predictors through a multi-head self-attention mechanism, called SWEFormer. This methodology is enriched by the concept of transfer learning that incrementally learns and combines the information content of ERA5 reanalysis data with sparse ground observations, addressing data limitations and improving accuracy. Validation against in situ observations shows promising performance metrics with root mean squared error, bias, and coefficient of determination of 65.76 mm, 21.77 mm, and 0.65, nearly three times better than ERA5 estimates. Unlike methodologies relying on higher microwave frequencies with a low-penetration depth in vegetated areas, SWEFormer provides a robust, all-weather solution for SWEp estimation, supporting ecosystem modeling in high-latitude watersheds and boreal forest regions, where the human population relies on snowmelt-driven spring streamflow. | AA19: Kumawat, Divya/NAX-6725-2025 | AO19: 2153-6996 | AQ19: 979-8-3315-0811-1; 979-8-3315-0810-4 | AU19: 2025 | BB19: 727 | BC19: 732 | BE19: 10.1109/IGARSS55030.2025.11242584 | BF19: =HYPERLINK("http://dx.doi.org/10.1109/IGARSS55030.2025.11242584","http://dx.doi.org/10.1109/IGARSS55030.2025.11242584") -> http://dx.doi.org/10.1109/IGARSS55030.2025.11242584 | BS19: WOS:001697407700156 | BT19: =HYPERLINK("https%3A%2F%2Fwww.webofscience.com%2Fwos%2Fwoscc%2Ffull-record%2FWOS:001697407700156","View Full Record in Web of Science") -> View Full Record in Web of Science
A20: J | B20: Yan, YC; Qin, Y; Liu, YQ; Qiu, YB; Liu, Y | F20: Yan, Yongchang; Qin, Yan; Liu, Yongqiang; Qiu, Yubao; Liu, Yang | I20: Estimation of Moderate-Resolution Snow Depth in Xinjiang With Enhanced-Resolution Passive Microwave and Reanalysis Data by Machine Learning Methods | J20: IEEE JOURNAL OF SELECTED TOPICS IN APPLIED EARTH OBSERVATIONS AND REMOTE SENSING | V20: The integration of multisource data into the passive microwave retrieval of snow depth (SD) is vital for accurately capturing large-scale distribution of SD. However, the exiting SD retrieval algorithms overlook the impact of snow characteristics on brightness temperature, leading to inadequate representation of SD in complex regions. Therefore, this study constructs and optimizes SD retrieval models using four machine learning algorithms, including extreme gradient boosting (XGBoost), light gradient-boosting machine (LightGBM), categorical boosting (CatBoost), and random forest (RF) combing enhanced-resolution passive microwave data. A variety of variables are integrated into the models, encompassing geolocation, topographic indices, land cover, and snow characteristics (fractional snow cover, snow density, and snow grain size) sourced from ERA5-land reanalysis data. This approach focuses on accurately estimating the spatiotemporal distribution of SD over Xinjiang, characterized by dry-cold snow. The results indicate that First, upon incorporating auxiliary variables, the SD from the CatBoost model demonstrated superior performances over the other algorithms ($R<^>{2}$: CatBoost > LightGBM > XGBoost > RF). Second, the SD product from the CatBoost model exhibits interannual fluctuations. It slightly overestimates shallow snow (SD < 20 cm) and underestimates deep snow (SD > 20 cm). Third, the SD product reveals the spatial differentiation. Areas in northern Xinjiang with high value for SD (SD > 20 cm) are mainly distributed in the Tianshan Mountains and Altai Mountains. In contrast, the southern Xinjiang with high value for SD (SD > 10 cm) is largely clustered in the high-elevation regions surrounding the Kunlun Mountains. The findings highlight that employing this approach can lead to the establishment of valuable long-term SD datasets for capturing SD distribution. | AA20: ; Qiu, Yubao/P-8103-2016 | AB20: 邱, 玉宝/0000-0003-1313-6313; Yan, Yongchang/0009-0003-2667-5778; | AO20: 1939-1404 | AP20: 2151-1535 | AU20: 2025 | AV20: 18 | BB20: 11250 | BC20: 11262 | BE20: 10.1109/JSTARS.2025.3562216 | BF20: =HYPERLINK("http://dx.doi.org/10.1109/JSTARS.2025.3562216","http://dx.doi.org/10.1109/JSTARS.2025.3562216") -> http://dx.doi.org/10.1109/JSTARS.2025.3562216 | BS20: WOS:001484675600007 | BT20: =HYPERLINK("https%3A%2F%2Fwww.webofscience.com%2Fwos%2Fwoscc%2Ffull-record%2FWOS:001484675600007","View Full Record in Web of Science") -> View Full Record in Web of Science
A21: C | B21: Zheng, YF; Jiang, LM; Pan, FB | E21: IEEE | F21: Zheng, Yifei; Jiang, Lingmei; Pan, Fangbo | I21: An Improved AVHRR Fractional Snow Cover Mapping Algorithm Using MODIS Observations Combined with Time-Scale Decomposition | J21: IGARSS 2025-2025 IEEE INTERNATIONAL GEOSCIENCE AND REMOTE SENSING SYMPOSIUM | K21: IEEE International Symposium on Geoscience and Remote Sensing IGARSS | O21: 2025 International Geoscience and Remote Sensing Symposium-IGARSS-Annual | P21: AUG 03-08, 2025 | Q21: Brisbane, AUSTRALIA | R21: Institute of Electrical and Electronics Engineers Inc | V21: Long-term fractional snow cover (FSC) data is a critical input for hydrological, climatic, and energy balance models, making its monitoring essential for understanding global climate and hydrological processes. AVHRR, as a unique long-term remote sensing sensor, provides valuable snow cover data, but its low spatial resolution and limited spectral bands present challenges for accurate snow cover retrieval. To overcome these challenges, this study proposes an improved AVHRR FSC mapping algorithm by combining time-scale decomposition with XG Boost, using MODIS observations to enhance spatial resolution and accuracy. The model generates AVHRR FSC products with 500 m resolution, significantly improving FSC accuracy compared to the original AVHRR data, with RMSE reduced from 0.196 to 0.107. These results highlight the potential of AVHRR in long-term snow cover monitoring and the benefit of combining machine learning and higher-resolution data. | AA21: Jiang, Lingmei/L-6099-2016; Pan, Fangbo/IQU-2803-2023 | AO21: 2153-6996 | AQ21: 979-8-3315-0811-1; 979-8-3315-0810-4 | AU21: 2025 | BB21: 2366 | BC21: 2370 | BE21: 10.1109/IGARSS55030.2025.11243237 | BF21: =HYPERLINK("http://dx.doi.org/10.1109/IGARSS55030.2025.11243237","http://dx.doi.org/10.1109/IGARSS55030.2025.11243237") -> http://dx.doi.org/10.1109/IGARSS55030.2025.11243237 | BS21: WOS:001697407700498 | BT21: =HYPERLINK("https%3A%2F%2Fwww.webofscience.com%2Fwos%2Fwoscc%2Ffull-record%2FWOS:001697407700498","View Full Record in Web of Science") -> View Full Record in Web of Science
A22: J | B22: Liu, Y; Yang, JM; Chen, X; Yao, JQ; Li, LH; Qiu, YB | F22: Liu, Yang; Yang, Jinming; Chen, Xi; Yao, Junqiang; Li, Lanhai; Qiu, Yubao | I22: Moderate-resolution snow depth product retrieval from passive microwave brightness data over Xinjiang using machine learning approach | J22: INTERNATIONAL JOURNAL OF DIGITAL EARTH | V22: Passive microwave (PM) remote sensing have been extensively used for snow depth (SD) estimation. However, current SD products from traditional PM data fail to capture the differentiation in mountainous and complex terrains with coarse resolution. Therefore, this study incorporates factors such as geographical location, topographic features, and land cover, along with various machine learning algorithms including Gaussian process regression (GPR), support vector machine (SVM), random forest (RF), extreme gradient boosting (XGBoost), and light gradient boosting machine (LightGBM), to construct and optimize SD estimation using enhanced-resolution PM data. The results demonstrate the following: (1)With the auxiliary variables, the SD product from LightGBM-based models exhibits the highest accuracy. (2)The performance of SD products from the LightGBM-based model varies monthly and annually, with shallow snow cover being slightly overestimated (30 cm). (3)The reliable SD product indicates spatial distribution characteristics in Xinjiang, with regions demonstrating no significant improvement being larger than those with no significant degradation. The above results illustrate the remarkable advantages of machine learning in capturing SD distribution and its spatio-temporal variation bolstered by enhanced PM data and auxiliary data. | AA22: Li, Lanhai/AAE-9967-2020; Qiu, Yubao/P-8103-2016; yang, jinming/IWL-8395-2023 | AB22: yang, jinming/0000-0002-1843-6908 | AO22: 1753-8947 | AP22: 1753-8955 | AT22: DEC 31 | AU22: 2024 | AV22: 17 | AW22: 1 | BD22: 2299208 | BE22: 10.1080/17538947.2023.2299208 | BF22: =HYPERLINK("http://dx.doi.org/10.1080/17538947.2023.2299208","http://dx.doi.org/10.1080/17538947.2023.2299208") -> http://dx.doi.org/10.1080/17538947.2023.2299208 | BS22: WOS:001135343300001 | BT22: =HYPERLINK("https%3A%2F%2Fwww.webofscience.com%2Fwos%2Fwoscc%2Ffull-record%2FWOS:001135343300001","View Full Record in Web of Science") -> View Full Record in Web of Science
A23: J | B23: Yan, ZN; Ji, Q; He, B; Chen, YZ; Wang, YY; Pang, XP | F23: Yan, Zhongnan; Ji, Qing; He, Bin; Chen, Yizhuo; Wang, Yueyun; Pang, Xiaoping | I23: A combined multi-source data and deep learning approach for retrieving snow depth on Antarctic Sea ice during the melting season | J23: INTERNATIONAL JOURNAL OF DIGITAL EARTH | V23: Snow on the Antarctic sea ice is a crucial component of the cryosphere. In response to the dynamic and highly heterogeneous Antarctic snow during the sea ice melting season, this study employed a combined multi-source data and deep learning method to accurately retrieve snow depth on Antarctic sea ice. Initially, we integrate multiple datasets, including satellite remote sensing, geospatial information, and meteorological data. Subsequently, a Convolutional Neural Network (CNN) is utilized to construct a snow depth retrieval model (PSDCNN-5_7 model). Compared to snow depth measurements from Alfred Wegener Institute (AWI) snow buoys, the PSDCNN-5_7 model outperforms existing algorithms, exhibiting a deviation of only -3.38 cm. The uncertainty of the snow depth caused by the model input is only 1.64 cm. In West Antarctica, snow depth is more affected by snowfall (SF), 2-m air temperature (T2m), and sea ice velocity (SIV). Conversely, in East Antarctica, snow depth is primarily influenced by SIV. The proposed approach accurately retrieves snow depth on Antarctic sea ice and facilitates the derivation of long-term variations and trends in snow depth, contributing to a better understanding of the relationship between sea ice, snow, and climate change. | AA23: Yan, Zhongnan/JED-7970-2023 | AO23: 1753-8947 | AP23: 1753-8955 | AT23: DEC 31 | AU23: 2024 | AV23: 17 | AW23: 1 | BD23: 2376260 | BE23: 10.1080/17538947.2024.2376260 | BF23: =HYPERLINK("http://dx.doi.org/10.1080/17538947.2024.2376260","http://dx.doi.org/10.1080/17538947.2024.2376260") -> http://dx.doi.org/10.1080/17538947.2024.2376260 | BS23: WOS:001270114800001 | BT23: =HYPERLINK("https%3A%2F%2Fwww.webofscience.com%2Fwos%2Fwoscc%2Ffull-record%2FWOS:001270114800001","View Full Record in Web of Science") -> View Full Record in Web of Science
A24: J | B24: Elyoussfi, H; Boudhar, A; Belaqziz, S; Bousbaa, M; Nifa, K; Bargam, B; Chehbouni, A | F24: Elyoussfi, Haytam; Boudhar, Abdelghani; Belaqziz, Salwa; Bousbaa, Mostafa; Nifa, Karima; Bargam, Bouchra; Chehbouni, Abdelghani | I24: Leveraging advanced deep learning and machine learning approaches for snow depth prediction using remote sensing and ground data | J24: JOURNAL OF HYDROLOGY-REGIONAL STUDIES | V24: Study regions: The study area encompasses two distinct sub-basins within the High Atlas Mountains: Oukaimeden in the Rheraya and Tichki in the Mgoun Valley. Study focus: The research integrates remote sensing data, particularly the Normalized-Difference Snow Index (NDSI) from the MODIS Sensor, with machine learning (ML) and deep learning (DL) models to predict daily snow depth (DSD) at a local scale. The models evaluated include two ML approaches: Support Vector Regression (SVR) and eXtreme Gradient Boosting (XGBoost) and four DL models: 1-Dimensional Convolutional Neural Network (1D-CNN), Long Short-Term Memory Networks (LSTM), Gated Recurrent Unit (GRU), and Bi-directional Long Short-Term Memory Network (Bi-LSTM). The dataset was processed and normalized for optimal performance, and hyperparameters were fine-tuned using a randomized search method. New hydrological insights for the region: The Results highlight the efficacy of AI-based approaches for snow depth prediction, with SVR achieving the best performance (Root Mean Square Error of 2-5 cm and an average coefficient of determination of 0.97). This study reveals that incorporating lag times of snow depth data significantly enhances predictive accuracy. These findings underscore the potential of integrating remote sensing with AI techniques to improve hydrological modeling and water resource planning in data-scarce regions like the Atlas Mountains. | AA24: Belaqziz, Salwa/W-1992-2019; ELYOUSSFI, Haytam/MHR-0198-2025; chehbouni, abdelghani/ACN-8375-2022; BOUSBAA, Mostafa/ISS-0641-2023; BOUDHAR, Abdelghani/S-5216-2019 | AB24: Belaqziz, Salwa/0000-0001-7248-8605; ELYOUSSFI, Haytam/0000-0001-6496-7200; | AP24: 2214-5818 | AT24: FEB | AU24: 2025 | AV24: 57 | BD24: 102085 | BE24: 10.1016/j.ejrh.2024.102085 | BF24: =HYPERLINK("http://dx.doi.org/10.1016/j.ejrh.2024.102085","http://dx.doi.org/10.1016/j.ejrh.2024.102085") -> http://dx.doi.org/10.1016/j.ejrh.2024.102085 | BH24: DEC 2024 | BS24: WOS:001381927800001 | BT24: =HYPERLINK("https%3A%2F%2Fwww.webofscience.com%2Fwos%2Fwoscc%2Ffull-record%2FWOS:001381927800001","View Full Record in Web of Science") -> View Full Record in Web of Science
A25: J | B25: Ni, ZA; Yang, QQ; Yue, LW; Peng, YF; Yuan, QQ | F25: Ni, Zi'ang; Yang, Qianqian; Yue, Linwei; Peng, Yanfei; Yuan, Qiangqiang | I25: Estimating high-resolution snow depth over the North Hemisphere mountains utilizing active microwave backscatter and machine learning | J25: JOURNAL OF HYDROLOGY | V25: While ground meteorological stations provide accurate snow depth data, their limited spatial coverage results in observational gaps. Satellites offer long-term, large-scale observations, addressing these gaps. Existing snow depth retrieval algorithms mainly use passive microwave remote sensing data with a 25 km resolution, insufficient for capturing snow depth variability in mountainous areas. This paper introduces active microwave backscatter data and machine learning techniques for high-resolution snow depth estimation. We conducted a preliminary exploration of the relationship between Sentinel-1 backscatter coefficient sigma(0) and snow depth. Due to factors such as vegetation coverage and underlying soil properties, the relationship between sigma(0) and snow depth is complex and nonlinear. Consequently, six machine learning models were trained to learn this relationship using sigma(0) and auxiliary data as input features, with in-situ snow depth serving as the target variable. After extensive validation, the Extreme Random Trees (ERT) model was selected for its high accuracy and stability. Using the ERT model, we generated 500 m-resolution snow depth data for northern hemisphere mountains, then analyzed temporal snow depth variations and altitudinal stratification. | AA25: ; Yue, Linwei/ABD-8243-2022 | AB25: Ni, Zi'ang/0009-0004-8298-0467; | AO25: 0022-1694 | AP25: 1879-2707 | AT25: DEC | AU25: 2024 | AV25: 645 | AX25: A | BD25: 132203 | BE25: 10.1016/j.jhydrol.2024.132203 | BF25: =HYPERLINK("http://dx.doi.org/10.1016/j.jhydrol.2024.132203","http://dx.doi.org/10.1016/j.jhydrol.2024.132203") -> http://dx.doi.org/10.1016/j.jhydrol.2024.132203 | BS25: WOS:001756997100001 | BT25: =HYPERLINK("https%3A%2F%2Fwww.webofscience.com%2Fwos%2Fwoscc%2Ffull-record%2FWOS:001756997100001","View Full Record in Web of Science") -> View Full Record in Web of Science
A26: J | B26: Dunmire, D; Lievens, H; Boeykens, L; De Lannoy, GJM | F26: Dunmire, Devon; Lievens, Hans; Boeykens, Lucas; De Lannoy, Gabrielle J. M. | I26: A machine learning approach for estimating snow depth across the European Alps from Sentinel-1 imagery | J26: REMOTE SENSING OF ENVIRONMENT | V26: Seasonal snow plays a crucial role in society and understanding trends in snow depth and mass is essential for making informed decisions about water resources and adaptation to climate change. However, quantifying snow depth in remote, mountainous areas with complex topography remains a significant challenge. The increasing availability of high-resolution synthetic aperture radar (SAR) observations from active microwave satellites has prompted opportunistic use of the data to retrieve snow depth remotely across large spatial and frequent temporal scales and at a high spatial resolution. Nevertheless, these novel SAR-based snow depth retrieval methods face their own set of limitations, including challenges for shallow snowpacks, high vegetation cover, and wet snow conditions. In response, here we introduce a machine learning approach to enhance SAR-based snow depth estimation over the European Alps. By integrating Sentinel-1 SAR imagery, optical snow cover observations, and topographic, forest cover and snow class information, our machine learning retrieval method more accurately estimates snow depth at independent in-situ measurement sites than current methods. Further, our method provides estimates at 100 m horizontal resolution and is capable of better capturing local-scale topographydriven snow depth variability. Through detailed feature importance analysis, we identify optimal conditions for SAR data utilization, thereby providing insight into future use of C-band SAR for snow depth retrieval. | AA26: De Lannoy, Gabrielle/C-9101-2017; Lievens, Hans/AAL-5717-2021 | AB26: De Lannoy, Gabrielle/0000-0002-6743-7122; Boeykens, Lucas/0009-0006-4365-4997; Lievens, Hans/0000-0002-6391-1691 | AO26: 0034-4257 | AP26: 1879-0704 | AT26: DEC 1 | AU26: 2024 | AV26: 314 | BD26: 114369 | BE26: 10.1016/j.rse.2024.114369 | BF26: =HYPERLINK("http://dx.doi.org/10.1016/j.rse.2024.114369","http://dx.doi.org/10.1016/j.rse.2024.114369") -> http://dx.doi.org/10.1016/j.rse.2024.114369 | BH26: AUG 2024 | BS26: WOS:001302838100001 | BT26: =HYPERLINK("https%3A%2F%2Fwww.webofscience.com%2Fwos%2Fwoscc%2Ffull-record%2FWOS:001302838100001","View Full Record in Web of Science") -> View Full Record in Web of Science
A27: J | B27: Meehan, TG; Hojatimalekshah, A; Marshall, HP; Deeb, EJ; O'Neel, S; McGrath, D; Webb, RW; Bonnell, R; Raleigh, MS; Hiemstra, C; Elder, K | F27: Meehan, Tate G.; Hojatimalekshah, Ahmad; Marshall, Hans-Peter; Deeb, Elias J.; O'Neel, Shad; McGrath, Daniel; Webb, Ryan W.; Bonnell, Randall; Raleigh, Mark S.; Hiemstra, Christopher; Elder, Kelly | I27: Spatially distributed snow depth, bulk density, and snow water equivalent from ground-based and airborne sensor integration at Grand Mesa, Colorado, USA | J27: CRYOSPHERE | V27: Estimating snow mass in the mountains remains a major challenge for remote-sensing methods. Airborne lidar can retrieve snow depth, and some promising results have recently been obtained from spaceborne platforms, yet density estimates are required to convert snow depth to snow water equivalent (SWE). However, the retrieval of snow bulk density remains unsolved, and limited data are available to evaluate model estimates of density in mountainous terrain. Toward the goal of landscape-scale retrievals of snow density, we estimated bulk density and length-scale variability by combining ground-penetrating radar (GPR) two-way travel-time observations and airborne-lidar snow depths collected during the mid-winter NASA SnowEx 2020 campaign at Grand Mesa, Colorado, USA. Key advancements of our approach include an automated layer-picking method that leverages the GPR reflection coherence and the distributed lidar-GPR-retrieved bulk density with machine learning. The root-mean-square error between the distributed estimates and in situ observations is 11 cm for depth, 27 kgm-3 for density, and 46 mm for SWE. The median relative uncertainty in distributed SWE is 13 %. Interactions between wind, terrain, and vegetation display corroborated controls on bulk density that show model and observation agreement. Knowledge of the spatial patterns and predictors of density is critical for the accurate assessment of SWE and essential snow research applications. The spatially continuous snow density and SWE estimated over approximately 16 km2 may serve as necessary calibration and validation for stepping prospective remote-sensing techniques toward broad-scale SWE retrieval. | AA27: ; Raleigh, Mark/M-7687-2015; Marshall, Hans-Peter/A-2374-2010; Elder, Kelly/IZQ-5813-2023; /AGN-0726-2022; Hojatimalekshah, Ahmad/AAX-6802-2020; Webb, Ryan/X-1122-2018; Bonnell, Randall/LRU-7969-2024 | AB27: MCGRATH, DANIEL/0000-0002-9462-6842; O'Neel, Shad/0000-0002-9185-0144; Hojatimalekshah, Ahmad/0000-0003-2695-469X; Webb, Ryan/0000-0002-1565-909X; Bonnell, Randall/0000-0002-8812-351X | AO27: 1994-0416 | AP27: 1994-0424 | AT27: JUL 22 | AU27: 2024 | AV27: 18 | AW27: 7 | BB27: 3253 | BC27: 3276 | BE27: 10.5194/tc-18-3253-2024 | BF27: =HYPERLINK("http://dx.doi.org/10.5194/tc-18-3253-2024","http://dx.doi.org/10.5194/tc-18-3253-2024") -> http://dx.doi.org/10.5194/tc-18-3253-2024 | BS27: WOS:001273258700001 | BT27: =HYPERLINK("https%3A%2F%2Fwww.webofscience.com%2Fwos%2Fwoscc%2Ffull-record%2FWOS:001273258700001","View Full Record in Web of Science") -> View Full Record in Web of Science
A28: J | B28: Hou, HY; Hu, GH; Chu, N; You, YH; Gao, MY; Li, MY; Hu, ZD | F28: Hou, Haiyan; Hu, Guohua; Chu, Nan; You, Yuanhong; Gao, Minyi; Li, Mengya; Hu, Zhiding | I28: Snow depth retrieval from microwave remote sensing by combining wavelet transform and machine learning models in Northern Xinjiang, China | J28: JOURNAL OF APPLIED REMOTE SENSING | V28: Passive microwave remote sensing is a valuable tool for snow depth estimation. However, accurate retrieval is limited by nonlinear relationships between the snow depth and passive microwave brightness temperature (TB) that are caused by snow physical properties, underlying surface type, and topographical factors. Our study aims to enhance snow depth estimation in Northern Xinjiang (NX), China, utilizing Advanced Microwave Scanning Radiometer 2 TB data (with a resolution of 0.1 deg) and fractional snow cover products through a combination of wavelet transform and two artificial neural network (ANN) models: feedforward neural network (FFNN) and generalized regression neural network (GRNN). The hybrid models were trained and validated using in situ snow depth observations from 44 stations across NX. Results indicate that applying wavelet transform reduces the root-mean-square error (RMSE) by 28.88% for FFNN. In the snow season of 2013 to 2014, Wavelet-GRNN (RMSE: 7.36 cm, NSE: 0.59, R: 0.78, bias: 1.68 cm) outperforms Wavelet-FFNN (RMSE: 8.26 cm, NSE: 0.48, R: 0.75, bias: 1.69 cm) by 10.90%. However, Wavelet-FFNN exhibits superior performance, up to 13.78% than Wavelet-GRNN in complex topographic areas like Xiaoquzi station. In addition, spatial-temporal estimations demonstrate that the hybrid models surpass three well-known snow depth products and alleviate issues of excessively high or low values in NX. These findings underscore the effectiveness of hybrid models combining wavelet transform and ANNs, integrating passive microwave remote sensing and auxiliary data, for accurate snow depth estimation in mountainous regions.(c) 2024 Society of Photo-Optical Instrumentation Engineers (SPIE) | AA28: Gao, Minyi/HZK-6206-2023; zhiding, Hu/HHN-5338-2022; Hu, Guohua/H-4269-2016 | AB28: Hou, Haiyan/0000-0002-3052-1259 | AP28: 1931-3195 | AT28: APR 1 | AU28: 2024 | AV28: 18 | AW28: 2 | BD28: 24517 | BE28: 10.1117/1.JRS.18.024517 | BF28: =HYPERLINK("http://dx.doi.org/10.1117/1.JRS.18.024517","http://dx.doi.org/10.1117/1.JRS.18.024517") -> http://dx.doi.org/10.1117/1.JRS.18.024517 | BS28: WOS:001270024600022 | BT28: =HYPERLINK("https%3A%2F%2Fwww.webofscience.com%2Fwos%2Fwoscc%2Ffull-record%2FWOS:001270024600022","View Full Record in Web of Science") -> View Full Record in Web of Science
A29: J | B29: Broxton, P; Ehsani, MR; Behrangi, A | F29: Broxton, Patrick; Ehsani, Mohammad Reza; Behrangi, Ali | I29: Improving Mountain Snowpack Estimation Using Machine Learning With Sentinel-1, the Airborne Snow Observatory, and University of Arizona Snowpack Data | J29: EARTH AND SPACE SCIENCE | V29: Accurate mapping of snow amount in the mountains is critical as mountain snowpacks are water supply for millions of people. Satellite remote sensing has been largely unable to reliably detect the amount of snowpack in these areas. Recently, C-band Synthetic Aperture Radar (SAR) data from the Sentinel-1 (S1) satellites have shown potential for measuring snow depth in the mountains. However, their spatiotemporal coverage is incomplete, and their evaluation with robust, aerial snow depth data is limited. Here, we evaluate two S1 snowpack datasets with some of the best available gridded snowpack data over the Colorado Rockies and Sierra Nevada mountains in the western US: the Airborne Snow Observatory (ASO) and the University of Arizona (UA) snowpack datasets. Compared to ASO and UA data, the S1 data are biased high when snow is shallow, and biased low when snow is deep (particularly later in spring when there is wet snow), though these biases are reduced for deep snow areas when wet snow pixels are removed. We then apply corrections based on machine learning that account for physiographic characteristics to improve the accuracy of the S1 data. Furthermore, we fill gaps in the S1 data by using snow persistence, but also account for potential snow accumulation and ablation, to generate temporally complete snow depth maps over mountainous areas. Corrected and gap-filled S1 snow depth mapping could be especially important for snow monitoring in remote mountain areas where other techniques for snow mapping do not work or are logistically infeasible or cost-prohibitive. Two versions of Sentinel-1 snow data are compared to the ASO and University of Arizona (UA) snow data in the western United States These data are biased (low) high when snow is (deep) shallow, but masking of wet snow pixels improves low biases in areas with deep snow Machine learning and gap-filling are used to correct biases and generate temporally complete Sentinel-1 snow depth maps in these regions | AA29: Ehsani, Mohammad Reza/AAV-6956-2021; Behrangi, Ali/V-8927-2019 | AB29: Ehsani, Mohammad Reza/0000-0003-0202-6901; | AP29: 2333-5084 | AT29: MAR 16 | AU29: 2024 | AV29: 11 | AW29: 3 | BD29: e2023EA002964 | BE29: 10.1029/2023EA002964 | BF29: =HYPERLINK("http://dx.doi.org/10.1029/2023EA002964","http://dx.doi.org/10.1029/2023EA002964") -> http://dx.doi.org/10.1029/2023EA002964 | BS29: WOS:001185603600001 | BT29: =HYPERLINK("https%3A%2F%2Fwww.webofscience.com%2Fwos%2Fwoscc%2Ffull-record%2FWOS:001185603600001","View Full Record in Web of Science") -> View Full Record in Web of Science
A30: C | B30: Bhawana; Anilkumar, R; Singh, M; Bharti, R | E30: IEEE | F30: Bhawana; Anilkumar, Ritu; Singh, Manmit; Bharti, Rishikesh | I30: Snow Depth Modelling using Hybrid Optical - SAR Approach | J30: 2024 IEEE INDIA GEOSCIENCE AND REMOTE SENSING SYMPOSIUM, INGARSS | O30: 2024 India Geoscience and Remote Sensing Symposium-INGARSS-Annual | P30: DEC 02-05, 2024 | Q30: INDIA | R30: Institute of Electrical and Electronics Engineers Inc | V30: This study investigates a hybrid Optical-SAR approach for modelling snow depth in North Sikkim, India, a region characterized by complex terrain and frequent cloud cover. By integrating Sentinel-2 multispectral imagery with Sentinel-1 SAR data, the research aims to improve the accuracy and reliability of snow depth estimations. The Gradient Boosting Regression (GBR) model was employed, utilizing key variables such as the Snow Index, SAR backscatter values, and NDVI. The model demonstrated strong predictive performance, with an R-2 of 0.922 and an RMSE of 0.26. The snow depth maps generated are essential for hydrological planning, disaster management, and climate studies, offering valuable insights into snow dynamics in challenging environments. This approach highlights the potential of combining optical and radar data with machine learning techniques for enhanced environmental monitoring. | AA30: ; Bharti, Rishikesh/S-5002-2019; Anilkumar, Ritu/GXZ-7944-2022 | AB30: Singh, Manmit/0000-0002-1679-236X; Anilkumar, Ritu/0000-0003-2695-6409 | AQ30: 979-8-3503-9035-3; 979-8-3503-9034-6 | AU30: 2024 | BB30: 752 | BC30: 755 | BE30: 10.1109/InGARSS61818.2024.10984375 | BF30: =HYPERLINK("http://dx.doi.org/10.1109/InGARSS61818.2024.10984375","http://dx.doi.org/10.1109/InGARSS61818.2024.10984375") -> http://dx.doi.org/10.1109/InGARSS61818.2024.10984375 | BS30: WOS:001515777600207 | BT30: =HYPERLINK("https%3A%2F%2Fwww.webofscience.com%2Fwos%2Fwoscc%2Ffull-record%2FWOS:001515777600207","View Full Record in Web of Science") -> View Full Record in Web of Science
A31: J | B31: Gallet, M; Atto, A; Karbou, F; Trouve, E | F31: Gallet, Matthieu; Atto, Abdourrahmane; Karbou, Fatima; Trouve, Emmanuel | I31: Wet Snow Detection From Satellite SAR Images by Machine Learning With Physical Snowpack Model Labeling | J31: IEEE JOURNAL OF SELECTED TOPICS IN APPLIED EARTH OBSERVATIONS AND REMOTE SENSING | V31: The detection of wet snow by satellite imaging is currently done in an unsupervised way and lacks quantitative evaluation due to the difficulty of collecting ground truths in extreme environments. In this article, we propose to take into account information associated with a physical model to label satellite data for the purpose of supervised learning of snow properties using synthetic aperture radar (SAR) imagery. This dataset is constructed from Sentinel-1 SAR images, augmented with topographic information obtained from a digital elevation model. The labeling of this data is done at the scale of the Northern Alps using the CROCUS physical snow model. Then, we trained, over 13 combinations of labeled dataset, a wide range of machine learning models to quantitatively identify the most relevant learners for the wet snow detection task. The results demonstrate consistency among the different algorithms, with significant improvement observed when incorporating polarimetric combinations and topographic orientation data in the input of the model. The best algorithmic solution trained on this dataset is evaluated by comparing the obtained wet snow map over a validation area in the French massif of the Grandes Rousses with the existing Copernicus products, fractional snow cover, and SAR wet snow. We also compare the temporal results obtained at one meteorological station located in the test area. The results show a better representation of wet snow during the melting period using the supervised learning approach, as well as a reduction in areas classified as wet during the winter season. | AA31: Gallet, Matthieu/KPB-7063-2024; Karbou, Fatima/AAF-1870-2019 | AB31: Gallet, Matthieu/0009-0005-3094-0532; Trouvé, Emmanuel/0000-0003-2140-3303; Karbou, Fatima/0000-0003-3499-2557 | AO31: 1939-1404 | AP31: 2151-1535 | AU31: 2024 | AV31: 17 | BB31: 2901 | BC31: 2917 | BE31: 10.1109/JSTARS.2023.3342990 | BF31: =HYPERLINK("http://dx.doi.org/10.1109/JSTARS.2023.3342990","http://dx.doi.org/10.1109/JSTARS.2023.3342990") -> http://dx.doi.org/10.1109/JSTARS.2023.3342990 | BS31: WOS:001144739300006 | BT31: =HYPERLINK("https%3A%2F%2Fwww.webofscience.com%2Fwos%2Fwoscc%2Ffull-record%2FWOS:001144739300006","View Full Record in Web of Science") -> View Full Record in Web of Science
A32: C | B32: Himmele, G; Joseph, A; Ofekeze, E; Pinder, N; Miller, R; Jain, A; Vuyovich, C; Espada, K | E32: IEEE | F32: Himmele, Gabriela; Joseph, Alicia; Ofekeze, Evi; Pinder, Nicholas; Miller, Ryan; Jain, Aditya; Vuyovich, Carrie; Espada, Kari | I32: USING UNSUPERVISED MACHINE LEARNING METHODS AND THE NASA SNOWEX SWESARR INSTRUMENT TO STUDY HOW SNOW WATER EQUIVALENT IS CHANGING WITH CLIMATE CHANGE | J32: IGARSS 2024-2024 IEEE INTERNATIONAL GEOSCIENCE AND REMOTE SENSING SYMPOSIUM, IGARSS 2024 | K32: IEEE International Symposium on Geoscience and Remote Sensing IGARSS | O32: IEEE International Geoscience and Remote Sensing Symposium (IGARSS) | P32: JUL 07-12, 2024 | Q32: Athens, GREECE | R32: Inst Elect & Elect Engineers,Inst Elect & Elect Engineers, Geoscience & Remote Sensing Soc | V32: The Snow Water Equivalent Synthetic Aperture Radar and Radiometer ( SWESARR) is a dual microwave instrument meant to fill in information gaps in the remote sensing data of Snow Water Equivalent (SWE). The aim of this work is to improve and validate SWESARR measurements of SWE for areas with tree canopy using unsupervised machine learning methods. This information is critical to NASA's SnowEx mission for understanding the spatial and temporal variability of snow. SWE is an integral part of the climate system and affects many other climate-related processes, thus an accurate understanding of how SWE is changing with climate change is crucial for future water resource management. We have made use of a suite of parameters to help in identifying features most important in predicting SWE in areas that have missing satellite data due to vegetation. Our aim is to validate and improve SWESARR measurements using unsupervised machine learning clustering algorithms with the goal of being able to better quantify spatial and temporal changes of SWE due to climate change. Other relevant datasets that have been central to identifying parameters for predicting SWE and data validation have been from the ASO (Airborne Snow Observatory), NSIDC (National Snow and Ice Data Center), and ground snow pit observations taken by the SnowEx field work team. This work is a result of NASA's SnowEx team based out of Goddard Space Flight Center within the Climate Change Research Initiative at NASA GISS. | AO32: 2153-6996 | AQ32: 979-8-3503-6033-2; 979-8-3503-6032-5 | AU32: 2024 | BB32: 1869 | BC32: 1872 | BE32: 10.1109/IGARSS53475.2024.10641609 | BF32: =HYPERLINK("http://dx.doi.org/10.1109/IGARSS53475.2024.10641609","http://dx.doi.org/10.1109/IGARSS53475.2024.10641609") -> http://dx.doi.org/10.1109/IGARSS53475.2024.10641609 | BS32: WOS:001316158502060 | BT32: =HYPERLINK("https%3A%2F%2Fwww.webofscience.com%2Fwos%2Fwoscc%2Ffull-record%2FWOS:001316158502060","View Full Record in Web of Science") -> View Full Record in Web of Science
A33: J | B33: Johnston, J; Jacobs, JM; Cho, ES | F33: Johnston, Jeremy; Jacobs, Jennifer M.; Cho, Eunsang | I33: Global Snow Seasonality Regimes from Satellite Records of Snow Cover | J33: JOURNAL OF HYDROMETEOROLOGY | V33: Snow cover provides distinct seasonal controls on the exchange of energy between Earth's surface and atmosphere, and on hydrologic cycling, and holds considerable importance to communities and ecosystems worldwide. In this work, we tackle a comprehensive review of existing snow classification approaches and the development of new glob-ally applicable snow cover-based rules for delineating snow seasonality classes. Snow classification rules are defined using machine learning approaches, which are then applied to the 22-yr record of snow cover (2000-22) from the Moderate Res-olution Imaging Spectroradiometer (MODIS) on a 0.018 global grid. For the MODIS period of record, we find the global land surface can be effectively partitioned into five snow seasonality classes: no snow, ephemeral, transitional, seasonal, and perennial snow regimes which on average cover extents of approximately 76 (52% of global land areas), 19 (13%), 16 (11%), 18 (13%), and 16 million km2 (11%), respectively. Using the multidecadal dataset, we explore changes within snow regimes and find significant increases in the areal extent of no snow (approximately 170000 km2 yr-1) as well as apparent losses in perennial (-3600 km2 yr-1) and seasonal snow regime coverage (-38000 km2 yr-1). The resulting classification maps have strong agreement with in situ snow depth observations and present similar patterns to existing snow and climate classifications with notable discrepancies in cold arid regions. The framework's ability to accurately capture variations in snow persistence, snow accumulation, and melt cycling is shown, providing a reference to the current state of global snow seasonality. | AA33: ; Johnston, Jeremy/AAZ-5052-2020 | AB33: Jacobs, Jennifer/0000-0003-3824-6439; Johnston, Jeremy/0000-0001-7895-6377 | AO33: 1525-755X | AP33: 1525-7541 | AT33: JAN | AU33: 2024 | AV33: 25 | AW33: 1 | BB33: 65 | BC33: 88 | BE33: 10.1175/JHM-D-23-0047.1 | BF33: =HYPERLINK("http://dx.doi.org/10.1175/JHM-D-23-0047.1","http://dx.doi.org/10.1175/JHM-D-23-0047.1") -> http://dx.doi.org/10.1175/JHM-D-23-0047.1 | BS33: WOS:001131597600001 | BT33: =HYPERLINK("https%3A%2F%2Fwww.webofscience.com%2Fwos%2Fwoscc%2Ffull-record%2FWOS:001131597600001","View Full Record in Web of Science") -> View Full Record in Web of Science
A34: C | B34: Joseph, A; Himmele, G; Pearce, M; Pinder, N; Jain, A; Espada, K; Conway, J; Mason, M; Vuyovichi, C | E34: IEEE | F34: Joseph, Alicia; Himmele, Gabriela; Pearce, Matthew; Pinder, Nicholas; Jain, Aditya; Espada, Kari; Conway, Joy; Mason, Megan; Vuyovichi, Carrie | I34: INTEGRATING EARLY CAREER STEM RESEARCH THROUGH MACHINE LEARNING BY THE NASA CLIMATE CHANGE RESEARCH INITIATIVE (CCRI) | J34: IGARSS 2024-2024 IEEE INTERNATIONAL GEOSCIENCE AND REMOTE SENSING SYMPOSIUM, IGARSS 2024 | K34: IEEE International Symposium on Geoscience and Remote Sensing IGARSS | O34: IEEE International Geoscience and Remote Sensing Symposium (IGARSS) | P34: JUL 07-12, 2024 | Q34: Athens, GREECE | R34: Inst Elect & Elect Engineers,Inst Elect & Elect Engineers, Geoscience & Remote Sensing Soc | V34: Satellites are particularly well-suited to provide spatially distributed observations of global snow. For hydrological research and applications, Snow Water Equivalent (SWE) is the most important observation, but it is also our biggest gap in snow remote sensing. Currently, no satellite sensor has the ability to measure SWE globally at the accuracy, resolution and frequency needed, because of a number of factors that impact the signals such as forests, mountains, clouds and the snow characteristics themselves. The NASA Climate Change Research Initiative (CCRI) SnowEx team uses machine learning approaches to attempt to address the unanswered questions of snow science. The team has collaborated with other similar NASA wide programs and leveraged skills and resources which led to the formation of a community machine learning (ML) working group. | AO34: 2153-6996 | AQ34: 979-8-3503-6033-2; 979-8-3503-6032-5 | AU34: 2024 | BB34: 1873 | BC34: 1877 | BE34: 10.1109/IGARSS53475.2024.10642493 | BF34: =HYPERLINK("http://dx.doi.org/10.1109/IGARSS53475.2024.10642493","http://dx.doi.org/10.1109/IGARSS53475.2024.10642493") -> http://dx.doi.org/10.1109/IGARSS53475.2024.10642493 | BS34: WOS:001316158502061 | BT34: =HYPERLINK("https%3A%2F%2Fwww.webofscience.com%2Fwos%2Fwoscc%2Ffull-record%2FWOS:001316158502061","View Full Record in Web of Science") -> View Full Record in Web of Science
A35: J | B35: Liu, X; Kan, X; Zhang, YH; Zhu, LL; Liu, Q; Zhou, Z; Ma, GY | F35: Liu, Xu; Kan, Xi; Zhang, Yonghong; Zhu, Linglong; Liu, Qi; Zhou, Zhou; Ma, Guangyi | I35: FSC-USNet: Fractional Snow Cover Retrieval on the Tibetan Plateau by Integrating Improved Attention Mechanisms | J35: IEEE JOURNAL OF SELECTED TOPICS IN APPLIED EARTH OBSERVATIONS AND REMOTE SENSING | V35: Snow on the Tibetan Plateau (TP) is not only a freshwater resource for the major rivers in Asia but also plays a significant role in adjusting temperature by reflecting solar radiation. Fractional snow cover mapping with fine spatial and temporal resolution is of great significance for clarifying snow resources and accurately managing snow water resources. However, due to the complex TP topography, the existing fractional snow cover (FSC) retrieval methods are affected by a variety of disturbance factors, resulting in a decrease in accuracy. In this study, a deep learning-based FSC retrieval method, FSC U-shape net, is proposed to improve snow cover mapping accuracy. The input images of FengYun-4A advanced geosynchronous radiation imager and geographic data are extracted using the proposed spatial-channel feature extraction module to characterize the shallow features with texture information into high-dimensional feature images. Additionally, an attention mechanism is introduced to improve the feature differences between different FSC degrees. Finally, the correlation of the decoded features in the channel direction is mined using the channel refinement module to obtain the final FSC results. In this study, a backpropagation artificial neural network, random forest, ResNet_FSC, and UNet are trained, compared, and validated against the MOA10A1 FSC product. The results show that the proposed method effectively mitigates the problems of unclear texture of snow edges, poor robustness, and underestimation in some areas, which exist in other models. Additionally, the proposed method has higher accuracy, with an R-2 and explained variance score reaching 0.7182 and 0.7332, respectively. Compared to the MOD10A1 snow product, the proposed method exhibits higher detection accuracy in mountainous areas with high snow cover and significantly improves the low snow cover detection rate. | AA35: Zhang, Yonghong/PJB-9718-2026 | AB35: Liu, Qi/0000-0002-8485-3582; Kan, Xi/0000-0002-4629-9357; xu, liu/0009-0001-3939-8082 | AO35: 1939-1404 | AP35: 2151-1535 | AU35: 2024 | AV35: 17 | BB35: 10083 | BC35: 10096 | BE35: 10.1109/JSTARS.2024.3360087 | BF35: =HYPERLINK("http://dx.doi.org/10.1109/JSTARS.2024.3360087","http://dx.doi.org/10.1109/JSTARS.2024.3360087") -> http://dx.doi.org/10.1109/JSTARS.2024.3360087 | BS35: WOS:001236723400012 | BT35: =HYPERLINK("https%3A%2F%2Fwww.webofscience.com%2Fwos%2Fwoscc%2Ffull-record%2FWOS:001236723400012","View Full Record in Web of Science") -> View Full Record in Web of Science
A36: C | B36: Santi, E; Pettinato, S; Paloscia, S; Pilia, S; Baroni, F; Ramat, G | E36: IEEE | F36: Santi, Emanuele; Pettinato, Simone; Paloscia, Simonetta; Pilia, Simone; Baroni, Fabrizio; Ramat, Giuliano | I36: INTEGRATION OF ACTIVE AND PASSIVE MULTIFREQUENCY DATA FROM AMSR-2 AND COSMO SKYMED FOR SNOW DEPTH MONITORING AT HIGH RESOLUTION IN ALPINE ENVIRONMENTS | J36: IGARSS 2024-2024 IEEE INTERNATIONAL GEOSCIENCE AND REMOTE SENSING SYMPOSIUM, IGARSS 2024 | K36: IEEE International Symposium on Geoscience and Remote Sensing IGARSS | O36: IEEE International Geoscience and Remote Sensing Symposium (IGARSS) | P36: JUL 07-12, 2024 | Q36: Athens, GREECE | R36: Inst Elect & Elect Engineers,Inst Elect & Elect Engineers, Geoscience & Remote Sensing Soc | V36: This study aims at improving the spatial resolution of snow depth (SD) products derived from microwave satellite radiometers by proposing a disaggregation method based on X- band SAR data. The method has been developed and tested in the Western part of Italian Alps, by involving Cosmo SkyMed (CSK) and AMSR-2 data. Machine learning methods play a twofold role in the proposed active/passive (A/P) implementation: the AMSR-2 data disaggregation process is indeed based on Artificial Neural Networks (ANN), while the SD retrieval using the disaggregated data is based on ANN and Random Forest (RF) algorithms. To assess the effectiveness of the proposed A/P technique, the SD retrievals have been compared with those obtained by estimating SD directly from CSK data. Taking advantage of the multifrequency information, the retrievals based on A/P method clearly outperformed those based on CSK data only: correlation increased from R=0.77 to R= 0.85 for the ANN based retrievals and from 0.76 to 0.86 for the RF based retrievals. The corresponding RMSE decreases from 34 cm to 28 cm and from 34 cm to 27 cm for ANN and RF, respectively, in a SD range between 0 and similar or equal to 220 cm. | AA36: Ramat, Giuliano/ADL-8637-2022; Baroni, Fabrizio/AFE-6939-2022; Pettinato, Simone/H-6051-2019 | AB36: Baroni, Fabrizio/0000-0003-4753-1258; | AO36: 2153-6996 | AQ36: 979-8-3503-6033-2; 979-8-3503-6032-5 | AU36: 2024 | BB36: 631 | BC36: 634 | BE36: 10.1109/IGARSS53475.2024.10642383 | BF36: =HYPERLINK("http://dx.doi.org/10.1109/IGARSS53475.2024.10642383","http://dx.doi.org/10.1109/IGARSS53475.2024.10642383") -> http://dx.doi.org/10.1109/IGARSS53475.2024.10642383 | BS36: WOS:001316158501007 | BT36: =HYPERLINK("https%3A%2F%2Fwww.webofscience.com%2Fwos%2Fwoscc%2Ffull-record%2FWOS:001316158501007","View Full Record in Web of Science") -> View Full Record in Web of Science
A37: C | B37: Santi, E; Pettinato, S; Paloscia, S; Pilia, S; Baroni, F; Ramat, G | D37: Bovenga, F; Notarnicola, C; Pierdicca, N; Santi, E | F37: Santi, Emanuele; Pettinato, Simone; Paloscia, Simonetta; Pilia, Simone; Baroni, Fabrizio; Ramat, Giuliano | I37: High resolution Snow Depth mapping in Alpine environments based on active and passive microwave data integration: a machine learning approach | J37: MICROWAVE REMOTE SENSING: DATA PROCESSING AND APPLICATIONS III | K37: Proceedings of SPIE | O37: 2024 Conference on Microwave Remote Sensing: Data Processing and Applications | P37: SEP 18-19, 2024 | Q37: Edinburgh, SCOTLAND | R37: The International Society for Optics and Photonics | V37: This study aims at improving the spatial resolution of snow depth (SD) products derived from microwave satellite radiometers by proposing a disaggregation method based on X-band SAR data. The method has been developed and tested in the Western part of Italian Alps, by involving Cosmo SkyMed (CSK) and AMSR- 2 data. Machine learning methods play a twofold role in the proposed active/passive (A/P) implementation: the AMSR-2 data disaggregation process is indeed based on Artificial Neural Networks (ANN), while the SD retrieval using the disaggregated data is based on ANN and Random Forest (RF) algorithms. To assess the effectiveness of the proposed A/P technique, the SD retrievals have been compared with those obtained by estimating SD directly from CSK data. Taking advantage of the multifrequency information, the retrievals based on A/P method clearly outperformed those based on CSK data only: correlation increased from R=0.77 to R= 0.85 for the ANN based retrievals and from 0.76 to 0.86 for the RF based retrievals. The corresponding RMSE decreases from 34 cm to 28 cm and from 34 cm to 27 cm for ANN and RF, respectively, in a SD range between 0 and similar or equal to 220 cm. | AA37: Pettinato, Simone/H-6051-2019; Ramat, Giuliano/ADL-8637-2022; Baroni, Fabrizio/AFE-6939-2022 | AB37: Ramat, Giuliano/0000-0003-4125-1634; Baroni, Fabrizio/0000-0003-4753-1258 | AO37: 0277-786X | AP37: 1996-756X | AQ37: 978-1-5106-8098-2; 978-1-5106-8099-9 | AU37: 2024 | AV37: 13195 | BD37: 131950A | BE37: 10.1117/12.3034917 | BF37: =HYPERLINK("http://dx.doi.org/10.1117/12.3034917","http://dx.doi.org/10.1117/12.3034917") -> http://dx.doi.org/10.1117/12.3034917 | BS37: WOS:001519952500006 | BT37: =HYPERLINK("https%3A%2F%2Fwww.webofscience.com%2Fwos%2Fwoscc%2Ffull-record%2FWOS:001519952500006","View Full Record in Web of Science") -> View Full Record in Web of Science
A38: J | B38: Yu, GA; Gu, LJ; Li, XF; Fan, XT | F38: Yu, Guangan; Gu, Lingjia; Li, Xiaofeng; Fan, Xintong | I38: Forest Snow Depth Estimation Based on Optimized Features and DNN Network Using C-Band SAR Data | J38: IEEE GEOSCIENCE AND REMOTE SENSING LETTERS | V38: With the rapid development of remote sensing technology, synthetic aperture radar (SAR) is gradually widely used in snow depth (SD) estimation and serves as a useful complement to optical sensor and passive microwave (PM) sensor for snow remote sensing applications. The selection of parameters and models related to the characteristics of snow in forest is crucial for improving the accuracy of forest SD estimation. The purpose of this letter is to develop a forest SD estimation algorithm based on optimized feature filtering (FF) and deep neural network (DNN) using Sentinel-1 C-band data and other auxiliary data. First, the optimized features are selected from the input dataset using the three FF methods based on machine learning (ML), maximum mutual information coefficient (MMIC), and the proposed Pearson correlation coefficient (PCC). Then, a nonlinear regression method based on DNN was developed to retrieve SD with the optimized features. Comparing results obtained from random forest (RF) algorithm, XGBoost (XGB) algorithm, and recurrent neural network (RNN) algorithm against the meteorological stations and field measured SD data in the forests of Northeast China, the proposed method performs superior with reduced uncertainties. The mean absolute error (MAE), root-mean-square error (RMSE), and coefficient of determination (R-2 ) of the proposed SD estimation method are 2.98 cm, 4.30 cm, and 0.77 for the test dataset, respectively. | AA38: ; li, xiaofeng/GXF-9442-2022 | AB38: Gu, Lingjia/0000-0002-4909-2263; | AO38: 1545-598X | AP38: 1558-0571 | AU38: 2024 | AV38: 21 | BD38: 4006905 | BE38: 10.1109/LGRS.2024.3379202 | BF38: =HYPERLINK("http://dx.doi.org/10.1109/LGRS.2024.3379202","http://dx.doi.org/10.1109/LGRS.2024.3379202") -> http://dx.doi.org/10.1109/LGRS.2024.3379202 | BS38: WOS:001193984600023 | BT38: =HYPERLINK("https%3A%2F%2Fwww.webofscience.com%2Fwos%2Fwoscc%2Ffull-record%2FWOS:001193984600023","View Full Record in Web of Science") -> View Full Record in Web of Science
A39: J | B39: Moradizadeh, M; Alijanian, M; Moeini, R | F39: Moradizadeh, Mina; Alijanian, Mohammadali; Moeini, Ramtin | I39: Spatial Downscaling of Snow Water Equivalent Using Machine Learning Methods Over the Zayandehroud River Basin, Iran | J39: PFG-JOURNAL OF PHOTOGRAMMETRY REMOTE SENSING AND GEOINFORMATION SCIENCE | V39: Snow cover is an informative indicator of climate change and surface hydrological cycles. Despite its essential accurate dynamic measurement (i.e., accumulation, erosion, and runoff), it is poorly known, particularly in mountainous regions. Since passive microwave sensors can contribute to obtaining information about snowpack volume, microwave brightness temperatures (BT) have long been used to assess spatiotemporal variations in snow water equivalent (SWE). However, SWE is greatly influenced by geographic location, terrain parameters/covers, and BT differences, and thus, the low spatial resolution of existing SWE products (i.e., the coarse resolution of AMSR-based products) leads to less satisfactory results, especially in regions with complex terrain conditions, strong seasonal transitions and, great spatiotemporal heterogeneity. A novel multifactor SWE downscaling algorithm based on the support vector regression (SVR) technique has been developed in this study for the Zayandehroud River basin. Thereby, passive microwave BT, location (latitude and longitude), terrain parameters (i.e., elevation, slope, and aspect), and vegetation cover serve as model input data. Evaluation of downscaled SWE estimates against ground-based observations demonstrated that when moving into higher spatial resolution, not only was there no significant decrease in accuracy, but a 4% increase was observed. In addition, this study suggests that integrating passive microwave remote sensing data with other auxiliary data can lead to a more efficient and effective algorithm for retrieving SWE with appropriate spatial resolution over various scales. | AA39: Moradizadeh, Mina/O-2815-2019; /AAL-3480-2021; Moeini, Ramtin/ABB-5201-2020 | AB39: Moradizadeh, Mina/0000-0003-3163-5853; | AO39: 2512-2789 | AP39: 2512-2819 | AT39: OCT | AU39: 2023 | AV39: 91 | AW39: 5 | BB39: 391 | BC39: 404 | BE39: 10.1007/s41064-023-00249-9 | BF39: =HYPERLINK("http://dx.doi.org/10.1007/s41064-023-00249-9","http://dx.doi.org/10.1007/s41064-023-00249-9") -> http://dx.doi.org/10.1007/s41064-023-00249-9 | BH39: JUL 2023 | BS39: WOS:001032089100001 | BT39: =HYPERLINK("https%3A%2F%2Fwww.webofscience.com%2Fwos%2Fwoscc%2Ffull-record%2FWOS:001032089100001","View Full Record in Web of Science") -> View Full Record in Web of Science
A40: J | B40: Gao, S; Li, Z; Zhang, P; Chen, Q; Huang, L; Zhou, JM; Zhao, CJ; Qiao, HW; Zheng, ZJ | F40: Gao, Shuo; Li, Zhen; Zhang, Ping; Chen, Quan; Huang, Lei; Zhou, Jianmin; Zhao, Changjun; Qiao, Haiwei; Zheng, Zhaojun | I40: A novel global snow depth retrieval method considering snow metamorphism and forest influence | J40: REMOTE SENSING OF ENVIRONMENT | V40: Accurate snow depth (SD) information at global scales is highly important for validation and calibration of hydrological model, snowmelt runoff prediction, and global water supplies estimation. Passive microwave remote sensing has been proven to be an efficient method to detect SD at regional or global scales. However, numerous heterogeneous snow property parameters and forest parameters affect the microwave radiation characteristics, which is a great challenge for SD retrieval. In this study, a novel SD retrieval algorithm that comprehensively considered the multiple sensitive factors was developed at global scales by coupling the Microwave Emission Model of Layered Snowpacks (MEMLS) model and machine learning (ML) technique. The exponential correlation length (Pec), snow density (& rho;), and forest cover fraction (fforest) are three sensitive parameters for retrieving SD from passive microwave observations based on the extended Fourier amplitude sensitivity test (EFAST) algorithm. The key parameter Pec, which characterizes the snow microstructure information inside snowpacks, was optimized by minimizing the brightness temperature between satellite observations and microwave radiative transfer model simulations by integrating the MEMLS, forest impact, and atmospheric radiation attenuation. The random forest (RF) ML technique was used, and the optimal combination of independent variables was selected by correlation heatmap and importance ranking of variables. Six selected essential parameters, including Pec, vertical polarized brightness temperature differences between 18.7 and 36.5 GHz, & rho; from ERA5, fforest, elevation, and longitude together with target SD output were used to train the RF model. Seventy percent of the entire data at meteorological stations were randomly chosen to train the RF model, and the remaining 30% were adopted as the validation data from 2013 to 2020 to ensure the mutual independence of training data and validation data. Compared with independent in situ measurements, the overall RMSE of SD is 13.6 cm, which was noticeably lower than those of the international SD remote sensing products and reanalysis datasets, including AMSR2 (36.2 cm), GlobSnow 3.0 (25.3 cm), ERA5 (38.2 cm), and ERA5-land (29.9 cm). The results demonstrated that the new proposed algorithm, by coupling the MEMLS model with the ML technique, could significantly enhance the overall performance in SD retrieval at global scales. | AA40: Qiao, Haiwei/MXK-6360-2025; Zhou, jianmin/PEX-7087-2025; Zhao, Changjun/MIT-4380-2025 | AB40: Qiao, Haiwei/0000-0002-8896-049X; Zhao, Changjun/0000-0002-8981-9009 | AO40: 0034-4257 | AP40: 1879-0704 | AT40: SEP 1 | AU40: 2023 | AV40: 295 | BD40: 113712 | BE40: 10.1016/j.rse.2023.113712 | BF40: =HYPERLINK("http://dx.doi.org/10.1016/j.rse.2023.113712","http://dx.doi.org/10.1016/j.rse.2023.113712") -> http://dx.doi.org/10.1016/j.rse.2023.113712 | BH40: JUL 2023 | BS40: WOS:001044934100001 | BT40: =HYPERLINK("https%3A%2F%2Fwww.webofscience.com%2Fwos%2Fwoscc%2Ffull-record%2FWOS:001044934100001","View Full Record in Web of Science") -> View Full Record in Web of Science
A41: J | B41: Ma, XY; Li, DY; Fang, YW; Margulis, SA; Lettenmaier, DP | F41: Ma, Xiaoyu; Li, Dongyue; Fang, Yiwen; Margulis, Steven A.; Lettenmaier, Dennis P. | I41: Estimating spatiotemporally continuous snow water equivalent from intermittent satellite observations: an evaluation using synthetic data | J41: HYDROLOGY AND EARTH SYSTEM SCIENCES | V41: Accurate estimates of snow water equivalent (SWE) based on remote sensing have been elusive, particularly in mountain areas. However, there now appears to be some potential for direct satellite-based SWE observations along ground tracks that only cover a portion of a spatial domain (e.g., watershed). Fortunately, spatiotemporally continuous meteorological and surface variables could be leveraged to infer SWE in the gaps between satellite ground tracks. Here, we evaluate statistical and machine learning (ML) approaches to performing track-to-area (TTA) transformations of SWE observations in California's upper Tuolumne River watershed using synthetic data. The synthetic SWE measurements are designed to mimic a potential future P-band Signals of Opportunity (P-SoOP) satellite mission with a (along-track) spatial resolution of about 500 m. We construct relationships between multiple meteorological and surface variables and synthetic SWE observations along observation tracks, and we then extend these relationships to unobserved areas between ground tracks to estimate SWE over the entire watershed. Domain-wide, SWE inferred on 1 April using two synthetic satellite tracks (similar to 4.5 % basin coverage) led to percent errors of basin-averaged SWE (PEBAS) of 24.5 %, 4.5 % and 6.3 % in an extremely dry water year (WY2015), a normal water year (WY2008) and an extraordinarily wet water year (WY2017), respectively. Assuming a 10 d overpass interval, percent errors of basin-averaged SWE during both snow accumulation and snowmelt seasons were mostly less than 10 %. We employ a feature sensitivity analysis to overcome the black-box nature of ML methods and increase the explainability of the ML results. Our feature sensitivity analysis shows that precipitation is the dominant variable controlling the TTA SWE estimation, followed by net long-wave radiation (NetLong). We find that a modest increase in the accuracy of SWE estimation occurs when more than two ground tracks are leveraged. The accuracy of 1 April SWE estimation is only modestly improved for track repeats more often than about 15 d. | AA41: Li, Dongyue/V-7975-2019; lettenmaier, dennis/F-8780-2011; Margulis, Steve/HOH-0155-2023; Ma, Xiaoyu/ABG-5188-2022 | AB41: Ma, Xiaoyu/0000-0001-9747-5907 | AO41: 1027-5606 | AP41: 1607-7938 | AT41: JAN 2 | AU41: 2023 | AV41: 27 | AW41: 1 | BB41: 21 | BC41: 38 | BE41: 10.5194/hess-27-21-2023 | BF41: =HYPERLINK("http://dx.doi.org/10.5194/hess-27-21-2023","http://dx.doi.org/10.5194/hess-27-21-2023") -> http://dx.doi.org/10.5194/hess-27-21-2023 | BS41: WOS:000906405200001 | BT41: =HYPERLINK("https%3A%2F%2Fwww.webofscience.com%2Fwos%2Fwoscc%2Ffull-record%2FWOS:000906405200001","View Full Record in Web of Science") -> View Full Record in Web of Science
A42: C | B42: Gallet, M; Atto, A; Trouvé, E; Karbou, F | E42: IEEE | F42: Gallet, Matthieu; Atto, Abdourrahmane; Trouve, Emmanuel; Karbou, Fatima | I42: CNN CLASSIFICATION OF WET SNOW BY PHYSICAL SNOWPACK MODEL LABELING | J42: IGARSS 2023 - 2023 IEEE INTERNATIONAL GEOSCIENCE AND REMOTE SENSING SYMPOSIUM | K42: IEEE International Symposium on Geoscience and Remote Sensing IGARSS | O42: IEEE International Geoscience and Remote Sensing Symposium (IGARSS) | P42: JUL 16-21, 2023 | Q42: Pasadena, CA | R42: IEEE,Inst Elect & Elect Engineers, Geoscience & Remote Sensing Soc | V42: We propose a new approach for wet snow extent mapping in Synthetic Aperture Radar (SAR) images by using a convolutional neural network (CNN) designed to learn with respect to snowpack outputs from the state-of-the-art snow model Crocus. The CNN was trained to classify the wet snow conditions based on features extracted from the SAR images, using both the VV,VH channel and the ratio between these channels and those of a reference image in summer. One of the key points of this work is the comprehensive comparison we have made between the performance of the CNN method and other advanced statistical methods. We found that the CNN was able to achieve good accuracy in wet snow classification, and giving a complementary vision of the solutions obtained by other machine learning algorithms such as the Random Forest classifier. The results of this study demonstrate the potential of using CNNs and SAR images for wet snow classification and highlight the importance of using physical information model for training machine learning models in snow state identification, a domain where collecting ground truth is intricate due to the complexity of the snowpack moisture measurement systems. | AA42: Gallet, Matthieu/KPB-7063-2024 | AB42: Gallet, Matthieu/0009-0005-3094-0532 | AO42: 2153-6996 | AQ42: 979-8-3503-2010-7 | AU42: 2023 | BB42: 5351 | BC42: 5354 | BE42: 10.1109/IGARSS52108.2023.10281833 | BF42: =HYPERLINK("http://dx.doi.org/10.1109/IGARSS52108.2023.10281833","http://dx.doi.org/10.1109/IGARSS52108.2023.10281833") -> http://dx.doi.org/10.1109/IGARSS52108.2023.10281833 | BS42: WOS:001098971605133 | BT42: =HYPERLINK("https%3A%2F%2Fwww.webofscience.com%2Fwos%2Fwoscc%2Ffull-record%2FWOS:001098971605133","View Full Record in Web of Science") -> View Full Record in Web of Science
A43: J | B43: Palermo, G; Raparelli, E; Tuccella, P; Orlandi, M; Marzano, FS | F43: Palermo, Gianluca; Raparelli, Edoardo; Tuccella, Paolo; Orlandi, Massimo; Marzano, Frank Silvio | I43: Using Artificial Neural Networks to Couple Satellite C-Band Synthetic Aperture Radar Interferometry and Alpine3D Numerical Model for the Estimation of Snow Cover Extent, Height, and Density | J43: IEEE JOURNAL OF SELECTED TOPICS IN APPLIED EARTH OBSERVATIONS AND REMOTE SENSING | V43: This work presents a new approach for the estimation of snow extent, height, and density in complex orography regions, which combines differential interferometric synthetic-aperture-radar (DInSAR) data and snowpack numerical model data through artificial neural networks (ANNs). The estimation method, subdivided into classification and estimation, is based on two ANNs trained by a DInSAR response model coupled with Alpine3D snow cover numerical model outputs. Auxiliary satellite training data from satellite visible-infrared MODIS imager as well as digital elevation and land cover models are used to discriminate wet and dry snow areas. For snow cover classification the ANN-based estimation methodology is combined with fuzzy-logic and compared with a consolidated decision threshold approach using C-band SAR backscattering information. For snow height (SH) and density estimation, the proposed methodology is compared with an analytical inverse method and two model-based statistical techniques (linear regression and maximum likelihood). The validation is carried out in Central Apennines, a mountainous area in Italy with an extension of about 104 km(2) and peaks up to 2912 m, using in situ data collected between December 2018 and February 2019. Results show that the ANN-based technique has a snow cover area classification accuracy of more than 80% when compared MODIS maps. Estimation bias and root mean square error are equal to about 0.5 cm and 20 cm for SH and to 5 kg/m(3) and 80 kg/m(3) for snow density. As expected, worse results are associated with low DInSAR coherence between two repeat passes and snow melting periods. | AA43: PALERMO, GIANLUCA/U-5867-2019; Tuccella, Paolo/O-7092-2016; Marzano, Frank/X-9052-2018 | AB43: Orlandi, Massimo/0000-0002-7698-2990; Raparelli, Edoardo/0000-0003-4283-0996 | AO43: 1939-1404 | AP43: 2151-1535 | AU43: 2023 | AV43: 16 | BB43: 2868 | BC43: 2888 | BE43: 10.1109/JSTARS.2023.3253804 | BF43: =HYPERLINK("http://dx.doi.org/10.1109/JSTARS.2023.3253804","http://dx.doi.org/10.1109/JSTARS.2023.3253804") -> http://dx.doi.org/10.1109/JSTARS.2023.3253804 | BS43: WOS:000989479900003 | BT43: =HYPERLINK("https%3A%2F%2Fwww.webofscience.com%2Fwos%2Fwoscc%2Ffull-record%2FWOS:000989479900003","View Full Record in Web of Science") -> View Full Record in Web of Science
A44: C | B44: Pan, FB; Jiang, LM | E44: IEEE | F44: Pan, Fangbo; Jiang, Lingmei | I44: DEEP LEARNING BASED CLOUD DETECTION FOR FY-4A/AGRI SNOW MAPPING CONSIDERING CLOUD AND SNOW SPECTRAL CHARACTERISTICS | J44: IGARSS 2023 - 2023 IEEE INTERNATIONAL GEOSCIENCE AND REMOTE SENSING SYMPOSIUM | K44: IEEE International Symposium on Geoscience and Remote Sensing IGARSS | O44: IEEE International Geoscience and Remote Sensing Symposium (IGARSS) | P44: JUL 16-21, 2023 | Q44: Pasadena, CA | R44: IEEE,Inst Elect & Elect Engineers, Geoscience & Remote Sensing Soc | V44: Cloud detection is the first step in remote sensing surface parameter retrieval. Due to the similar spectral properties of cloud and snow, cloud products commonly used in snow monitoring sensors have a certain degree of cloud and snow misjudgment problem. With the launch of a new generation of geostationary satellite (such as China's FY-4A), its time resolution is 15 minutes, and high-frequency observations make accurate cloud and snow identification possible. This study utilizes the high-frequency and multispectral observation characteristics of FY4A, combining the multi band threshold method with deep learning algorithm, to fully explore the spectral and texture differences of cloud and snow, as well as the characteristics of rapid cloud changes, and achieve high-precision cloud detection. Then, the CALIPSO data is used to evaluate the accuracy of the new algorithm's detection results. From the results, the new algorithm for cloud and snow recognition is more accurate and consistent with CALIPSO observations. In terms of specific accuracy indicators, the cloud hit rate(CHR) increase 1.07% and the false alarm rate(FAR) decrease 5.15%. At the same time, both in terms of single scene or daily composite results, the proportion of cloud cover has decreased about 20%, and the proportion of snow cover can increase by up to about 15%. This laid a solid foundation for high-precision fractional snow cover retrieval and spatiotemporal reconstruction in the future. | AA44: Jiang, Lingmei/L-6099-2016; Pan, Fangbo/IQU-2803-2023 | AO44: 2153-6996 | AQ44: 979-8-3503-2010-7 | AU44: 2023 | BB44: 98 | BC44: 101 | BE44: 10.1109/IGARSS52108.2023.10281481 | BF44: =HYPERLINK("http://dx.doi.org/10.1109/IGARSS52108.2023.10281481","http://dx.doi.org/10.1109/IGARSS52108.2023.10281481") -> http://dx.doi.org/10.1109/IGARSS52108.2023.10281481 | BS44: WOS:001098971600026 | BT44: =HYPERLINK("https%3A%2F%2Fwww.webofscience.com%2Fwos%2Fwoscc%2Ffull-record%2FWOS:001098971600026","View Full Record in Web of Science") -> View Full Record in Web of Science
A45: J | B45: Tanniru, S; Ramsankaran, RAAJ | F45: Tanniru, Srinivasarao; Ramsankaran, R. A. A. J. | I45: Machine Learning-Based Estimation of High-Resolution Snow Depth in Alaska Using Passive Microwave Remote Sensing Data | J45: IEEE JOURNAL OF SELECTED TOPICS IN APPLIED EARTH OBSERVATIONS AND REMOTE SENSING | V45: Snow depth (SD) knowledge is significant in many applications related to hydrology, climate, and disaster management. Many SD models are developed using multifrequency spaceborne passive microwave (PMW) brightness temperature (Tb) observations because of their sensitivity to SD. The sensitivity of Tb to SD is affected by snow metamorphism, which constrains the utility of several empirical and conceptual models for estimating SD. For the first time, extremely randomized trees (ERT), a machine learning algorithm, which is less susceptible to data noise, is used in this study for estimatingSDat high resolution (1kmx1 km) forAlaska. Different ERT SD models (i.e., Alaska wide model, zonal model) are developed using Advanced Microwave Scanning Radiometer-2 data and auxiliary datasets for various Alaska regions during 2012-2021. Thesemodels are evaluated using three different crossvalidations (i.e., sample, spatial, and temporal). Further, ERT models' predictive power assessment is performed using independent spatial, temporal datasets. The results indicate that: 1) inclusion of auxiliary parameters improves the accuracy of ERT SD estimates; 2) there is no substantial difference between the zonal and Alaska wide ERT model estimates; 3) when SD >30 cm, the ERT models have outperformed the AMSR-2 product, the GlobSnow product, and the Chang model; 4) the mean absolute error in SD estimates increases with a decrease in latitude, an increase in elevation, and from early winter to late winter across Alaska. Overall, this study shows that the ERT SD model has good potential for improving moderate to deep SD estimates. | AA45: Tanniru, SrinivasaRao/F-1862-2013; Ramsankaran, RAAJ/B-9198-2008 | AB45: Tanniru, SrinivasaRao/0000-0002-6632-6893; Ramsankaran, RAAJ/0000-0001-8602-1934 | AO45: 1939-1404 | AP45: 2151-1535 | AU45: 2023 | AV45: 16 | BB45: 6007 | BC45: 6025 | BE45: 10.1109/JSTARS.2023.3287410 | BF45: =HYPERLINK("http://dx.doi.org/10.1109/JSTARS.2023.3287410","http://dx.doi.org/10.1109/JSTARS.2023.3287410") -> http://dx.doi.org/10.1109/JSTARS.2023.3287410 | BS45: WOS:001029274100023 | BT45: =HYPERLINK("https%3A%2F%2Fwww.webofscience.com%2Fwos%2Fwoscc%2Ffull-record%2FWOS:001029274100023","View Full Record in Web of Science") -> View Full Record in Web of Science
A46: J | B46: Yu, X; Hu, X; Wang, GQ; Wang, KC; Chen, XL | F46: Yu, Xiao; Hu, Xie; Wang, Guoquan; Wang, Kaicun; Chen, Xuelong | I46: Machine-Learning Estimation of Snow Depth in 2021 Texas Statewide Winter Storm Using SAR Imagery | J46: GEOPHYSICAL RESEARCH LETTERS | V46: The frequency of extreme climate events has escalated since 1980. In February 2021, an unprecedented winter storm dumped the snow record in Texas. It claimed hundreds of lives and evolved into a national major disaster. However, we still lack a systematic approach to quantify large-scale snow depth. Here, we use the differential coherence from Sentinel-1 synthetic aperture radar (SAR) imagery to characterize the surface disturbance due to this winter storm. We further rely on machine-learning algorithms to quantify Texas statewide snow depth using surface disturbance map, SAR amplitude, precipitation, temperature, surface topography, land cover, and population. Our approach can provide an independent snow depth estimation. Approximately 89% of Texas accumulated over 30-mm snow depth. The SAR and machine-learning integrated methods can also be applied to quantify other forms of surface disturbance and to ultimately help natural hazard mitigation. | AA46: Wang, Kaicun/F-7813-2012; Chen, Xuelong/C-2748-2014 | AB46: Wang, Kaicun/0000-0002-7414-5400; Chen, Xuelong/0000-0003-3892-5298; Yu, Xiao/0000-0003-4891-1260; Hu, Xie/0000-0002-6744-7291 | AO46: 0094-8276 | AP46: 1944-8007 | AT46: SEP 16 | AU46: 2022 | AV46: 49 | AW46: 17 | BD46: e2022GL099119 | BE46: 10.1029/2022GL099119 | BF46: =HYPERLINK("http://dx.doi.org/10.1029/2022GL099119","http://dx.doi.org/10.1029/2022GL099119") -> http://dx.doi.org/10.1029/2022GL099119 | BS46: WOS:000850889000001 | BT46: =HYPERLINK("https%3A%2F%2Fwww.webofscience.com%2Fwos%2Fwoscc%2Ffull-record%2FWOS:000850889000001","View Full Record in Web of Science") -> View Full Record in Web of Science
A47: J | B47: Yang, CY; Zhang, YH; Xia, M; Lin, HF; Liu, J; Li, Y | F47: Yang, Chaoyun; Zhang, Yonghong; Xia, Min; Lin, Haifeng; Liu, Jia; Li, Yang | I47: Satellite Image for Cloud and Snow Recognition Based on Lightweight Feature Map Attention Network | J47: ISPRS INTERNATIONAL JOURNAL OF GEO-INFORMATION | V47: Cloud and snow recognition technology is of great significance in the field of meteorology, and is also widely used in remote sensing mapping, aerospace, and other fields. Based on the traditional method of manually labeling cloud-snow areas, a method of labeling cloud and snow areas using deep learning technology has been gradually developed to improve the accuracy and efficiency of recognition. In this paper, from the perspective of designing an efficient and lightweight network model, a cloud snow recognition model based on a lightweight feature map attention network (Lw-fmaNet) is proposed to ensure the performance and accuracy of the cloud snow recognition model. The model is improved based on the ResNet18 network with the premise of reducing the network parameters and improving the training efficiency. The main structure of the model includes a shallow feature extraction module, an intrinsic feature mapping module, and a lightweight adaptive attention mechanism. Overall, in the experiments conducted in this paper, the accuracy of the proposed cloud and snow recognition model reaches 95.02%, with a Kappa index of 93.34%. The proposed method achieves an average precision rate of 94.87%, an average recall rate of 94.79%, and an average F1-Score of 94.82% for four sample recognition classification tasks: no snow and no clouds, thin cloud, thick cloud, and snow cover. Meanwhile, our proposed network has only 5.617M parameters and takes only 2.276 s. Compared with multiple convolutional neural networks and lightweight networks commonly used for cloud and snow recognition, our proposed lightweight feature map attention network has a better performance when it comes to performing cloud and snow recognition tasks. | AA47: Xia, Min/AAC-7472-2019; Zhang, Yonghong/PJB-9718-2026 | AB47: Xia, Min/0000-0003-4681-9129; | AP47: 2220-9964 | AT47: JUL | AU47: 2022 | AV47: 11 | AW47: 7 | BD47: 390 | BE47: 10.3390/ijgi11070390 | BF47: =HYPERLINK("http://dx.doi.org/10.3390/ijgi11070390","http://dx.doi.org/10.3390/ijgi11070390") -> http://dx.doi.org/10.3390/ijgi11070390 | BS47: WOS:000833788000001 | BT47: =HYPERLINK("https%3A%2F%2Fwww.webofscience.com%2Fwos%2Fwoscc%2Ffull-record%2FWOS:000833788000001","View Full Record in Web of Science") -> View Full Record in Web of Science
A48: J | B48: Yatheendradas, S; Kumar, S | F48: Yatheendradas, Soni; Kumar, Sujay | I48: A Novel Machine Learning-Based Gap-Filling of Fine-Resolution Remotely Sensed Snow Cover Fraction Data by Combining Downscaling and Regression | J48: JOURNAL OF HYDROMETEOROLOGY | V48: Satellite-based remotely sensed observations of snow cover fraction (SCF) can have data gaps in spatially distributed coverage from sensor and orbital limitations. We mitigate these limitations in the example fine-resolution Moderate Resolution Imaging Spectroradiometer (MODIS) data by gap-filling using auxiliary 1-km datasets that either aid in downscaling from coarser-resolution (5 km) MODIS SCF wherever not fully covered by clouds, or else by themselves via regression wherever fully cloud covered. This study's prototype predicts a 1-km version of the 500-m MOD10A1 SCF target. Due to noncollocatedness of spatial gaps even across input and auxiliary datasets, we consider a recent gap-agnostic advancement of partial convolution in computer vision for both training and predictive gap-filling. Partial convolution accommodates spatially consistent gaps across the input images, effectively implementing a two-dimensional masking. To overcome reduced usable data from noncollocated spatial gaps across inputs, we innovate a fully generalized three-dimensional masking in this partial convolution. This enables a valid output value at a pixel even if only a single valid input variable and its value exist in the neighborhood covered by the convolutional filter zone centered around that pixel. Thus, our gap-agnostic technique can use significantly more examples for training (similar to 67%) and prediction (similar to 100%), instead of only less than 10% for the previous partial convolution. We train an example simple three-layer legacy super-resolution convolutional neural network (SRCNN) to obtain downscaling and regression component performances that are better than baseline values of either climatology or MOD10C1 SCF as relevant. Our generalized partial convolution can enable multiple Earth science applications like downscaling, regression, classification, and segmentation that were hindered by data gaps. | AA48: KUMAR, SUJAY/B-8142-2015 | AB48: KUMAR, SUJAY/0000-0001-8797-9482 | AO48: 1525-755X | AP48: 1525-7541 | AT48: MAY | AU48: 2022 | AV48: 23 | AW48: 5 | BB48: 637 | BC48: 658 | BE48: 10.1175/JHM-D-20-0111.1 | BF48: =HYPERLINK("http://dx.doi.org/10.1175/JHM-D-20-0111.1","http://dx.doi.org/10.1175/JHM-D-20-0111.1") -> http://dx.doi.org/10.1175/JHM-D-20-0111.1 | BS48: WOS:000814991800001 | BT48: =HYPERLINK("https%3A%2F%2Fwww.webofscience.com%2Fwos%2Fwoscc%2Ffull-record%2FWOS:000814991800001","View Full Record in Web of Science") -> View Full Record in Web of Science
A49: J | B49: Luo, JF; Dong, CY; Lin, KR; Chen, XH; Zhao, LQ; Menzel, L | F49: Luo, Jianfeng; Dong, Chunyu; Lin, Kairong; Chen, Xiaohong; Zhao, Liqiang; Menzel, Lucas | I49: Mapping snow cover in forests using optical remote sensing, machine learning and time-lapse photography | J49: REMOTE SENSING OF ENVIRONMENT | V49: The accurate spatial information of snow cover is useful for understanding the impact of global warming, and it is of high significance for hydrological disaster prediction, water resources management, and climate change research. The Normalized Difference Snow Index (NDSI) based approach has been used extensively around the world for mapping snow, and they displayed high accuracy in open areas. However, capturing snow cover in forests remains problematic due to the obstruction effects of the forest canopy, which causes the snow cover area to be seriously underestimated. In this paper, we present a new algorithm based on machine learning (ML) technology to improve the accuracy of binary snow cover (BSC) mapping in forests, using the remotely sensed surface reflectance and ground truth data. A time-lapse photography network with a two-hour resolution was established in the eastern Qilian Mountains in northwestern China to obtain the ground truth data both in forests and open areas. We trained Random Forests (RF) with the 500-m Moderate Resolution Imaging Spectroradiometer (MODIS) reflectance data from bands 1-7 to generate BSC results (RF-BSC). Then we evaluated RF-BSC and the NDSI-derived BSC maps with three different NDSI thresholds (i.e., 0.10, 0.29, and 0.40) against ground truth data. The results indicate that the proposed algorithm has a high performance in forest BSC mapping in this area, compared to the NDSI-threshold approach. The RF-BSC can retrieve 67% of all real forest snow pixels, while the NDSI-based BSC can only detect 8-14%. We also find that the performance of the algorithm seems to be sensitive to changes in solar illumination conditions and forest coverage. This study suggests that machine learning with the fusion of optical remote sensing and ground-based observations is an effective approach for improving the accuracy of forest snow cover mapping at regional scales. | AA49: Menzel, Lucas/A-6881-2018; Dong, Chunyu/P-1741-2019 | AB49: Menzel, Lucas/0000-0002-2201-3406; Luo, Jianfeng/0000-0001-8344-7016; Dong, Chunyu/0000-0001-5721-9247 | AO49: 0034-4257 | AP49: 1879-0704 | AT49: JUN 15 | AU49: 2022 | AV49: 275 | BD49: 113017 | BE49: 10.1016/j.rse.2022.113017 | BF49: =HYPERLINK("http://dx.doi.org/10.1016/j.rse.2022.113017","http://dx.doi.org/10.1016/j.rse.2022.113017") -> http://dx.doi.org/10.1016/j.rse.2022.113017 | BH49: APR 2022 | BS49: WOS:000798981000003 | BT49: =HYPERLINK("https%3A%2F%2Fwww.webofscience.com%2Fwos%2Fwoscc%2Ffull-record%2FWOS:000798981000003","View Full Record in Web of Science") -> View Full Record in Web of Science
A50: J | B50: Yang, KH; Musselman, KN; Rittger, K; Margulis, SA; Painter, TH; Molotch, NP | F50: Yang, Kehan; Musselman, Keith N.; Rittger, Karl; Margulis, Steven A.; Painter, Thomas H.; Molotch, Noah P. | I50: Combining ground-based and remotely sensed snow data in a linear regression model for real-time estimation of snow water equivalent | J50: ADVANCES IN WATER RESOURCES | V50: Effective water resources management in California relies substantially on real-time information of snow water equivalent (SWE) at basin scale and mountain ranges given that mountain snowpacks provide the primary water supply for the State. However, SWE estimation based solely on remote sensing, modeling, or ground observations does not meet contemporary operational requirements. In this context, this study develops a data-fusion framework that combines multi-source datasets including satellite-observed daily mean fractional snowcovered area (DMFSCA), snow pillow SWE measurements, physiographic data, and historical SWE patterns into a linear regression model (LRM) to improve SWE estimates in real-time. We test two LRMs: a baseline regression model (LRM-baseline) that uses physiographic data and historical SWE patterns as independent variables, and an FSCA-informed regression model (LRM-FSCA) that includes the DMFSCA from Moderate Resolution Imaging Spectroradiometer (MODIS) satellite imagery as an additional independent variable. By incorporating the satellite-observed DMFSCA, LRM-FSCA outperforms LRM-baseline with increased median R-2 from 0.54 to 0.60, and reduced median PBIAS of basin average SWE from 2.6% to 2.2% in the snow pillow SWE cross-validation. LRM-FSCA explains 87% of the variance in the snow course SWE measurements with 0.1% PBIAS, while LRM-baseline explains a lower 81% variance with 1.4% PBIAS, both of which show higher accuracy than SWE estimates from the two operational SWE datasets: the Snow Data Assimilation System (SNODAS, 73% and-2.4%, respectively) and Nationtional Water Model (NWM, 75% and-15.9%, respectively). Additionally, LRM-FSCA explains 85% of the median variance in the Airborne Snow Observatory SWE with-9.2% PBIAS, which is comparable to the LRM-baseline (86% and-11.3%, respectively) and considerably better than SNODAS (64% and 28.2%, respectively) and NWM (33% and-30.1%, respectively). This study shows a substantial model improvement by constraining the geographical and seasonal variation on snow-cover via satellite observation and highlights the values of using multi-source observations in real-time SWE estimation. The developed SWE estimation framework has crucial implications for effective water supply forecasting and management in California, where climate extremes (e.g., droughts and floods) require particularly skillful monitoring practices. | AA50: Yang, Kehan/AAQ-9081-2020; Musselman, Keith/KVB-3328-2024; Margulis, Steve/HOH-0155-2023; Painter, Thomas/AAC-9493-2019 | AB50: Musselman, Keith/0000-0001-8394-491X; MOLOTCH, NOAH/0000-0003-4733-8060; | AO50: 0309-1708 | AP50: 1872-9657 | AT50: FEB | AU50: 2022 | AV50: 160 | BD50: 104075 | BE50: 10.1016/j.advwatres.2021.104075 | BF50: =HYPERLINK("http://dx.doi.org/10.1016/j.advwatres.2021.104075","http://dx.doi.org/10.1016/j.advwatres.2021.104075") -> http://dx.doi.org/10.1016/j.advwatres.2021.104075 | BH50: JAN 2022 | BS50: WOS:000788071300005 | BT50: =HYPERLINK("https%3A%2F%2Fwww.webofscience.com%2Fwos%2Fwoscc%2Ffull-record%2FWOS:000788071300005","View Full Record in Web of Science") -> View Full Record in Web of Science
A51: C | B51: Boyd, DR; Alam, AM; Kurum, M; Gurbuz, AC; Osmanoglu, B | E51: IEEE | F51: Boyd, D. R.; Alam, A. M.; Kurum, M.; Gurbuz, A. C.; Osmanoglu, B. | I51: PRELIMINARY SNOW WATER EQUIVALENT RETRIEVAL OF SNOWEX20 SWESARR DATA | J51: 2022 IEEE INTERNATIONAL GEOSCIENCE AND REMOTE SENSING SYMPOSIUM (IGARSS 2022) | K51: IEEE International Symposium on Geoscience and Remote Sensing IGARSS | O51: IEEE International Geoscience and Remote Sensing Symposium (IGARSS) | P51: JUL 17-22, 2022 | Q51: Kuala Lumpur, MALAYSIA | R51: IEEE | V51: This paper explores the retrieval of snow water equivalent (SWE) through the use of machine learning techniques and active radar data collected over the 2020 SnowEx campaign. The retrieval makes use of active radar measurements provided by NASA's SWESARR instrument for direct sensing of snowpack sensitivity to SWE. The example results show that an RMSE of 1.93 cm can be obtained through a combined use of SAR data with sufficient ancillary data. Such results may indicate successful SWE estimation by means of pairing spaceborne SAR measurements with sufficient auxiliary information. | AA51: Alam, Ahmed Manavi/GZK-8611-2022; Gurbuz, Ali/AAB-5330-2020 | AB51: Alam, Ahmed Manavi/0000-0003-2022-9761; | AO51: 2153-6996 | AQ51: 978-1-6654-2792-0 | AU51: 2022 | BB51: 3927 | BC51: 3930 | BE51: 10.1109/IGARSS46834.2022.9883412 | BF51: =HYPERLINK("http://dx.doi.org/10.1109/IGARSS46834.2022.9883412","http://dx.doi.org/10.1109/IGARSS46834.2022.9883412") -> http://dx.doi.org/10.1109/IGARSS46834.2022.9883412 | BS51: WOS:000920916604024 | BT51: =HYPERLINK("https%3A%2F%2Fwww.webofscience.com%2Fwos%2Fwoscc%2Ffull-record%2FWOS:000920916604024","View Full Record in Web of Science") -> View Full Record in Web of Science
A52: J | B52: Jin, D; Lee, KS; Choi, S; Seong, NH; Jung, D; Sim, S; Woo, J; Jeon, U; Byeon, Y; Han, KS | F52: Jin, Donghyun; Lee, Kyeong-Sang; Choi, Sungwon; Seong, Noh-Hun; Jung, Daeseong; Sim, Suyoung; Woo, Jongho; Jeon, Uujin; Byeon, Yugyeong; Han, Kyung-Soo | I52: An improvement of snow/cloud discrimination from machine learning using geostationary satellite data | J52: INTERNATIONAL JOURNAL OF DIGITAL EARTH | V52: Snow and cloud discrimination is a main factor contributing to errors in satellite-based snow cover. To address the error, satellite-based snow cover performs snow reclassification tests on the cloud pixels of the cloud mask, but the error still remains. Machine Learning (ML) has recently been applied to remote sensing to calculate satellite-based meteorological data, and its utility has been demonstrated. In this study, snow and cloud discrimination errors were analyzed for GK-2A/AMI snow cover, and ML models (Random Forest and Deep Neural Network) were applied to accurately distinguish snow and clouds. The ML-based snow reclassified was integrated with the GK-2A/AMI snow cover through post-processing. We used the S-NPP/VIIRS snow cover and ASOS in situ snow observation data, which are satellite-based snow cover and ground truth data, as validation data to evaluate whether the snow/cloud discrimination is improved. The ML-based integrated snow cover detected 33-53% more snow compared to the GK-2A/AMI snow cover. In terms of performance, the F1-score and overall accuracy of the GK-2A/AMI snow cover was 73.06% and 89.99%, respectively, and those of the integrated snow cover were 76.78-78.28% and 90.93-91.26%, respectively. | AB52: jung, daeseong/0000-0002-0796-5601; jeon, woojin/0000-0003-0499-640X; 우, 종호/0000-0002-4216-8835; Seong, Noh-hun/0000-0002-9371-8104; Sim, Suyoung/0000-0003-4164-1165; 진, 동현/0000-0001-5449-8252; Han, Kyung-Soo/0000-0002-5031-0256; Lee, kyeong-sang/0000-0002-7639-5729 | AO52: 1753-8947 | AP52: 1753-8955 | AU52: 2022 | AV52: 15 | AW52: 1 | BB52: 2355 | BC52: 2375 | BE52: 10.1080/17538947.2022.2152886 | BF52: =HYPERLINK("http://dx.doi.org/10.1080/17538947.2022.2152886","http://dx.doi.org/10.1080/17538947.2022.2152886") -> http://dx.doi.org/10.1080/17538947.2022.2152886 | BS52: WOS:000933403100001 | BT52: =HYPERLINK("https%3A%2F%2Fwww.webofscience.com%2Fwos%2Fwoscc%2Ffull-record%2FWOS:000933403100001","View Full Record in Web of Science") -> View Full Record in Web of Science
A53: C | B53: Paloscia, S; Santi, E; Pettinato, S; Lapini, A; Fontanelli, G; Pilia, S; Baroni, F; Ramat, G; Santurri, L; Notarnicola, C; De Gregorio, L; Cuozzo, G; Tapete, D; Cigna, F | E53: IEEE | F53: Paloscia, S.; Santi, E.; Pettinato, S.; Lapini, A.; Fontanelli, G.; Pilia, S.; Baroni, F.; Ramat, G.; Santurri, L.; Notarnicola, C.; De Gregorio, L.; Cuozzo, G.; Tapete, D.; Cigna, F. | I53: MULTIFREQUENCY SAR DATA FOR ESTIMATING SNOW, SOIL AND VEGETATION PARAMETERS | J53: 2022 IEEE INTERNATIONAL GEOSCIENCE AND REMOTE SENSING SYMPOSIUM (IGARSS 2022) | K53: IEEE International Symposium on Geoscience and Remote Sensing IGARSS | O53: IEEE International Geoscience and Remote Sensing Symposium (IGARSS) | P53: JUL 17-22, 2022 | Q53: Kuala Lumpur, MALAYSIA | R53: IEEE | V53: The research results described in this paper have been obtained in the framework of the 2019-2022 ALGORITMI project between the Italian Space Agency (ASI) and the Institute of Applied Physics of the National Research Council (CNR-IFAC). The focus of the research was the development of innovative algorithms for the estimation of geophysical parameters of soil, snow, and vegetation with the aim of monitoring soil, snow cover and agricultural crop conditions. The estimation of soil moisture, vegetation biomass, snow water equivalent, and crop classification was improved by using retrieval algorithms based on machine- learning approaches and temporal series of SAR images from COSMO-SkyMed (CSK) and Sentinel-1 (S-1) missions, along with optical images from Sentinel-2. This paper provides an overview of the most recent and valuable results obtained during the project. In particular, the validation of soil moisture provided R=0.89 and RMSE=0.025 m(3)/m(3) by integrating data from S-1 and CSK and that one of snow water equivalent gave R=0.85 with RMSE=86.24 mm (CSK HIMAGE) and R=0.86 with RMSE=71.59 mm (CSK PP). Early mapping results showed an almost monotonic progression in overall accuracy over time higher than 90% by increasing the available images. | AA53: Cigna, Francesca/B-9173-2015; Lapini, Alessano/J-6624-2017; Pettinato, Simone/H-6051-2019; santi, emanuele/A-7755-2013; Baroni, Fabrizio/AFE-6939-2022; Ramat, Giuliano/ADL-8637-2022; Tapete, Deodato/AAB-7528-2021 | AB53: Cigna, Francesca/0000-0001-8134-1576; Pilia, Simone/0000-0001-9773-9298; Lapini, Alessano/0000-0002-7711-7229; santi, emanuele/0000-0003-1882-6321; Baroni, Fabrizio/0000-0003-4753-1258; SANTURRI, LEONARDO/0000-0001-7316-643X; | AO53: 2153-6996 | AQ53: 978-1-6654-2792-0 | AU53: 2022 | BB53: 5180 | BC53: 5183 | BE53: 10.1109/IGARSS46834.2022.9884859 | BF53: =HYPERLINK("http://dx.doi.org/10.1109/IGARSS46834.2022.9884859","http://dx.doi.org/10.1109/IGARSS46834.2022.9884859") -> http://dx.doi.org/10.1109/IGARSS46834.2022.9884859 | BS53: WOS:000920916605064 | BT53: =HYPERLINK("https%3A%2F%2Fwww.webofscience.com%2Fwos%2Fwoscc%2Ffull-record%2FWOS:000920916605064","View Full Record in Web of Science") -> View Full Record in Web of Science
A54: J | B54: Santi, E; De Gregorio, L; Pettinato, S; Cuozzo, G; Jacob, A; Notarnicola, C; Günther, D; Strasser, U; Cigna, F; Tapete, D; Paloscia, S | F54: Santi, Emanuele; De Gregorio, Ludovica; Pettinato, Simone; Cuozzo, Giovanni; Jacob, Alexander; Notarnicola, Claudia; Guenther, Daniel; Strasser, Ulrich; Cigna, Francesca; Tapete, Deodato; Paloscia, Simonetta | I54: On the Use of COSMO-SkyMed X-Band SAR for Estimating Snow Water Equivalent in Alpine Areas: A Retrieval Approach Based on Machine Learning and Snow Models | J54: IEEE TRANSACTIONS ON GEOSCIENCE AND REMOTE SENSING | V54: This study aims at estimating the dry snow water equivalent (SWE) by using X-band synthetic aperture radar (SAR) data from the COSMO-SkyMed (CSK) satellite constellation. The time series of CSK acquisitions have been collected during the dry snow period in the Alto Adige test site, in the Italian Alps, during the winter seasons from 2013 to 2015 and from 2019 to 2021. The SAR data have been analyzed and compared with the in situ measurements to understand the X-band SAR sensitivity to SWE, which has been further assessed by dense media radiative transfer (DMRT) model simulations. The sensitivity analysis provided the basis for addressing the SWE retrieval from the CSK data, by exploiting two different machine learning (ML) techniques, namely, artificial neural networks (ANNs) and support vector regression (SVR). To ensure statistical independence of training and validation processes, the algorithms are trained and tested using SWE predictions of the fully distributed snow model AMUNDSEN as reference data and are subsequently validated on the experimental dataset. Due to its influence on the CSK estimates, the effect of forest canopy was accounted for in the analysis. Depending on the algorithm, the validation resulted in a correlation coefficient 0.78 <= R <= 0.91 and a root-mean-square error (RMSE) 55.5 mm <= RMSE <= 87.4 mm between estimated and in situ SWE. Further analysis and validation are needed; however, the obtained results seem suggesting the CSK constellation as an effective tool for the retrieval of the dry SWE in alpine areas. | AA54: ; Tapete, Deodato/AAB-7528-2021; Pettinato, Simone/H-6051-2019; Cigna, Francesca/B-9173-2015; santi, emanuele/A-7755-2013 | AB54: Notarnicola, Claudia/0000-0003-1968-0125; Tapete, Deodato/0000-0002-7242-4473; Cuozzo, Giovanni/0000-0001-9120-7426; Jacob, Alexander/0000-0003-4434-7244; De Gregorio, Ludovica/0000-0003-2022-1479; Günther, Daniel/0000-0001-8268-6998; Cigna, Francesca/0000-0001-8134-1576; santi, emanuele/0000-0003-1882-6321 | AO54: 0196-2892 | AP54: 1558-0644 | AU54: 2022 | AV54: 60 | BD54: 4305419 | BE54: 10.1109/TGRS.2022.3191409 | BF54: =HYPERLINK("http://dx.doi.org/10.1109/TGRS.2022.3191409","http://dx.doi.org/10.1109/TGRS.2022.3191409") -> http://dx.doi.org/10.1109/TGRS.2022.3191409 | BS54: WOS:000831177200001 | BT54: =HYPERLINK("https%3A%2F%2Fwww.webofscience.com%2Fwos%2Fwoscc%2Ffull-record%2FWOS:000831177200001","View Full Record in Web of Science") -> View Full Record in Web of Science
A55: J | B55: Wei, YL; Li, XF; Gu, LJ; Zheng, XM; Jiang, T; Zheng, ZJ | F55: Wei, Yanlin; Li, Xiaofeng; Gu, Lingjia; Zheng, Xingming; Jiang, Tao; Zheng, Zhaojun | I55: A Fine-Resolution Snow Depth Retrieval Algorithm From Enhanced-Resolution Passive Microwave Brightness Temperature Using Machine Learning in Northeast China | J55: IEEE GEOSCIENCE AND REMOTE SENSING LETTERS | V55: As one of the major components in the hydrological system, seasonal snow cover in Northeast China has drawn much attention recently. Because of the coarse spatial resolution of the passive microwave (PMW), heterogeneity of snowpack, and forest cover, it is difficult for existing snow products to achieve high precision snow parameters [e.g., snow depth (SD) or snow water equivalent (SWE)] assessment and hydrological research in fine scale. In this study, a novel SD retrieval algorithm that considered both the spatiotemporal dynamic of snow characteristics and forest attenuation was developed by combining the Calibrated Enhanced-Resolution Brightness Temperature (TB) data and other auxiliary information and produced a fine resolution (i.e., 6.25 km x 6.25 km) and high accuracy SD data in Northeast China. Instead of complex physical models, the machine learning was used to untangle the nonlinear complex relationship between SD and the enhanced-resolution TB, forest fraction (FF), and snow characteristics. The verification results at ground weather stations showed that the retrieved SD by the proposed algorithm had high consistency with the observed SD, its RMSE, bias, and correlation coefficient (R) of 632 cm, -0.23 cm, and 0.63, respectively. Compared with the existing SD products (WESTDC and AMSR2), the developed model greatly improved both spatial resolution and retrieval accuracy. In general, the fine-resolution SD inversion model achieved satisfactory accuracy and stability, and it will be used to generate a long-term SD dataset service for climate change and hydrological research in the future. | AA55: li, xiaofeng/GXF-9442-2022 | AB55: Wei, Yanlin/0000-0001-5755-7107; ZHENG, Zhaojun/0000-0002-7331-1905; Gu, Lingjia/0000-0002-4909-2263 | AO55: 1545-598X | AP55: 1558-0571 | AU55: 2022 | AV55: 19 | BD55: 2001305 | BE55: 10.1109/LGRS.2022.3196135 | BF55: =HYPERLINK("http://dx.doi.org/10.1109/LGRS.2022.3196135","http://dx.doi.org/10.1109/LGRS.2022.3196135") -> http://dx.doi.org/10.1109/LGRS.2022.3196135 | BS55: WOS:000842059000007 | BT55: =HYPERLINK("https%3A%2F%2Fwww.webofscience.com%2Fwos%2Fwoscc%2Ffull-record%2FWOS:000842059000007","View Full Record in Web of Science") -> View Full Record in Web of Science
A56: J | B56: Xiong, C; Yang, JR; Pan, JM; Lei, YH; Shi, JC | F56: Xiong, Chuan; Yang, Jingran; Pan, Jinmei; Lei, Yonghui; Shi, Jiancheng | I56: Mountain Snow Depth Retrieval From Optical and Passive Microwave Remote Sensing Using Machine Learning | J56: IEEE GEOSCIENCE AND REMOTE SENSING LETTERS | V56: Snow depth (SD) or snow water equivalent in mountainous regions is crucial for hydrology, water resources management, meteorological, and climate research. Remote sensing can be used for SD monitoring on a regional scale or global scale. However, the spaceborne remote sensing of SD in the mountain is challenging because of the sensor sensitivity and spatial resolution problems. Recently, the time series Sentinel-1 is used for SD retrieval in mountains, which shows encouraging accuracy. In this study, an algorithm to estimate the SD in mountainous regions using optical and passive microwave remote sensing observations is proposed, which can be applied in periods before and after the launch of Sentinel-1. The optical and passive microwave remote sensing observations and the Sentinel-1 derived SD in 2016-2021 are used to train the SD retrieval algorithm using the Extreme gradient boosting (XGBoost) machine learning algorithm. Validations are performed using the cross-validation method and independent in situ SD data. The cross-validation shows a correlation coefficient of 0.81 and a mean absolute error (MAE) of 0.17 m. The correlation coefficient and MAE of predicted SD and in situ SD in 2002-2016 are 0.61 and 0.33 m, respectively, which shows significantly higher accuracy compared with AMSR-E/AMSR2 SD products. The site dependence of the machine learning method is also discussed. The machine learning-based SD retrieval presented in this study can be applied to mountains globally in the optical and passive microwave remote sensing era. | AA56: Shi, Jiancheng/HIU-0908-2022 | AB56: 熊, 川/0000-0001-9164-4810; 施, 建成/0000-0002-6163-2912 | AO56: 1545-598X | AP56: 1558-0571 | AU56: 2022 | AV56: 19 | BD56: 2001705 | BE56: 10.1109/LGRS.2022.3226204 | BF56: =HYPERLINK("http://dx.doi.org/10.1109/LGRS.2022.3226204","http://dx.doi.org/10.1109/LGRS.2022.3226204") -> http://dx.doi.org/10.1109/LGRS.2022.3226204 | BS56: WOS:000902088700006 | BT56: =HYPERLINK("https%3A%2F%2Fwww.webofscience.com%2Fwos%2Fwoscc%2Ffull-record%2FWOS:000902088700006","View Full Record in Web of Science") -> View Full Record in Web of Science
A57: C | B57: Yu, GG; Gu, LJ; Ren, RZ; Jiang, MD | D57: Butler, JJ; Xiong, X; Gu, X | F57: Yu, Guangan; Gu, Lingjia; Ren, Ruizhi; Jiang, Mingda | I57: Snow depth mapping in agricultural areas of Northeast China based on deep learning and multi-temporal Sentinel-1 data | J57: EARTH OBSERVING SYSTEMS XXVII | K57: Proceedings of SPIE | O57: Conference on Earth Observing Systems XXVII | P57: AUG 23-25, 2022 | Q57: San Diego, CA | R57: SPIE | V57: Snow is an essential element in surface climate studies. Snow measurement using remote sensing data gradually has become mainstream with the continuous development of remote sensing technology. Synthetic aperture radar (SAR) has the capability of all-day, all-weather ground observation, and combines high spatial resolution, interferometry, and polarization imaging. C-band SAR images are more sensitive to snow characteristics and are an effective data source for obtaining the spatial distribution of snow in areas with complex terrain. In recent years, the methods of using machine learning and deep learning to invert snow parameters such as snow depth and snow water equivalent have been widely used. In this paper, the study area is the farmland area of Northeast China. The relationship between snow depth and snow parameters is analyzed by a deep learning algorithm and machine learning algorithm using multi-temporal Sentinel-1 C-band SAR data, measured snow depth data, and so on. The inversion model based on the type of farmland subsurface is established to invert the snow depth in the farmland area of northeast China and output the map. The aim is to generate surface-based snow depth inversion results with less error and higher accuracy. The average MAE of the model is 2.06cm, RMSE is 2.96 cm, R-2 is 0.72, the maximum absolute error is 10.206 cm, and the minimum absolute error is 0.045cm for the farmland mixed group feature screening dataset. | AO57: 0277-786X | AP57: 1996-756X | AQ57: 978-1-5106-5449-5; 978-1-5106-5448-8 | AU57: 2022 | AV57: 12232 | BD57: 122321I | BE57: 10.1117/12.2631482 | BF57: =HYPERLINK("http://dx.doi.org/10.1117/12.2631482","http://dx.doi.org/10.1117/12.2631482") -> http://dx.doi.org/10.1117/12.2631482 | BS57: WOS:000882951300043 | BT57: =HYPERLINK("https%3A%2F%2Fwww.webofscience.com%2Fwos%2Fwoscc%2Ffull-record%2FWOS:000882951300043","View Full Record in Web of Science") -> View Full Record in Web of Science
A58: J | B58: Zhu, XX; Gu, LJ; Li, XF; Jiang, T | F58: Zhu, Xiaoxin; Gu, Lingjia; Li, Xiaofeng; Jiang, Tao | I58: Snow Depth Estimation Based on Parameter Combinations Selection and Machine Learning Algorithm Using C-Band SAR Data in Northeast China | J58: IEEE GEOSCIENCE AND REMOTE SENSING LETTERS | V58: Radar images with high spatial resolution are not affected by illumination or meteorological conditions, which effectively compensate for the shortcomings of optical images and passive microwave images. Thus, active microwave remote sensing technology has advantages in snow depth (SD) research. Machine learning algorithms (MLAs), which do not need to consider complex physical models, have increasingly been applied to SD research. Considering the snow conditions of different underlying surfaces, it is very important to select the appropriate parameter combinations (PC) reflecting the SD information for MLAs. In this study, C-band SAR data with 20 m spatial resolution, ground-based SD observation data from meteorological stations, and field measurement data in Northeast China were used to construct and validate the SD estimation method. Two parameter selection methods including the correlation coefficient method and the machine learning (ML) fusion method were proposed to discuss the influence of different PC on SD estimation. Then, XGBoost, random forest (RF), linear support vector regression (LSVR), and kernel support vector regression (KSVR) were applied to estimate SD based on the selected PC, and evaluate the accuracies of SD estimation using different MLAs. The results demonstrated that the PC selected using the correlation coefficient method and XGBoost algorithm could achieve the best SD results in the study area. Combining RPC-C with XGBoost algorithm, in cropland areas, the average values of mean absolute error (MAE) and root mean squared error (RMSE) were 1.75 and 2.58 cm, respectively. Combining RPC-F with XGBoost algorithm, in forest areas, the average values of MAE and RMSE were 3.12 and 5.07 cm, respectively. The research of this letter can select the optimal PC for MLAs and effectively improve the accuracy of SD estimation using C-band SAR data. | AA58: li, xiaofeng/GXF-9442-2022 | AB58: Gu, Lingjia/0000-0002-4909-2263; Zhu, Xiaoxin/0000-0003-1697-9340 | AO58: 1545-598X | AP58: 1558-0571 | AU58: 2022 | AV58: 19 | BD58: 4502405 | BE58: 10.1109/LGRS.2021.3129998 | BF58: =HYPERLINK("http://dx.doi.org/10.1109/LGRS.2021.3129998","http://dx.doi.org/10.1109/LGRS.2021.3129998") -> http://dx.doi.org/10.1109/LGRS.2021.3129998 | BS58: WOS:000742225800068 | BT58: =HYPERLINK("https%3A%2F%2Fwww.webofscience.com%2Fwos%2Fwoscc%2Ffull-record%2FWOS:000742225800068","View Full Record in Web of Science") -> View Full Record in Web of Science
A59: J | B59: Yang, JW; Jiang, LM; Lemmetyinen, J; Pan, JM; Luojus, K; Takala, M | F59: Yang, J. W.; Jiang, L. M.; Lemmetyinen, J.; Pan, J. M.; Luojus, K.; Takala, M. | I59: Improving snow depth estimation by coupling HUT-optimized effective snow grain size parameters with the random forest approach | J59: REMOTE SENSING OF ENVIRONMENT | V59: Snow cover is highly critical for global water and energy cycles because of its wide areal extent, high reflectivity and good thermal insulation. Knowledge of snow conditions, e.g., snow water equivalent (SWE) and snow depth, is significant to hydrologic and climatologic processes. Spaceborne passive microwave (PMW) data, namely, brightness temperature (TB), have been in use for snow depth and SWE retrieval at the global scale since 1978. However, the sensitivity of TB to these parameters is complex due to snow metamorphism (e.g., snow grain size, GS), which limits the feasibility of many existing algorithms characterizing snow. This study presents a new methodology to retrieve snow depth over China by coupling a microwave snow emission model with a random forest (RF) machine learning (ML) technique. An effective GS value (effGS), a prior snowpack descriptor, was optimized utilizing the Helsinki University of Technology (HUT) model by minimizing the difference between AMSR2 observations (18.7 and 36.5 GHz) and HUT simulations. Five elaborately selected independent variables, including vertical polarized TB differences (TBD) between 18.7 and 36.5 GHz (TBD18.7V&36.5V), 10.65 and 36.5 GHz (TBD10.65V&36.5V), longitude, elevation and effGS, together with the target variable, snow depth, were applied to train the RF model, and then the 10-fold cross-validation (10-CV) approach was employed for performance validation using station data during the period from 2012 to 2018. The results indicated that (1) inclusion of effGS in RF greatly enhanced the overall performance in snow depth estimation; (2) the trained RF model performed better on a temporal scale than on a spatial scale, with unRMSEs of 1.81 cm and 3.17 cm, respectively; (3) specifically, the fitted RF algorithm partially addressed the overestimation in shallow (<= 20 cm) snowpacks and underestimation in deep (> 20 cm) snow conditions when compared with the established RF algorithm based solely on predictor variables but without effGS. To evaluate the predictive power of the RF algorithm trained with samples in 2017 and 2018, spatially independent station measurements during the period from 2012 to 2016 and field survey data collected from January 2018 to March 2019 were used for validation. Additionally, the RF estimates were compared with two widely used satellite products (AMSR2 and GlobSnow-2). The validation results showed that RF estimates were closer to the in situ data than the other two satellite products. This study demonstrated the potential utility of combining the snow emission model with an ML approach to improve snow depth estimation. | AA59: Luojus, Kari/AAO-7912-2020; Jiang, Lingmei/L-6099-2016; Lemmetyinen, Juha/B-3739-2016 | AB59: Luojus, Kari/0000-0002-4066-6005; Jiang, Lingmei/0000-0002-9847-9034; | AO59: 0034-4257 | AP59: 1879-0704 | AT59: OCT | AU59: 2021 | AV59: 264 | BD59: 112630 | BE59: 10.1016/j.rse.2021.112630 | BF59: =HYPERLINK("http://dx.doi.org/10.1016/j.rse.2021.112630","http://dx.doi.org/10.1016/j.rse.2021.112630") -> http://dx.doi.org/10.1016/j.rse.2021.112630 | BH59: AUG 2021 | BS59: WOS:000688490900003 | BT59: =HYPERLINK("https%3A%2F%2Fwww.webofscience.com%2Fwos%2Fwoscc%2Ffull-record%2FWOS:000688490900003","View Full Record in Web of Science") -> View Full Record in Web of Science
A60: J | B60: Zhang, J; Pohjola, VA; Pettersson, R; Norell, B; Marchand, WD; Clemenzi, I; Gustafsson, D | F60: Zhang, Jie; Pohjola, Veijo A.; Pettersson, Rickard; Norell, Bjorn; Marchand, Wolf-Dietrich; Clemenzi, Ilaria; Gustafsson, David | I60: Improving the snowpack monitoring in the mountainous areas of Sweden from space: a machine learning approach | J60: ENVIRONMENTAL RESEARCH LETTERS | V60: Under a warming climate, an improved understanding of the water stored in snowpacks is becoming increasingly important for hydropower planning, flood risk assessment and water resource management. Due to inaccessibility and a lack of ground measurement networks, accurate quantification of snow water storage in mountainous terrains still remains a major challenge. Remote sensing can provide dynamic observations with extensive spatial coverage, and has proved a useful means to characterize snow water equivalent (SWE) at a large scale. However, current SWE products show very low quality in the mountainous areas due to very coarse spatial resolution, complex terrain, large spatial heterogeneity and deep snow. With more high-quality satellite data becoming available from the development of satellite sensors and platforms, it provides more opportunities for better estimation of snow conditions. Meanwhile, machine learning provides an important technique for handling the big data offered from remote sensing. Using the overuman Catchment in Northern Sweden as a case study, this paper explores the potentials of machine learning for improving the estimation of mountain snow water storage using satellite observations, topographic factors, land cover information and ground SWE measurements from the spatially distributed snow survey. The results show that significantly improved SWE estimation close to the peak of snow accumulation can be achieved in the catchment using the random forest regression. This study demonstrates the potentials of machine learning for better understanding the snow water storage in mountainous areas. | AA60: ; Gustafsson, David/G-6729-2012 | AB60: Clemenzi, Ilaria/0000-0001-7140-6647; Gustafsson, David/0000-0002-2754-7415 | AO60: 1748-9326 | AT60: AUG | AU60: 2021 | AV60: 16 | AW60: 8 | BD60: 84007 | BE60: 10.1088/1748-9326/abfe8d | BF60: =HYPERLINK("http://dx.doi.org/10.1088/1748-9326/abfe8d","http://dx.doi.org/10.1088/1748-9326/abfe8d") -> http://dx.doi.org/10.1088/1748-9326/abfe8d | BS60: WOS:000678345800001 | BT60: =HYPERLINK("https%3A%2F%2Fwww.webofscience.com%2Fwos%2Fwoscc%2Ffull-record%2FWOS:000678345800001","View Full Record in Web of Science") -> View Full Record in Web of Science
A61: J | B61: Cannistra, AF; Shean, DE; Cristea, NC | F61: Cannistra, Anthony F.; Shean, David E.; Cristea, Nicoleta C. | I61: High-resolution CubeSat imagery and machine learning for detailed snow-covered area | J61: REMOTE SENSING OF ENVIRONMENT | V61: Snow cover affects a diverse array of physical, ecological, and societal systems. As such, the development of optical remote sensing techniques to measure snow-covered area (SCA) has enabled progress in a wide variety of research domains. However, in many cases, the spatial and temporal resolutions of currently available remotely sensed SCA products are insufficient to capture SCA evolution at spatial and temporal resolutions relevant to the study of fine-scale spatially heterogeneous phenomena. We developed a convolutional neural network-based method to identify snow covered area using the similar to 3 m, 4-band PlanetScope optical satellite image dataset with similar to daily, near-global coverage. By comparing our model performance to snow extent derived from high-resolution airborne lidar differential depth measurements and satellite platforms in two North American sites (Sierra Nevada, CA, USA and Rocky Mountains, CO, USA), we show that these emerging image archives have great potential to accurately observe snow-covered area at high spatial and temporal resolutions despite limited radiometric bandwidth and band placement. We achieve average snow classification F-Scores of 0.73 in our training basin and 0.67 in a climatically-distinct out-of-sample basin, suggesting opportunities for model transferability. We also evaluate the performance of these data in forested regions, suggesting avenues for further research. The unparalleled spatial and temporal coverage of CubeSat imagery offers an excellent opportunity for satellite remote sensing of snow, with real implications for ecological and water resource applications. | AA61: ; Cannistra, Anthony/MCY-6687-2025; Cristea, Nicoleta/P-6245-2019 | AB61: Shean, David/0000-0003-3840-3860; Cannistra, Anthony/0000-0002-9852-6291; | AO61: 0034-4257 | AP61: 1879-0704 | AT61: JUN 1 | AU61: 2021 | AV61: 258 | BD61: 112399 | BE61: 10.1016/j.rse.2021.112399 | BF61: =HYPERLINK("http://dx.doi.org/10.1016/j.rse.2021.112399","http://dx.doi.org/10.1016/j.rse.2021.112399") -> http://dx.doi.org/10.1016/j.rse.2021.112399 | BH61: MAR 2021 | BS61: WOS:000637767400001 | BT61: =HYPERLINK("https%3A%2F%2Fwww.webofscience.com%2Fwos%2Fwoscc%2Ffull-record%2FWOS:000637767400001","View Full Record in Web of Science") -> View Full Record in Web of Science
A62: J | B62: Kuter, S | F62: Kuter, Semih | I62: Completing the machine learning saga in fractional snow cover estimation from MODIS Terra reflectance data: Random forests versus support vector regression | J62: REMOTE SENSING OF ENVIRONMENT | V62: This study; i) investigates the suitability of two frequently employed machine learning algorithms in remote sensing, namely, random forests (RFs) and support vector regression (SVR) for fractional snow cover (FSC) estimation from MODIS Terra data, and ii) compares them with the previously proposed artificial neural networks (ANNs) and multivariate adaptive regression splines (MARS) methods over an heterogeneous and complex alpine terrain. The dataset comprises 20 Landsat 8 - MODIS image pairs that belong to European Alps acquired from Apr 2013 to Dec 2016. The fifteen image pairs are used to generate the training dataset necessary to build the models, whereas the remaining five are employed as a separate test dataset. The reference FSC maps are derived from the binary classified Landsat 8 snow/no snow maps at 30 m resolution. In order to assess the effect of sampling type and sample size, nine different training datasets are generated. The RF and SVR models are trained accordingly by using various settings of model tuning parameters. During the training of the models, MODIS top-of-atmosphere reflectance values of bands 1-7, NDSI, NDVI and land cover class are input as independent variables (i.e., predictors) to estimate the dependent variable (i.e., response), i.e., FSC value. The resolution of the generated FSC maps is 500 m. The results indicate that the ANN, MARS, RF and SVR models exhibit high consistency with reference FSC values as indicated by low RMSE (similar to 0.14) and high R (similar to 0.93) values. In order to analyze the effect of using three auxiliary variables, i.e., NDSI, NDVI and land cover class, to the predictive ability of the models; ANN, MARS, RF and SVR models are also trained without these predictor variables, i.e., by only using MODIS bands 1-7. The models trained without three auxiliary variables slightly differ from the ones trained with the full set of predictors by only resulting in a mean decrease in R <0.012 and a mean increase in RMSE <0.009, showing that they perform well in solving the complex functional dependencies by only using MODIS reflectance data. In terms of computational efficiencies of the proposed algorithms measured by the CPU times spent during model training, MARS and RF algorithms outperform ANN and SVR methods. | AA62: Kuter, Semih/AAF-3298-2021 | AB62: Kuter, Semih/0000-0002-4760-3816 | AO62: 0034-4257 | AP62: 1879-0704 | AT62: MAR 15 | AU62: 2021 | AV62: 255 | BD62: 112294 | BE62: 10.1016/j.rse.2021.112294 | BF62: =HYPERLINK("http://dx.doi.org/10.1016/j.rse.2021.112294","http://dx.doi.org/10.1016/j.rse.2021.112294") -> http://dx.doi.org/10.1016/j.rse.2021.112294 | BH62: JAN 2021 | BS62: WOS:000619233500003 | BT62: =HYPERLINK("https%3A%2F%2Fwww.webofscience.com%2Fwos%2Fwoscc%2Ffull-record%2FWOS:000619233500003","View Full Record in Web of Science") -> View Full Record in Web of Science
A63: C | B63: Qiao, DJ; Li, Z; Zhang, P; Zhou, JM; Liang, S | E63: IEEE | F63: Qiao, Dejing; Li, Zhen; Zhang, Ping; Zhou, Jianmin; Liang, Shuang | I63: PREDICTION OF SNOW DEPTH BASED ON MULTI-SOURCE DATA AND MACHINE LEARNING ALGORITHMS | J63: 2021 IEEE INTERNATIONAL GEOSCIENCE AND REMOTE SENSING SYMPOSIUM IGARSS | K63: IEEE International Symposium on Geoscience and Remote Sensing IGARSS | O63: IEEE International Geoscience and Remote Sensing Symposium (IGARSS) | P63: JUL 12-16, 2021 | Q63: ELECTR NETWORK | R63: Inst Elect & Elect Engineers,Inst Elect & Elect Engineers Geoscience & Remote Sensing Soc | V63: As an important element of the earth's surface, snow cover plays an important role in the global terrestrial ecosystem, climate change, water cycle and energy cycle. Snow depth (SD) provides information on the spatial distribution of snow cover and material energy information. It is also used to study the climatic effects of snow cover, water balance in the basin, snowmelt runoff simulation, and monitoring and evaluation of snow disasters. Snow depth data has become an indispensable basic supporting data in multi-disciplinary research. However, the current snow depth data is relatively poor in completeness and consistency and cannot meet the needs of related scientific research and industry applications, which will bring great confusion to users. This study attempts to use machine learning methods to effectively integrate snow depth data products from multiple sources to obtain a snow depth data set with high consistency in China. This paper chooses the passive microwave remote sensing data (WESTDC), ground-based data (Canadian Meteorological Centre, CMC) and Land surface models (Global Land Data Assimilation System, GLDAS; the NASA Modern-Era Retrospective Analysis for Research and Applications MERRA2; the European Centre for Medium-Range Weather Forecasts Interim Reanalysis, ERA-Interim) as the main SD data source of random forest model, and considering the influencing factors (e.g., land cover, snow class, forest cover fraction, surface roughness). The results show that the random forest fusion model method can effectively gather the advantages of each data source, improve the accuracy of snow depth estimation, and reduce the inconsistency between snow depth data from multiple sources. The correlation coefficient between the fused snow depth dataset and the observed snow depth can reach 0.87, and the root mean square error is 5.1 cm. Therefore, the multi-source snow depth fusion using random forest model can improve the accuracy of snow depth estimation. | AO63: 2153-6996 | AQ63: 978-1-6654-0369-6 | AU63: 2021 | BB63: 5578 | BC63: 5581 | BE63: 10.1109/IGARSS47720.2021.9554675 | BF63: =HYPERLINK("http://dx.doi.org/10.1109/IGARSS47720.2021.9554675","http://dx.doi.org/10.1109/IGARSS47720.2021.9554675") -> http://dx.doi.org/10.1109/IGARSS47720.2021.9554675 | BS63: WOS:001250139805188 | BT63: =HYPERLINK("https%3A%2F%2Fwww.webofscience.com%2Fwos%2Fwoscc%2Ffull-record%2FWOS:001250139805188","View Full Record in Web of Science") -> View Full Record in Web of Science
A64: C | B64: Santi, E; Paloscia, S; Pettinato, S; Notarnicola, C; Cuozzo, G; De Gregorio, L; Cigna, F; Tapete, D | E64: IEEE | F64: Santi, E.; Paloscia, S.; Pettinato, S.; Notarnicola, C.; Cuozzo, G.; De Gregorio, L.; Cigna, F.; Tapete, D. | I64: SNOW WATER EQUIVALENT RETRIEVAL FROM COSMO-SKYMED OBSERVATIONS THROUGH MACHINE LEARNING ALGORITHMS AND MODEL SIMULATIONS | J64: 2021 IEEE INTERNATIONAL GEOSCIENCE AND REMOTE SENSING SYMPOSIUM IGARSS | K64: IEEE International Symposium on Geoscience and Remote Sensing IGARSS | O64: IEEE International Geoscience and Remote Sensing Symposium (IGARSS) | P64: JUL 12-16, 2021 | Q64: ELECTR NETWORK | R64: Inst Elect & Elect Engineers,Inst Elect & Elect Engineers Geoscience & Remote Sensing Soc | V64: The monitoring of snow conditions in Alpine areas to support water management and avalanche warning applications would require the estimate of snow parameters, such as the snow water equivalent (SWE). In this research, COSMO-SkyMed (CSK) X-band SAR data were exploited to estimate the SWE. In-situ snow measurements (depth, density, snow grain radius, temperature) collected in South Tyrol (Italy), were used to simulate the X-band backscatter with the Dense Medium Radiative Transfer (DMRT) electromagnetic model. Two SWE retrieval algorithms based on machine learning approach were implemented. The algorithms are based on Artificial Neural Networks (ANN) and Support Vector Regression (SVR) and have been trained with both experimental data and DMRT model simulations. These algorithms were applied to a selection of CSK StripMap HIMAGE HH-polarized scenes collected over the test area. The obtained results are promising and they confirm the potential of SAR data at X-band to retrieve snow parameters, although the algorithm validation should be improved in the future, with more consistent measurement dataset. | AB64: Cuozzo, Giovanni/0000-0001-9120-7426; santi, emanuele/0000-0003-1882-6321; Notarnicola, Claudia/0000-0003-1968-0125 | AO64: 2153-6996 | AQ64: 978-1-6654-0369-6 | AU64: 2021 | BB64: 5473 | BC64: 5476 | BE64: 10.1109/IGARSS47720.2021.9553985 | BF64: =HYPERLINK("http://dx.doi.org/10.1109/IGARSS47720.2021.9553985","http://dx.doi.org/10.1109/IGARSS47720.2021.9553985") -> http://dx.doi.org/10.1109/IGARSS47720.2021.9553985 | BS64: WOS:001250139805162 | BT64: =HYPERLINK("https%3A%2F%2Fwww.webofscience.com%2Fwos%2Fwoscc%2Ffull-record%2FWOS:001250139805162","View Full Record in Web of Science") -> View Full Record in Web of Science
A65: J | B65: Zaerpour, A; Adib, A; Motamedi, A | F65: Zaerpour, Arash; Adib, Arash; Motamedi, Ali | I65: Snow depth retrieval from passive microwave imagery using different artificial neural networks | J65: ARABIAN JOURNAL OF GEOSCIENCES | V65: The high degree of nonlinearity in the analysis of hydrologic systems demonstrates that artificial neural networks are suitable methods for this purpose. Artificial neural networks and passive microwave imagery have been combined for monitoring snow parameters, particularly in arid and semi-arid areas where the hydrologic process of the water basin is very dependent on the snow conditions (snow depth, snow water equivalent, snow density, snow cover area, snow stratigraphy, the shape of the crystals of snow). The multilayer perceptron is learned by different methods (Levenberg-Marquardt, scaled conjugate gradient, gradient descent with momentum and adaptive learning rate). These multilayer perceptrons are compared with radial basis function and multilayer perceptron-genetic algorithm for evaluating snow depth. Snow depth is estimated using passive microwave brightness temperature of a special sensor microwave/imager sensor. The results indicate that multilayer perceptron-genetic algorithm outperformed other artificial neural networks (multilayer perceptron-Levenberg-Marquardt, multilayer perceptron-scaled conjugate gradient, multilayer perceptron-gradient descent with momentum and adaptive learning rate, multilayer perceptron-genetic algorithm and radial basis function) with r = 0.97, RMSE = 0.18, and NSE = 0.83 for training and r = 0.90, RMSE = 0.19, and NSE = 0.39 for testing. | AA65: Adib, Arash/AAF-5415-2021 | AB65: Adib, Arash/0000-0002-1575-0387 | AO65: 1866-7511 | AP65: 1866-7538 | AT65: JUL 18 | AU65: 2020 | AV65: 13 | AW65: 15 | BD65: 696 | BE65: 10.1007/s12517-020-05642-x | BF65: =HYPERLINK("http://dx.doi.org/10.1007/s12517-020-05642-x","http://dx.doi.org/10.1007/s12517-020-05642-x") -> http://dx.doi.org/10.1007/s12517-020-05642-x | BS65: WOS:000552403600005 | BT65: =HYPERLINK("https%3A%2F%2Fwww.webofscience.com%2Fwos%2Fwoscc%2Ffull-record%2FWOS:000552403600005","View Full Record in Web of Science") -> View Full Record in Web of Science
A66: J | B66: Bloshchinskiy, VD; Kuchma, MO; Andreev, A; Sorokin, AA | F66: Bloshchinskiy, Vladislav D.; Kuchma, Mikhail O.; Andreev, Alexander, I; Sorokin, Aleksei A. | I66: Snow and cloud detection using a convolutional neural network and low-resolution data from the Electro-L No. 2 Satellite | J66: JOURNAL OF APPLIED REMOTE SENSING | V66: We describe an algorithm based on a convolutional neural network that detects cloud formations and snow cover in satellite images using textures. Herein, multispectral satellite images, received from a multizone scanning instrument used for hydrometeorological support and installed on the Russian satellite Electro-L No. 2, are used as input data. The problem of snow and cloud classification in the absence of a spectral channel in the range of 1.4 to 1.8 mu m, which is necessary for their accurate separation, is considered. The developed algorithm can produce cloud and snow cover masks for an area limited by the values of the solar zenith angle in the range of 0 deg to 80 deg for daytime. Algorithm accuracy was evaluated using machine learning metrics and comparing its results with ground truth masks segmented manually by an experienced interpreter. In addition, we compared the resulting masks with a similar cloud mask product from the European Organisation for the Exploitation of Meteorological Satellites based on the data of the Spinning Enhanced Visible and Infrared Imager (SEVIRI) instrument installed on the Meteosat-8 satellite. According to the results of this comparison, we conclude that the cloud masks produced by the proposed convolutional neural network-based algorithm have a lower probability of false detection than products based on the SEVIRI data. The proposed algorithm is fully automatic, and it works in any season of the year during the daytime. (C) 2020 Society of Photo-Optical Instrumentation Engineers (SPIE) | AA66: Bloshchinskiy, Vladislav/AAQ-5068-2020; Kuchma, Mikhail/ADP-6622-2022; Sorokin, Aleksei/I-5980-2014 | AB66: Bloshchinskiy, Vladislav/0000-0001-7378-6559; Kuchma, Mikhail/0000-0002-3450-7323; Sorokin, Aleksei/0000-0003-3334-3440 | AP66: 1931-3195 | AT66: JUL 15 | AU66: 2020 | AV66: 14 | AW66: 3 | BD66: 34506 | BE66: 10.1117/1.JRS.14.034506 | BF66: =HYPERLINK("http://dx.doi.org/10.1117/1.JRS.14.034506","http://dx.doi.org/10.1117/1.JRS.14.034506") -> http://dx.doi.org/10.1117/1.JRS.14.034506 | BS66: WOS:000551468300001 | BT66: =HYPERLINK("https%3A%2F%2Fwww.webofscience.com%2Fwos%2Fwoscc%2Ffull-record%2FWOS:000551468300001","View Full Record in Web of Science") -> View Full Record in Web of Science
A67: J | B67: Yang, JW; Jiang, LM; Luojus, K; Pan, JM; Lemmetyinen, J; Takala, M; Wu, SL | F67: Yang, Jianwei; Jiang, Lingmei; Luojus, Kari; Pan, Jinmei; Lemmetyinen, Juha; Takala, Matias; Wu, Shengli | I67: Snow depth estimation and historical data reconstruction over China based on a random forest machine learning approach | J67: CRYOSPHERE | V67: We investigated the potential capability of the random forest (RF) machine learning (ML) model to estimate snow depth in this work. Four combinations composed of critical predictor variables were used to train the RF model. Then, we utilized three validation datasets from out-of-bag (OOB) samples, a temporal subset, and a spatiotemporal subset to verify the fitted RF algorithms. The results indicated the following: (1) the accuracy of the RF model is greatly influenced by geographic location, elevation, and land cover fractions; (2) however, the redundant predictor variables (if highly correlated) slightly affect the RF model; and (3) the fitted RF algorithms perform better on temporal than spatial scales, with unbiased root-mean-square errors (RMSEs) of similar to 4.4 and similar to 7.3 cm, respectively. Finally, we used the fitted RF2 algorithm to retrieve a consistent 32-year daily snow depth dataset from 1987 to 2018. This product was evaluated against the independent station observations during the period 1987-2018. The mean unbiased RMSE and bias were 7.1 and -0.05 cm, respectively, indicating better performance than that of the former snow depth dataset (8.4 and -1.20 cm) from the Environmental and Ecological Science Data Center for West China (WESTDC). Although the RF product was superior to the WESTDC dataset, it still underestimated deep snow cover (> 20 cm), with biases of -10.4, -8.9, and -34.1 cm for northeast China (NEC), northern Xinjiang (XJ), and the Qinghai-Tibetan Plateau (QTP), respectively. Additionally, the long-term snow depth datasets (station observations, RF estimates, and WESTDC product) were analyzed in terms of temporal and spatial variations over China. On a temporal scale, the ground truth snow depth presented a significant increasing trend from 1987 to 2018, especially in NEC. However, the RF and WESTDC products displayed no significant changing trends except on the QTP. The WESTDC product presented a significant decreasing trend on the QTP, with a correlation coefficient of -0.55, whereas there were no significant trends for ground truth observations and the RF product. For the spatial characteristics, similar trend patterns were observed for RF and WESTDC products over China. These characteristics presented significant decreasing trends in most areas and a significant increasing trend in central NEC. | AA67: Jiang, Lingmei/L-6099-2016; Luojus, Kari/AAO-7912-2020; Wu, Shengli/Y-9381-2019; Lemmetyinen, Juha/B-3739-2016 | AB67: Jiang, Lingmei/0000-0002-9847-9034; Luojus, Kari/0000-0002-4066-6005; Wu, Shengli/0000-0002-5930-3183; Lemmetyinen, Juha/0000-0003-4434-9696 | AO67: 1994-0416 | AP67: 1994-0424 | AT67: JUN 3 | AU67: 2020 | AV67: 14 | AW67: 6 | BB67: 1763 | BC67: 1778 | BE67: 10.5194/tc-14-1763-2020 | BF67: =HYPERLINK("http://dx.doi.org/10.5194/tc-14-1763-2020","http://dx.doi.org/10.5194/tc-14-1763-2020") -> http://dx.doi.org/10.5194/tc-14-1763-2020 | BS67: WOS:000538410900001 | BT67: =HYPERLINK("https%3A%2F%2Fwww.webofscience.com%2Fwos%2Fwoscc%2Ffull-record%2FWOS:000538410900001","View Full Record in Web of Science") -> View Full Record in Web of Science
A68: J | B68: Wang, JW; Yuan, QQ; Shen, HF; Liu, TT; Li, TW; Yue, LW; Shi, XG; Zhang, LP | F68: Wang, Jiwen; Yuan, Qiangqiang; Shen, Huanfeng; Liu, Tingting; Li, Tongwen; Yue, Linwei; Shi, Xiaogang; Zhang, Liangpei | I68: Estimating snow depth by combining satellite data and ground-based observations over Alaska: A deep learning approach | J68: JOURNAL OF HYDROLOGY | V68: Snow cover plays a vital role in the climate system because it is related to climate, hydrological cycle, and ecosystem. On this basis, deriving a long-term and large-scale snow depth (SD) time series and monitoring its temporal and spatial variations are crucial. Passive microwave remote sensing data in combination with in-situ SD data have long been used to retrieve SD. However, the retrieval accuracy is limited in case of sparse meteorological stations, and the high-quality applications of retrieval results are hindered in specific areas. The ground-based global navigation satellite system reflectometry (GNSS-R) method is currently a potential way to monitor SD variations with a high degree of accuracy but has a limited spatial coverage. In this study, a deep learning-based approach, which displays a stronger nonlinear expressiveness capability than conventional neural networks, was applied to estimate SD by combining satellite observations, in-situ data, and GNSS-R estimates. The model was trained and tested with data obtained in Alaska between 2008 and 2017. Results show that the proposed deep belief network model performs better than linear methods and conventional neural network models and demonstrate the effectiveness of combining GNSS-R estimation with increased cross-validation R of 0.85 and decreased RMSE of 15.40 cm. The predicted SD distribution indicates that the variations in mean SD in Alaska for March and April between 2008 and 2017 were associated with the climate anomalies and air temperature. Overall, the proposed deep learning-based method is a promising approach in the satellite-retrieved SD field. | AA68: Yue, Linwei/ABD-8243-2022; Shen, Huanfeng/HPD-8048-2023; Liu, Tingting/HCH-2239-2022; Zhang, Liangpei/ADI-7616-2022; Yuan, Qiangqiang/V-4671-2019 | AB68: Yue, Linwei/0009-0008-8794-2389; Shen, Huanfeng/0000-0002-4140-1869; Li, Tongwen/0000-0001-7197-3713; | AO68: 0022-1694 | AP68: 1879-2707 | AT68: JUN | AU68: 2020 | AV68: 585 | BD68: 124828 | BE68: 10.1016/j.jhydrol.2020.124828 | BF68: =HYPERLINK("http://dx.doi.org/10.1016/j.jhydrol.2020.124828","http://dx.doi.org/10.1016/j.jhydrol.2020.124828") -> http://dx.doi.org/10.1016/j.jhydrol.2020.124828 | BS68: WOS:000544230000079 | BT68: =HYPERLINK("https%3A%2F%2Fwww.webofscience.com%2Fwos%2Fwoscc%2Ffull-record%2FWOS:000544230000079","View Full Record in Web of Science") -> View Full Record in Web of Science
A69: J | B69: Liu, Y; Chen, X; Hao, JS; Li, LH | F69: Liu Yang; Chen Xi; Hao Jian-Sheng; Li Lan-hai | I69: Snow cover estimation from MODIS and Sentinel-1 SAR data using machine learning algorithms in the western part of the Tianshan Mountains | J69: JOURNAL OF MOUNTAIN SCIENCE | V69: Obtaining the spatial distribution of snow cover in mountainous areas using the optical image of remote sensing technology is difficult because of cloud and fog. In this study, the object-based principle component analysis-support vector machine (PCA-SVM) method is proposed for snow cover mapping through the integration of moderateresolution imaging spectroradiometer (MODIS) snow cover products and the Sentinel-1 synthetic aperture radar (SAR) scattering characteristics. First, derived from the Sentinel-1A SAR images, the feature parameters, including VV/VH backscatter, scattering entropy, and scattering alpha, were used to describe the variations of snow and non-snow covers. Second, the optimum feature combinations of snow cover were formed from the feature parameters using the principle component analysis (PCA) algorithm. Finally, using the optimum feature combinations, a snow cover map with a 20 m spatial resolution was extracted by means of an object-based SVM classifier. This method was applied in the study area of the Xinyuan County, which is located in the western part of the Tianshan Mountains in Xinjiang, China. The accuracies in this method were analyzed according to the data observed at different experimental sites. Results showed that the snow cover pixels of the extraction were less than those in the actual situation (FB1=93.86, FB2=59.78). The evaluation of the threat score (TS), probability of detection (POD), and false alarm ratio (FAR) for the snow-covered pixels obtained from the two-stage SAR images were different (TS1=86.84, POD1=90.10, FAR(1)=4.01; TS2=56.40, POD2=57.62, FAR(2)=3.62). False and misclassifications of the snow cover and non-snow cover pixels were found. Although the classifications were not highly accurate, the approach showed potential for integrating different sources to retrieve the spatial distribution of snow covers during a stable period. | AA69: Li, Lanhai/AAE-9967-2020 | AO69: 1672-6316 | AP69: 1993-0321 | AT69: APR | AU69: 2020 | AV69: 17 | AW69: 4 | BB69: 884 | BC69: 897 | BE69: 10.1007/s11629-019-5723-1 | BF69: =HYPERLINK("http://dx.doi.org/10.1007/s11629-019-5723-1","http://dx.doi.org/10.1007/s11629-019-5723-1") -> http://dx.doi.org/10.1007/s11629-019-5723-1 | BS69: WOS:000525174500009 | BT69: =HYPERLINK("https%3A%2F%2Fwww.webofscience.com%2Fwos%2Fwoscc%2Ffull-record%2FWOS:000525174500009","View Full Record in Web of Science") -> View Full Record in Web of Science
A70: J | B70: Guo, XJ; Chen, Y; Liu, XF; Zhao, Y | F70: Guo, Xuejun; Chen, Yin; Liu, Xiaofeng; Zhao, Yue | I70: Extraction of snow cover from high-resolution remote sensing imagery using deep learning on a small dataset | J70: REMOTE SENSING LETTERS | V70: Snow cover is of great significance for many applications. However, automatic extraction of snow cover from high spatial resolution remote sensing (HSRRS) imagery remains challenging, owing to its multiscale characteristics, similarities to clouds, and occlusion by the shadows of mountains and clouds. Deep convolutional neural networks for semantic segmentation are the most popular approach to automatic map generation, but they require huge computing time and resources, as well as a large dataset of pixel-wise annotated HSRRS images, which precludes the application of many superior models. In this study, these limitations are overcome by using a sequence of transfer learning steps. The method starts with a modified aligned ?Xception? model pre-trained for object classification on ImageNet. Subsequently, a ?DeepLab version three plus? (DeepLabv3+) model is trained using a large dataset of Landsat images and corresponding snow cover products. Finally, a second transfer learning step is employed to fine-tune the model on the small dataset of GaoFen-2, the highest resolution HSRRS satellite in China. Experiments demonstrate the feasibility and effectiveness of this framework for automatic snow cover extraction. | AA70: liu, xiaofeng/GQG-9287-2022; Zhao, Yue/LUY-9370-2024 | AO70: 2150-704X | AP70: 2150-7058 | AT70: JAN 2 | AU70: 2020 | AV70: 11 | AW70: 1 | BB70: 66 | BC70: 75 | BE70: 10.1080/2150704X.2019.1686548 | BF70: =HYPERLINK("http://dx.doi.org/10.1080/2150704X.2019.1686548","http://dx.doi.org/10.1080/2150704X.2019.1686548") -> http://dx.doi.org/10.1080/2150704X.2019.1686548 | BS70: WOS:000493463300001 | BT70: =HYPERLINK("https%3A%2F%2Fwww.webofscience.com%2Fwos%2Fwoscc%2Ffull-record%2FWOS:000493463300001","View Full Record in Web of Science") -> View Full Record in Web of Science
A71: C | B71: Pettinato, S; Paloscia, S; Santi, E; Palchetti, E; De Gregorio, L; Notarnicola, C; Cuozzo, G; Marin, C; Cigna, F; Tapete, D | E71: IEEE | F71: Pettinato, S.; Paloscia, S.; Santi, E.; Palchetti, E.; De Gregorio, L.; Notarnicola, C.; Cuozzo, G.; Marin, C.; Cigna, F.; Tapete, D. | I71: MULTI-FREQUENCY SAR IMAGES FOR SWE RETRIEVAL IN ALPINE AREAS THROUGH MACHINE LEARNING APPROACHES | J71: IGARSS 2020 - 2020 IEEE INTERNATIONAL GEOSCIENCE AND REMOTE SENSING SYMPOSIUM | K71: IEEE International Symposium on Geoscience and Remote Sensing IGARSS | O71: IEEE International Geoscience and Remote Sensing Symposium (IGARSS) | P71: SEP 26-OCT 02, 2020 | Q71: ELECTR NETWORK | R71: Inst Elect & Elect Engineers,Inst Elect & Elect Engineers Geoscience & Remote Sensing Soc | V71: The characterization of snow conditions and the estimation of snow water equivalent (SWE) are the main goals of this paper, achieved through the exploitation of multi-frequency SAR data at both C- and X-bands from Sentinel-1 (S-1) and COSMO-SkyMed (CSK) satellites, respectively. Dry/wet snow conditions have first been assessed using C-band S-1 images. Subsequently, a sensitivity analysis was carried out by using datasets of in-situ snow measurements (i.e. snow depth, density, snow grain radius, temperature and wetness) collected in South Tyrol region, in north-eastern Italy. Simulations based on the Dense Medium Radiative Transfer (DMRT) forward electromagnetic model were considered to interpret and assess the experimental findings. Two retrieval algorithms for SWE estimation from X-band SAR data were implemented. These algorithms are based on machine learning approaches, i.e. Artificial Neural Networks (ANN) and Support Vector Regression (SVR). The training of the algorithms accounts for experimental data and DMRT model simulations and, then is applied to a selection of X-band CSK StripMap HIMAGE scenes collected over the test area. The results are promising, and pave the way for further analysis and validation to exploit the potential of SAR for snow parameter retrieval. | AA71: ; Cigna, Francesca/B-9173-2015; santi, emanuele/A-7755-2013; Tapete, Deodato/AAB-7528-2021; Pettinato, Simone/H-6051-2019 | AB71: Cuozzo, Giovanni/0000-0001-9120-7426; Notarnicola, Claudia/0000-0003-1968-0125; Cigna, Francesca/0000-0001-8134-1576; santi, emanuele/0000-0003-1882-6321; | AO71: 2153-6996 | AQ71: 978-1-7281-6374-1 | AU71: 2020 | BB71: 2930 | BC71: 2933 | BE71: 10.1109/IGARSS39084.2020.9323472 | BF71: =HYPERLINK("http://dx.doi.org/10.1109/IGARSS39084.2020.9323472","http://dx.doi.org/10.1109/IGARSS39084.2020.9323472") -> http://dx.doi.org/10.1109/IGARSS39084.2020.9323472 | BS71: WOS:000664335302234 | BT71: =HYPERLINK("https%3A%2F%2Fwww.webofscience.com%2Fwos%2Fwoscc%2Ffull-record%2FWOS:000664335302234","View Full Record in Web of Science") -> View Full Record in Web of Science
A72: C | B72: Santi, E; Paloscia, S; Pettinato, S; De Gregorio, L; Cuozzo, G; Jacob, A; Notarnicola, C; Cigna, F; Tapete, D | E72: IEEE | F72: Santi, Emanuele; Paloscia, Simonetta; Pettinato, Simone; De Gregorio, Ludovica; Cuozzo, Giovanni; Jacob, Alexander; Notarnicola, Claudia; Cigna, Francesca; Tapete, Deodato | I72: SWE retrieval in Alpine areas with high-resolution COSMO-SkyMed X-band SAR data using Artificial Neural Networks and Support Vector Regression techniques | J72: 2020 XXXIIIRD GENERAL ASSEMBLY AND SCIENTIFIC SYMPOSIUM OF THE INTERNATIONAL UNION OF RADIO SCIENCE | O72: 33rd General Assembly and Scientific Symposium (GASS) of the International-Union-of-Radio-Science (URSI) | P72: AUG 29-SEP 05, 2020 | Q72: Rome, ITALY | R72: Int Union Radio Sci | V72: The potential of satellite Synthetic Aperture Radar (SAR) sensors for Snow Water Equivalent (SWE) retrieval in Alpine areas is assessed in this study. X-band HH-polarized SAR backscatter from 2012-2015 images acquired by the COSMO-SkyMed constellation over the South Tyrol province in northern Italy is compared with SWE in-situ measurements and nivo-meteorological station records. The resulting relationship is compared with simulations based on the Dense Media Radiative Transfer - Quasi Mie Scattering (DMRT - QMS) model. Artificial Neural Networks (ANN) and Support Vector Regression (SVR) machine learning techniques are trained and used for SWE retrieval from COSMO-SkyMed data. Good accuracy and small computational cost are observed for both ANN and SVR. The resulting SWE maps agree with snow conditions measured in-situ. | AA72: Pettinato, Simone/H-6051-2019; Jacob, Alexander/V-8401-2019; Tapete, Deodato/AAB-7528-2021; santi, emanuele/A-7755-2013; Cigna, Francesca/B-9173-2015 | AB72: Jacob, Alexander/0000-0003-4434-7244; Notarnicola, Claudia/0000-0003-1968-0125; santi, emanuele/0000-0003-1882-6321; Cigna, Francesca/0000-0001-8134-1576; Cuozzo, Giovanni/0000-0001-9120-7426 | AQ72: 978-9-4639-6800-3 | AU72: 2020 | BE72: 10.23919/ursigass49373.2020.9232247 | BF72: =HYPERLINK("http://dx.doi.org/10.23919/ursigass49373.2020.9232247","http://dx.doi.org/10.23919/ursigass49373.2020.9232247") -> http://dx.doi.org/10.23919/ursigass49373.2020.9232247 | BS72: WOS:000632276400173 | BT72: =HYPERLINK("https%3A%2F%2Fwww.webofscience.com%2Fwos%2Fwoscc%2Ffull-record%2FWOS:000632276400173","View Full Record in Web of Science") -> View Full Record in Web of Science
A73: J | B73: Ahmad, JA; Forman, BA; Kwon, Y | F73: Ahmad, Jawairia A.; Forman, Barton A.; Kwon, Yonghwan | I73: Analyzing Machine Learning Predictions of Passive Microwave Brightness Temperature Spectral Difference Over Snow-Covered Terrain in High Mountain Asia | J73: FRONTIERS IN EARTH SCIENCE | V73: Snow is an important component of the terrestrial freshwater budget in high mountain Asia (HMA) and contributes to the runoff in Himalayan rivers through snowmelt. Despite the importance of snow in HMA, considerable spatiotemporal uncertainty exists across the different estimates of snow water equivalent for this region. In order to better estimate snow water equivalent, radiative transfer models are often used in conjunction with microwave brightness temperature measurements. In this study, the efficacy of support vector machines (SVMs), a machine learning technique, to predict passive microwave brightness temperature spectral difference (Delta Tb) as a function of geophysical variables (snow water equivalent, snow depth, snow temperature, and snow density) is explored through a sensitivity analysis. The use of machine learning (as opposed to radiative transfer models) is a relatively new and novel approach for improving snow water equivalent estimates. The Noah-MP land surface model within the NASA Land Information System framework is used to simulate the hydrologic cycle over HMA and model geophysical variables that are then used for SVM training. The SVMs serve as a nonlinear map between the geophysical space (modeled in Noah-MP) and the observation space (Delta Tb as measured by the radiometer). Advanced Microwave Scanning Radiometer-Earth Observing System measured passive microwave brightness temperatures over snow-covered locations in the HMA region are used as training data during the SVM training phase. Sensitivity of well-trained SVMs to each Noah-MP modeled state variable is assessed by computing normalized sensitivity coefficients. Sensitivity analysis results generally conform with the known first-order physics. Input states that increase volume scattering of microwave radiation, such as snow density and snow water equivalent, exhibit a plurality of positive normalized sensitivity coefficients. In general, snow temperature was the most sensitive input to the SVM predictions. The sensitivity of each state is location and time dependent. The signs of normalized sensitivity coefficients that indicate physical irrationality are ascribed to significant cross-correlation between Noah-MP simulated states and decreased SVM prediction capability at specific locations due to insufficient training data. SVM prediction pitfalls do exist that serve to highlight the limitations of this particular machine learning algorithm. | AA73: Forman, Barton A/I-2227-2012 | AB73: Forman, Barton A/0000-0001-6410-9978; Ahmad, Jawairia/0000-0003-2953-9360 | AP73: 2296-6463 | AT73: AUG 20 | AU73: 2019 | AV73: 7 | BD73: 212 | BE73: 10.3389/feart.2019.00212 | BF73: =HYPERLINK("http://dx.doi.org/10.3389/feart.2019.00212","http://dx.doi.org/10.3389/feart.2019.00212") -> http://dx.doi.org/10.3389/feart.2019.00212 | BS73: WOS:000481868600002 | BT73: =HYPERLINK("https%3A%2F%2Fwww.webofscience.com%2Fwos%2Fwoscc%2Ffull-record%2FWOS:000481868600002","View Full Record in Web of Science") -> View Full Record in Web of Science
A74: C | B74: De Gregorio, L; Cigna, F; Cuozzo, G; Jacob, A; Paloscia, S; Pettinato, S; Santi, E; Tapete, D; Bruzzone, L; Notarnicola, C | D74: Bovenga, F; Notarnicola, C; Pierdicca, N; Santi, E | F74: De Gregorio, Ludovica; Cigna, Francesca; Cuozzo, Giovanni; Jacob, Alexander; Paloscia, Simonetta; Pettinato, Simone; Santi, Emanuele; Tapete, Deodato; Bruzzone, Lorenzo; Notarnicola, Claudia | I74: SWE retrieval by exploiting COSMO-SkyMed X-band SAR imagery and ground data through a machine learning approach | J74: ACTIVE AND PASSIVE MICROWAVE REMOTE SENSING FOR ENVIRONMENTAL MONITORING III | K74: Proceedings of SPIE | O74: Conference on Active and Passive Microwave Remote Sensing for Environmental Monitoring III | P74: SEP 11-12, 2019 | Q74: Strasbourg, FRANCE | R74: SPIE | V74: The main objective of this work is to estimate Snow Water Equivalent (SWE) by jointly exploiting the information derived from X-band Synthetic Aperture Radar (SAR) imagery acquired by the Italian Space Agency COSMO-SkyMed satellite constellation in StripMap HIMAGE mode and manual SWE ground measurements. The idea is to verify the sensitivity of the backscattering coefficient at X-band to the SWE and, by means of a Support Vector Regression (SVR) algorithm, to estimate the SWE for the South Tyrol region, north-eastern Italy. The regressor is trained by exploiting about 1,000 simulated backscattering coefficients corresponding to different snowpack conditions, obtained with a theoretical model based on the Dense Media Radiative Transfer theory - Quasi-crystalline approximation Mie scattering of Sticky spheres (DMRT-QMS). Then, the performance is evaluated on the backscattering values derived from COSMO-SkyMed satellite images and using the corresponding ground measurements of SWE as references. The results show a correlation coefficient equal to 0.6, a bias of 10.5 mm and a RMSE of 51.8 mm between estimated SWE values and ground measurements. The limited performance could be related to the DMRT-QMS theoretical model used for the simulations that results to be very sensitive to snow grain size and may have generated a training dataset only partially representative of satellite derived backscattering coefficients used for testing the algorithm. | AA74: Pettinato, Simone/H-6051-2019; Bruzzone, Lorenzo/JPL-7703-2023; Cigna, Francesca/B-9173-2015; Jacob, Alexander/V-8401-2019; Tapete, Deodato/AAB-7528-2021; santi, emanuele/A-7755-2013 | AB74: Cigna, Francesca/0000-0001-8134-1576; Jacob, Alexander/0000-0003-4434-7244; Notarnicola, Claudia/0000-0003-1968-0125; Tapete, Deodato/0000-0002-7242-4473; santi, emanuele/0000-0003-1882-6321; Cuozzo, Giovanni/0000-0001-9120-7426 | AO74: 0277-786X | AP74: 1996-756X | AQ74: 978-1-5106-3011-6; 978-1-5106-3012-3 | AU74: 2019 | AV74: 11154 | BD74: UNSP 111540M | BE74: 10.1117/12.2550824 | BF74: =HYPERLINK("http://dx.doi.org/10.1117/12.2550824","http://dx.doi.org/10.1117/12.2550824") -> http://dx.doi.org/10.1117/12.2550824 | BS74: WOS:000511150300005 | BT74: =HYPERLINK("https%3A%2F%2Fwww.webofscience.com%2Fwos%2Fwoscc%2Ffull-record%2FWOS:000511150300005","View Full Record in Web of Science") -> View Full Record in Web of Science
